Workbook

Sheet Cópia de Extração
A1: LLM1: CHATGPT
A2: LLM2: GEMINI
A3: ID do artigo | B3: Tipo de publicação | C3: Local de publicação | D3: Título | E3: Link | F3: Ano | G3: Autores | H3: País | I3: Base de Dados | J3: RQ (Pergunta de Pesquisa) | K3: Extração LLM 1 (ChatGPT) | L3: Extração LLM 2 (Gemini) | M3: Extração validada (humana) | N3: ChatGPT acertou? | O3: Gemini acertou? | P3: Concordância entre LLMs | Q3: Observações / Comentários
A4: ES01 | B4: Journal | C4: Biological Psychology | D4: Effects of working memory training on EEG, cognitive performance, and self-report indices potentially relevant for social anxiety | E4: PubMed | F4: 2020 | G4: Xin Zhao, Chen Dang, Joseph H R Maes | I4: PubMed | J4: RQ1 | K4: <<Texto extraído da IA>> | L4: <<Texto extraído da IA>> | P4: =IF(OR(N4="",O4=""),"",IF(N4=O4,"Igual","Diferente"))
A5: ES02 | B5: Journal | C5: international psychogeriatrics | D5: Effects of repetitive paired associative stimulation on brain plasticity and working memory in Alzheimer's disease: a pilot randomized double-blind-controlled trial | E5: PubMed | F5: 2020 | G5: Sanjeev Kumar, Reza Zomorrodi, Zaid Ghazala, Michelle S Goodman, Daniel M Blumberger, Zafiris J Daskalakis, Corinne E Fischer, Benoit H Mulsant, Bruce G Pollock, Tarek K Rajji | I5: PubMed | J5: RQ2 | P5: =IF(OR(N5="",O5=""),"",IF(N5=O5,"Igual","Diferente"))
A6: ES03 | B6: Journal | C6: Schizophrenia Research: Cognition | D6: The aperiodic and periodic activities of EEG dynamically relate with cognitive performance in schizophrenia | E6: PubMed | F6: 2025 | G6: Kexin Zhang, Yunfei Ji, Xiaodong Guo, Tianqi Gao, Xuemin Zhang, Xin Yu, Jing Wang | I6: PubMed | J6: RQ3 | P6: =IF(OR(N6="",O6=""),"",IF(N6=O6,"Igual","Diferente"))
A7: ES04 | D7: Psilocybin-assisted neurofeedback for the improvement of executive functions: a randomized... feasibility study | E7: 10.1098/rstb.2023.0095 | F7: 2024 | G7: Enriquez-Geppert S, et al. | I7: PubMed | J7: RQ4 | P7: =IF(OR(N7="",O7=""),"",IF(N7=O7,"Igual","Diferente"))
A8: ES05 | B8: Journal | C8: Sensors (Basel) | D8: Investigating the Impact of Guided Imagery on Stress, Brain Functions, and Attention: A Randomized Trial | E8: 10.3390/s23136210 | F8: 2023 | G8: Zemla K, et al. | I8: PubMed | J8: RQ5 | P8: =IF(OR(N8="",O8=""),"",IF(N8=O8,"Igual","Diferente"))
A9: ES06 | B9: Journal | C9: Journal of Affective Disorders | D9: Subanesthetic ketamine alters EEG signal complexity: Implications for treatment stratification in depression | E9: 10.1016/j.jad.2025.119477 | F9: 2025 | G9: Chan WL, et al. | I9: PubMed | J9: RQ6 | P9: =IF(OR(N9="",O9=""),"",IF(N9=O9,"Igual","Diferente"))
A10: ES07 | B10: Journal | C10: JMIR Ment Health | D10: Design and Implementation of a Brief Digital Mindfulness and Compassion Training App...: Cluster Randomized Controlled Trial | E10: 10.2196/49467 | F10: 2024 | G10: Jaiswal S, et al. | I10: PubMed | J10: RQ7 | P10: =IF(OR(N10="",O10=""),"",IF(N10=O10,"Igual","Diferente"))
A11: ES08 | B11: Journal | C11: Scientific Reports | D11: Feasibility of a novel neurofeedback system: a parallel randomized single-blinded pilot study | E11: 10.1038/s41598-023-44545-1 | F11: 2023 | G11: Horváth D, et al. | I11: PubMed | J11: RQ8 | P11: =IF(OR(N11="",O11=""),"",IF(N11=O11,"Igual","Diferente"))
A12: ES09 | B12: Journal | C12: Human Psychopharmacol | D12: Comprehensive Mitigation of Peripheral and Central Stress Responses by Nx4: Insights From EEG and Heart Rate Variability... | E12: 10.1002/hup.70020 | F12: 2025 | G12: Krylova M, et al. | I12: PubMed | J12: RQ9 | P12: =IF(OR(N12="",O12=""),"",IF(N12=O12,"Igual","Diferente"))
A13: ES10 | B13: Journal | C13: Biological Psychology | D13: Effects of working memory training on EEG, cognitive performance, and self-report indices potentially relevant for social anxiety | E13: https://doi.org/10.1016/j.biopsycho.2019.107840 | F13: 2020 | G13: Zhao, Xin; Dang, Chen; Maes, Joseph H.R. | I13: Science Direct | P13: =IF(OR(N13="",O13=""),"",IF(N13=O13,"Igual","Diferente"))
A14: ES11 | B14: Journal | C14: Neuroscience Letters | D14: Investigation of the effects of transcranial direct current stimulation and neurofeedback by continuous performance test | E14: https://doi.org/10.1016/j.neulet.2019.134648 | F14: 2020 | G14: Guleken, Zozan; Eskikurt, Gökçer; Karamürsel, Sacit | I14: Science Direct | P14: =IF(OR(N14="",O14=""),"",IF(N14=O14,"Igual","Diferente"))
A15: ES12 | B15: Journal | C15: NeuroImage: Clinical | D15: Real-time fMRI neurofeedback amygdala training may influence kynurenine pathway metabolism in major depressive disorder | E15: https://doi.org/10.1016/j.nicl.2021.102559 | F15: 2021 | G15: Tsuchiyagaito, Aki; Smith, Jared L.; El-Sabbagh, Nour; Zotev, Vadim; Misaki, Masaya; Al Zoubi, Obada; Kent Teague, T.; Paulus, Martin P.; Bodurka, Jerzy; Savitz, Jonathan | I15: Science Direct | P15: =IF(OR(N15="",O15=""),"",IF(N15=O15,"Igual","Diferente"))
A16: ES13 | B16: Journal | C16: JMIR Ment Health | D16: Design and Implementation of a Brief Digital Mindfulness and Compassion Training App for Health Care Professionals: Cluster Randomized Controlled Trial | E16: https://doi.org/10.2196/49467 | F16: 2024 | G16: Jaiswal, Satish; Purpura, Suzanna R; Manchanda, James K; Nan, Jason; Azeez, Nihal; Ramanathan, Dhakshin; Mishra, Jyoti | I16: Science Direct | P16: =IF(OR(N16="",O16=""),"",IF(N16=O16,"Igual","Diferente"))
A17: ES14 | B17: Journal | C17: Brain Simulation | D17: Daily prefrontal closed-loop repetitive transcranial magnetic stimulation (rTMS) produces progressive EEG quasi-alpha phase entrainment in depressed adults | E17: https://doi.org/10.1016/j.brs.2022.02.008 | F17: 2022 | G17: Faller, Josef; Doose, Jayce; Sun, Xiaoxiao; Mclntosh, James R.; Saber, Golbarg T.; Lin, Yida; Teves, Joshua B.; Blankenship, Aidan; Huffman, Sarah; Goldman, Robin I.; George, Mark S.; Brown, Truman R.; Sajda, Paul | I17: Science Direct | P17: =IF(OR(N17="",O17=""),"",IF(N17=O17,"Igual","Diferente"))
A18: ES15 | D18: Preliminary Real-World Evidence Supporting the Efficacy of a Remote Neurofeedback System in Improving Mental Health: Retrospective Single-Group Pretest-Posttest Study | E18: https://doi.org/10.2196/35636 | F18: 2022 | G18: Whitehead, Jocelyne C; Neeman, Ron; Doniger, Glen M | I18: Science Direct | P18: =IF(OR(N18="",O18=""),"",IF(N18=O18,"Igual","Diferente"))
A19: ES16 | D19: Advancing Posttraumatic Stress Disorder Diagnosis and the Treatment of Trauma in Humanitarian Emergencies via Mobile Health: Protocol for a Proof-of-Concept Nonrandomized Controlled Trial | E19: https://doi.org/10.2196/38223 | F19: 2022 | G19: Pinto, Janaina V; Hunt, Caroline; O'Toole, Brian | I19: Science Direct | P19: =IF(OR(N19="",O19=""),"",IF(N19=O19,"Igual","Diferente"))
A20: ES17 | D20: Neuromodulation-Assisted Psychotherapy: Can Transcranial Magnetic Stimulation Increase The Efficacy Of Acceptance And Commitment Therapy For Comorbid Chronic Pain And Depression? | E20: https://doi.org/10.1016/j.jpain.2023.02.188 | F20: 2023 | G20: Tynan, Mara; Martinez, Erica; Chu, Gage; Ramanathan, Dhakshin; Herbert, Matthew S. | I20: Science Direct | P20: =IF(OR(N20="",O20=""),"",IF(N20=O20,"Igual","Diferente"))
A21: ES18 | D21: Individualized Spectral Features in First-Episode and Drug-Naïve Major Depressive Disorder: Insights From Periodic and Aperiodic Electroencephalography Analysis | E21: https://doi.org/10.1016/j.bpsc.2024.12.014 | F21: 2025 | G21: Li, Jiaxin; Xiong, Dongsheng; Gao, Chenyang; Huang, Yuanyuan; Li, Zhaobo; Zhou, Jing; Ning, Yuping; Wu, Fengchun; Wu, Kai | I21: Science Direct | P21: =IF(OR(N21="",O21=""),"",IF(N21=O21,"Igual","Diferente"))
A22: ES19 | D22: Effects of high carbon dioxide concentration on emotional processing: Based on multimodal evidence | E22: https://doi.org/10.1016/j.buildenv.2024.111434 | F22: 2024 | G22: Yang, Li; Zhang, Jiaxing; Yang, Yukai; Wang, Nan; Zhang, Zhen; Chen, Liqun | I22: Science Direct | P22: =IF(OR(N22="",O22=""),"",IF(N22=O22,"Igual","Diferente"))
A23: ES20 | D23: Rationale and study design of a trial to assess rTMS add-on value for the amelioration of negative symptoms of schizophrenia (RADOVAN) | E23: https://doi.org/10.1016/j.conctc.2022.100891 | F23: 2022 | G23: Hebel, T.; Langguth, B.; Schecklmann, M.; Schoisswohl, S.; Staudinger, S.; Schiller, A.; Ustohal, L.; Sverak, T.; Horky, M.; Kasparek, T.; Skront, T.; Hyza, M.; Poeppl, T.B.; Riester, M.L.; Schwemmer, L.; Zimmermann, S.; Sakreida, K. | I23: Science Direct | P23: =IF(OR(N23="",O23=""),"",IF(N23=O23,"Igual","Diferente"))
A24: ES21 | D24: Combined EEG-tDCS approach in resting state to reduce comorbid anxiety and depressive symptoms in affective disorders: A sham-controlled pilot study | E24: https://doi.org/10.1016/j.ibneur.2024.04.007 | F24: 2024 | G24: Couto, Tania A.; Gao, Fei; Lak, Davis C.; Yuan, Zhen | I24: Science Direct | P24: =IF(OR(N24="",O24=""),"",IF(N24=O24,"Igual","Diferente"))
A25: ES22 | D25: Binaural sound therapy for tinnitus treatment: A psychometric and neurophysiological evaluation | E25: https://doi.org/10.1016/j.amjoto.2021.103248 | F25: 2022 | G25: Ibarra-Zarate, David I.; Naal-Ruiz, Norberto E.; Alonso-Valerdi, Luz María | I25: Science Direct | P25: =IF(OR(N25="",O25=""),"",IF(N25=O25,"Igual","Diferente"))
A26: ES23 | D26: EEG Based Evaluation of Examination Stress and Test Anxiety Among College Students | E26: https://doi.org/10.1016/j.irbm.2021.06.011 | F26: 2022 | G26: Rajendran, V.G.; Jayalalitha, S.; Adalarasu, K. | I26: Science Direct | P26: =IF(OR(N26="",O26=""),"",IF(N26=O26,"Igual","Diferente"))
A27: ES24 | D27: A qualitative analysis of participant experience during an EEG-linked auditory targeted cognitive training exercise: Implications for implementation and protocol optimization | E27: https://doi.org/10.1016/j.psychres.2024.116254 | F27: 2024 | G27: Conroy, Carmen; Li, Francesca; Sprock, Joyce; Rabin, Borsika A.; Joshi, Yash B. | I27: Science Direct | P27: =IF(OR(N27="",O27=""),"",IF(N27=O27,"Igual","Diferente"))
A28: ES25 | D28: Chapter Five - The complex associations between adiposity, fitness, mental wellbeing and neurocognitive function after exercise: A randomized crossover trial in preadolescent children | E28: https://doi.org/10.1016/bs.pbr.2023.11.004 | F28: 2024 | G28: Logan, Nicole E.; Occidental, Nicole; Watrous, Jennifer N.H.; Lloyd, Katherine M.; Raine, Lauren B.; Kramer, Arthur F.; Hillman, Charles H. | I28: Science Direct | P28: =IF(OR(N28="",O28=""),"",IF(N28=O28,"Igual","Diferente"))
A29: ES26 | D29: Subanesthetic ketamine alters EEG signal complexity: Implications for treatment stratification in depression | E29: https://doi.org/10.1016/j.jad.2025.119477 | F29: 2025 | G29: Chan, Weng-Lam; Olbrich, Sebastian; Jiang, Xinwen; Zhang, Haoyun; Ip, Cheng-Teng; Brunovsky, Martin | I29: Science Direct | P29: =IF(OR(N29="",O29=""),"",IF(N29=O29,"Igual","Diferente"))
A30: ES27 | D30: BCI Facilitates the Improvement of Cognitive Functions in Children and Elderly | E30: https://ieeexplore.ieee.org/document/9061625 | F30: 2020 | G30: Cuntai Guan; Choon Guan Lim; Daniel Fung; Helen Juan Zhou; Ranga Krishnan; Tih Shih Lee | I30: IEEE Explore | P30: =IF(OR(N30="",O30=""),"",IF(N30=O30,"Igual","Diferente"))
A31: ES28 | D31: Closed-Loop Individual Music Neurofeedback Based on Brain-Computer Interaction for Student Stress Intervention | E31: https://ieeexplore.ieee.org/document/10973423 | F31: 2024 | G31: Mengxuan Hu; Jingxi Zhang; Guangying Pei; Tianyi Yan | I31: IEEE Explore | P31: =IF(OR(N31="",O31=""),"",IF(N31=O31,"Igual","Diferente"))
A32: ES29 | D32: The Role of Non-Invasive Neural Devices in Modern Neurorehabilitation and Mental Health Treatment | E32: https://ieeexplore.ieee.org/document/11013597 | F32: 2025 | G32: Adesh Pawar; Palash Gourshettiwar; Pradnyawant M. Gote; Vishal Kumar Choudhary; Prajyot Yesankar; Shrikant Khadse | I32: IEEE Explore | P32: =IF(OR(N32="",O32=""),"",IF(N32=O32,"Igual","Diferente"))
A33: ES30 | D33: Automated Generated Binaural Beats Using EEG: A User-Friendly Auditory Brain-Computer Interface | E33: https://ieeexplore.ieee.org/stamp/stamp.jsp?arnumber=9645921 | F33: 2021 | G33: S. Negi; R. Jain; S. Saboo; S. Kwatra | I33: IEEE Explore | P33: =IF(OR(N33="",O33=""),"",IF(N33=O33,"Igual","Diferente"))
A34: ES31 | D34: EEG-Driven Massage Headband For Anxiety Alleviation | E34: https://ieeexplore.ieee.org/stamp/stamp.jsp?arnumber=11013104 | F34: 2025 | G34: K. Sravani; S. Nadipineni; B. Anjali; C. Vedavathi; B. Ramya | I34: IEEE Explore | P34: =IF(OR(N34="",O34=""),"",IF(N34=O34,"Igual","Diferente"))
A35: ES32 | D35: Using Generative AI for Neurofeedback Content Personalization | E35: https://ieeexplore.ieee.org/stamp/stamp.jsp?arnumber=11036309 | F35: 2025 | G35: T. L. Shuler; D. A. Ostrowski | I35: IEEE Explore | P35: =IF(OR(N35="",O35=""),"",IF(N35=O35,"Igual","Diferente"))
A36: ES33 | D36: Closed-Loop Individual Music Neurofeedback Based on Brain-Computer Interaction for Student Stress Intervention | E36: https://ieeexplore.ieee.org/stamp/stamp.jsp?arnumber=10973423 | F36: 2024 | G36: M. Hu; J. Zhang; G. Pei; T. Yan | I36: IEEE Explore | P36: =IF(OR(N36="",O36=""),"",IF(N36=O36,"Igual","Diferente"))
A37: ES34 | D37: Research on Optimization Model of Cognitive Enhancement Algorithm in Intelligent Data Analysis System | E37: https://ieeexplore.ieee.org/stamp/stamp.jsp?arnumber=10835027 | F37: 2024 | G37: L. Tao; D. Xinyue; L. Yongjuan; L. Guangfu | I37: IEEE Explore | P37: =IF(OR(N37="",O37=""),"",IF(N37=O37,"Igual","Diferente"))
A38: ES35 | D38: The Role of Non-Invasive Neural Devices in Modern Neurorehabilitation and Mental Health Treatment | E38: https://ieeexplore.ieee.org/stamp/stamp.jsp?arnumber=11013597 | F38: 2025 | G38: A. Pawar; P. Gourshettiwar; P. M. Gote; V. K. Choudhary; P. Yesankar; S. Khadse | I38: IEEE Explore | P38: =IF(OR(N38="",O38=""),"",IF(N38=O38,"Igual","Diferente"))
A39: ES36 | D39: Real-Time Attention Regulation and Cognitive Monitoring Using a Wearable EEG-Based BCI | E39: https://ieeexplore.ieee.org/stamp/stamp.jsp?arnumber=10694718 | F39: 2025 | G39: H. Huang; J. Chen; J. Xiao; D. Chen; J. Zhang; J. Pan; Y. Li | I39: IEEE Explore | P39: =IF(OR(N39="",O39=""),"",IF(N39=O39,"Igual","Diferente"))
A40: ES37 | D40: Brain Wave Response of Style Geometry in Artistic Creation in VR Environments: an Impact Study on Cognitive Function and Mental Health of Autistic Children | E40: https://ieeexplore.ieee.org/stamp/stamp.jsp?arnumber=10686974 | F40: 2024 | G40: G. Peng; W. Y. Leong | I40: IEEE Explore | P40: =IF(OR(N40="",O40=""),"",IF(N40=O40,"Igual","Diferente"))
A41: ES38 | D41: Effect of Alpha Wave-Containing Music on the Psychological Stress Level of Hospital Staffs and their Cognitive Performance | E41: https://ieeexplore.ieee.org/stamp/stamp.jsp?arnumber=9510421 | F41: 2021 | G41: T. V. Quang Thinh; N. Lam Quang; A. H. Minh Anh; T. Hoang Long; N. T. Hieu; T. Van Luan; N. T. Kien; T. Tien Tai; H. H. Truong Giang; V. Van Toi; H. T. Thanh Huong | I41: IEEE Explore | P41: =IF(OR(N41="",O41=""),"",IF(N41=O41,"Igual","Diferente"))
... A86: ES83 | D86: Virtual agents for studying the effect of emotional feedback on motor learning- A feasibility study | E86: https://dl.acm.org/doi/10.1145/3652988.3673922 | F86: 2024 | G86: Tal Krasovsky, Michal Kafri, Moshe H. Aharoni e Arik Cheshin. | I86: IEEE Explore | P86: =IF(OR(N86="",O86=""),"",IF(N86=O86,"Igual","Diferente"))
A87: ES84 | D87: Cognitive efficiency in VR simulated natural indoor environments examined through EEG and affective responses | E87: https://www.scopus.com/inward/record.uri?eid=2-s2.0-105017610930&doi=10.1038%2Fs41598-025-18629-z&partnerID=40&md5=3252dd909bd5f6250b844de4f2bd7603 | F87: 2025 | G87: Kim, S. | I87: ACM | P87: =IF(OR(N87="",O87=""),"",IF(N87=O87,"Igual","Diferente"))
A88: ES85 | D88: EEG-Based Neurophysiological Responses to Classroom Window Views in Green Campus Settings | E88: https://www.scopus.com/inward/record.uri?eid=2-s2.0-105017554919&doi=10.15627%2Fjd.2025.23&partnerID=40&md5=2d2040446bbb14128eb910c301914334 | F88: 2025 | G88: Binarti, F.; Sekarlangi, N.; Brilianto, M.K.V.; Hakim, B.R. | I88: ACM | P88: =IF(OR(N88="",O88=""),"",IF(N88=O88,"Igual","Diferente"))
A89: ES86 | D89: The effect of sports on mental performance according to skill types in youth athletes | E89: https://www.scopus.com/inward/record.uri?eid=2-s2.0-105015480737&doi=10.1186%2Fs13102-025-01320-1&partnerID=40&md5=e65b50281140b1d4a2430b3ca00ac857 | F89: 2025 | G89: Alagöz, I.; Demirkan, E.; Özkadı, T.; Yildirim, T. | I89: ACM | P89: =IF(OR(N89="",O89=""),"",IF(N89=O89,"Igual","Diferente"))
A90: ES87 | D90: Enhancing Working Memory and Reducing Anxiety in University Students: A Neurofeedback Approach | E90: https://www.scopus.com/inward/record.uri?eid=2-s2.0-85196905848&doi=10.3390%2Fbrainsci14060578&partnerID=40&md5=1fcca2cf66842726ed1a3907e0adaa35 | F90: 2024 | G90: Diotaiuti, P.; Valente, G.; Corrado, S.; Tosti, B.; Carissimo, C.; Di Libero, T.; Cerro, G.; Rodio, A.; Mancone, S. | I90: Scopus | P90: =IF(OR(N90="",O90=""),"",IF(N90=O90,"Igual","Diferente"))
A91: ES88 | D91: Investigating the Relationship between Noise Exposure and Human Cognitive Performance: Attention, Stress, and Mental Workload Based on EEG Signals Using Power Spectrum Density | E91: https://www.scopus.com/inward/record.uri?eid=2-s2.0-85192452023&doi=10.3390%2Fapp14072699&partnerID=40&md5=4821853b1a3bb0bba375347e70ba6c98 | F91: 2024 | G91: Astuti, R.D.; Suhardi, B.; Laksono, P.W.; Susanto, N. | I91: Scopus | P91: =IF(OR(N91="",O91=""),"",IF(N91=O91,"Igual","Diferente"))
A92: ES89 | D92: The Impact of Light Conditions on Neural Affect Classification: A Deep Learning Approach | E92: https://www.scopus.com/inward/record.uri?eid=2-s2.0-85188915840&doi=10.3390%2Fmake6010011&partnerID=40&md5=a4debee62344f1c1a08d2ea33ce45ee2 | F92: 2024 | G92: Zentner, S.; Chacón, A.; Wriessnegger, S.C. | I92: Scopus | P92: =IF(OR(N92="",O92=""),"",IF(N92=O92,"Igual","Diferente"))
A93: ES90 | D93: Evaluating Deep Learning with different feature scaling techniques for EEG-based Music Entrainment Brain Computer Interface | E93: https://www.scopus.com/inward/record.uri?eid=2-s2.0-85183991218&doi=10.1016%2Fj.prime.2024.100448&partnerID=40&md5=c808a8a78749760a1ba0294131bbc596 | F93: 2024 | G93: Rashmi, R.; Shantala, D.S. | I93: Scopus | P93: =IF(OR(N93="",O93=""),"",IF(N93=O93,"Igual","Diferente"))
A94: ES91 | D94: Neuroplasticity of the left dorsolateral prefrontal cortex in patients with treatment-resistant depression as indexed with paired associative stimulation: a TMS–EEG study | E94: https://www.scopus.com/inward/record.uri?eid=2-s2.0-85184013375&doi=10.1093%2Fcercor%2Fbhad515&partnerID=40&md5=b50616f30bb750d1e489a441ead98181 | F94: 2024 | G94: Kaneko, N.; Wada, M.; Nakajima, S.; Takano, M.; Taniguchi, K.; Honda, S.; Mimura, M.; Noda, Y. | I94: Scopus | P94: =IF(OR(N94="",O94=""),"",IF(N94=O94,"Igual","Diferente"))
A95: ES92 | D95: Assessment of driver fatigue-related brain responses and causal factors during driving under different traffic conditions | E95: https://www.scopus.com/inward/record.uri?eid=2-s2.0-85204294626&doi=10.3389%2Ffams.2024.1426253&partnerID=40&md5=8550b39c85a699289128d33a68752a5e | F95: 2024 | G95: Adachi, M.; Nobukawa, S.; Inagaki, K. | I95: Scopus | P95: =IF(OR(N95="",O95=""),"",IF(N95=O95,"Igual","Diferente"))
A96: ES93 | D96: Does emotional valence affect cognitive performance and neurophysiological response during decision making? A preliminary study | E96: https://www.scopus.com/inward/record.uri?eid=2-s2.0-85201819430&doi=10.3389%2Ffnins.2024.1408526&partnerID=40&md5=ed80d6785dced9ffebc3dacfd1670549 | F96: 2024 | G96: Balconi, M.; Rovelli, K. | I96: Scopus | P96: =IF(OR(N96="",O96=""),"",IF(N96=O96,"Igual","Diferente"))
A97: ES94 | D97: Prolonged Disease Course Leads to Impaired Brain Function in Anxiety Disorder: A Resting State EEG Study | E97: https://www.scopus.com/inward/record.uri?eid=2-s2.0-85200670789&doi=10.2147%2FNDT.S458106&partnerID=40&md5=1972d361ba2a9e545cee88afc0510482 | F97: 2024 | G97: Mou, S.; Yan, S.; Shen, S.; Shuai, Y.; Li, G.; Shen, Z.; Shen, P. | I97: Scopus | P97: =IF(OR(N97="",O97=""),"",IF(N97=O97,"Igual","Diferente"))
A98: ES95 | D98: Mental stress recognition on the fly using neuroplasticity spiking neural networks | E98: https://www.scopus.com/inward/record.uri?eid=2-s2.0-85170370500&doi=10.1038%2Fs41598-023-34517-w&partnerID=40&md5=362ab7b02d354b47c378873f5c2e286d | F98: 2023 | G98: Weerasinghe, M.M.A.; Wang, G.; Whalley, J.; Crook-Rumsey, M. | I98: Scopus | P98: =IF(OR(N98="",O98=""),"",IF(N98=O98,"Igual","Diferente"))
... A123: ES120 | D123: Prediction of Cognitive Decline in Temporal Lobe Epilepsy and Mild Cognitive Impairment by EEG, MRI, and Neuropsychology | E123: https://www.scopus.com/inward/record.uri?eid=2-s2.0-85085956389&doi=10.1155%2F2020%2F8915961&partnerID=40&md5=ecb644f72797038c854b2152a84deed9 | F123: 2020 | G123: Höller, Y.; Butz, K.H.G.; Thomschewski, A.C.; Schmid, E.V.; Hofer, C.D.; Uhl, A.; Bathke, A.C.; Staffen, W.; Nardone, R.; Schwimmbeck, F.; Leitinger, M.; Kuchukhidze, G.; Derner, M.; Fell, J.; Trinka, E. | I123: Scopus | P123: =IF(OR(N123="",O123=""),"",IF(N123=O123,"Igual","Diferente"))
P124: =IF(OR(N124="",O124=""),"",IF(N124=O124,"Igual","Diferente"))
P125: =IF(OR(N125="",O125=""),"",IF(N125=O125,"Igual","Diferente"))
P126: =IF(OR(N126="",O126=""),"",IF(N126=O126,"Igual","Diferente"))
P127: =IF(OR(N127="",O127=""),"",IF(N127=O127,"Igual","Diferente"))
P128: =IF(OR(N128="",O128=""),"",IF(N128=O128,"Igual","Diferente"))
P129: =IF(OR(N129="",O129=""),"",IF(N129=O129,"Igual","Diferente"))
P130: =IF(OR(N130="",O130=""),"",IF(N130=O130,"Igual","Diferente"))
P131: =IF(OR(N131="",O131=""),"",IF(N131=O131,"Igual","Diferente"))
P132: =IF(OR(N132="",O132=""),"",IF(N132=O132,"Igual","Diferente"))
P133: =IF(OR(N133="",O133=""),"",IF(N133=O133,"Igual","Diferente"))
P134: =IF(OR(N134="",O134=""),"",IF(N134=O134,"Igual","Diferente"))
P135: =IF(OR(N135="",O135=""),"",IF(N135=O135,"Igual","Diferente"))
... P995: =IF(OR(N995="",O995=""),"",IF(N995=O995,"Igual","Diferente"))

Sheet Cópia de Extração 1
A1: LLM1: CHATGPT
A2: LLM2: GEMINI
A3: ID do artigo | B3: Tipo de publicação | C3: Citação | D3: Local de publicação | E3: Título | F3: Link | G3: Ano | H3: Autores | I3: País | J3: Área de estudo | K3: Base de Dados | L3: RQ (Pergunta de Pesquisa) | M3: Extração LLM 1 (ChatGPT) | N3: Extração LLM 2 (Gemini) | O3: Extração validada (humana) | P3: ChatGPT acertou? | Q3: Gemini acertou? | R3: Concordância entre LLMs | S3: Observações / Comentários
A4: ES01 | B4: Journal | C4: Zhao X, Dang C, Maes JHR. Effects of working memory training on EEG, cognitive performance, and self-report indices potentially relevant for social anxiety. Biol Psychol. 2020 Feb;150:107840. doi: 10.1016/j.biopsycho.2019.107840. Epub 2020 Jan 2. PMID: 31904404. | D4: Biological Psychology | E4: Effects of working memory training on EEG, cognitive performance, and self-report indices potentially relevant for social anxiety | F4: PubMed | G4: 2020 | H4: Xin Zhao, Chen Dang, Joseph H R Maes | I4: China | J4: Psicologia Cognitiva | K4: PubMed | L4: RQ1 | M4: RQ1 — Excerpt: “No evidence found.” | Explanation: The article does not mention any Brain-Computer Interfaces (invasive, non-invasive, or hybrid). It focuses exclusively on working memory training and EEG as a measurement tool, not as a BCI. | N4: RQ1 — Excerpt: “No evidence found.” | Explanation: The article is a specific experimental study on Working Memory training using EEG/ERPs as measurement tools and does not review or categorize the types of Brain-Computer Interfaces (invasive, non-invasive, hybrid) most used in general mental health applications. | O4: Este artigo não trata diretamente de BCIs. Ele aborda treinamento de memória de trabalho (WM training) e medidas de EEG/ERP em estudantes com sintomas de ansiedade social. Portanto, não responde à RQ1. | P4: Sim | Q4: Sim | R4: =IF(OR(P4="",Q4=""),"",IF(P4=Q4,"Igual","Diferente")) -> Igual | S4: As respostas das duas LLMs apresentam alta concordância tanto no trecho citado quanto na explicação. Trecho citado (Excerpt): Ambas indicam “No evidence found.”, mostrando total acordo na conclusão sobre a ausência de informações relevantes no artigo quanto a BCIs. Explicação (Explanation): As duas LLMs apontam que o artigo foca em treinamento de memória de trabalho usando EEG como ferramenta de medida, e não em BCIs. A diferença está no detalhamento: a segunda (Gemini) menciona explicitamente ERPs e enfatiza que o artigo não revisa ou categoriza os tipos de BCIs em aplicações gerais de saúde mental.
I5: Netherlands | L5: RQ2 | M5: RQ2 — Excerpt: “No evidence found.” | Explanation: The study examines only social anxiety and does not reference other mental disorders in the context of BCI usage, nor does it discuss BCIs at all. | N5: RQ2 — Excerpt: “No evidence found.” | Explanation: The study focuses exclusively on Social Anxiety (SA) and does not provide a review or comparison of which mental disorders (such as depression, anxiety, schizophrenia, ADHD) have received the most attention in research involving BCIs. | O5: O artigo foca especificamente em ansiedade sociall. Trecho que destaca isso: “Social anxiety (SA) is quite common and associated with multiple comorbidities. Here, we examined the effects of working memory (WM) training on various indices potentially related to SA.” | P5: Sim | Q5: Sim | R5: =IF(OR(P5="",Q5=""),"",IF(P5=Q5,"Igual","Diferente")) -> Igual
L6: RQ3 | M6: RQ3 — Excerpt: “No evidence found.” | Explanation: The paper does not evaluate any BCI effectiveness. Its metrics concern cognitive tasks (WM, Stroop, dot-probe), EEG components (P1, N170, P2, N2), and self-report scales—not BCI outcomes. | N6: RQ3 — Excerpt: “Pre- and post-treatment assessments were made using questionnaires related to (social) anxiety and depression, and tasks measuring WM, interference control, and attentional biases towards, and event-related potentials (ERPs) elicited by, angry faces.” | Explanation: The evaluation methods used in this neuro-cognitive study include self-report measures (questionnaires), behavioral performance on cognitive tasks (WM, interference control), and electrophysiological signals (ERPs) recorded by EEG. | O6: Embora não seja um estudo de BCI, ele usa tals métricas de avaliação de treinamento cognitivo: Questionários: Liebowitz Social Anxiety Scale (LSAS), State-Trait Anxiety Inventory (STAI-T), Beck Depression Inventory (BDI-13). Tarefas cognitivas: Automated Operation Span Task (Aospan), Stroop Task, Dot-Probe Task. Medidas neurofisiológicas: ERP componentes P1, N170, P2, N2. | P6: Sim | Q6: Parcialmente | R6: =IF(OR(P6="",Q6=""),"",IF(P6=Q6,"Igual","Diferente")) -> Diferente | S6: O GPT teve a mesma percepção que a extração Humana
L7: RQ4 | M7: RQ4 — Excerpt: “working memory (WM) training… enhanced WM transfer task performance” | Explanation: Although the study is unrelated to BCIs, it does address cognitive enhancement—specifically improvements in working memory through behavioral training, not through BCI technology. | N7: RQ4 — Excerpt: “One treatment that, at least theoretically, could enhance the inﬂuence of the top-down system by strengthening EF is working memory (WM) training. WM, speciﬁcally WM updating, is an important component of executive functions... Accordingly, WM updating training might generally enhance attentional control and reduce...” | Explanation: The article explains that WM training, which strengthens Executive Function (EF), is a mechanism that can theoretically enhance cognitive abilities like attentional control, which in turn helps reduce anxiety symptoms. | O7: O artigo não usa BCI, mas mostra que treinamento de memória de trabalho pode melhorar atenção e reduzir sintomas de ansiedade, segundo tal trecho: “The training enhanced WM transfer task performance, reduced SA symptoms, and changed the amplitude of the P1, N170, P2, and N2 ERP components.” | P7: Sim | Q7: Parcialmente | R7: =IF(OR(P7="",Q7=""),"",IF(P7=Q7,"Igual","Diferente")) -> Diferente | S7: O GPT teve a mesma percepção que a extração Humana
L8: RQ5 | M8: RQ5 — Excerpt: “No evidence found.” | Explanation: The article does not discuss technical, clinical, or ethical barriers related to the use of BCIs in therapy or human enhancement. | N8: RQ5 — Excerpt: “No evidence found.” | Explanation: The article is an experimental report, not a systematic review, and therefore does not discuss or list the main technical, clinical, and ethical barriers that generally limit the adoption of BCI technology. | O8: O artigo não discute barreiras técnicas/éticas de BCI. | P8: Sim | Q8: Sim | R8: =IF(OR(P8="",Q8=""),"",IF(P8=Q8,"Igual","Diferente")) -> Igual
L9: RQ6 | M9: RQ6 — Excerpt: “No evidence found.” | Explanation: Nothing in the study addresses data security, privacy, or integrity of neural data in the context of BCIs. EEG is used only as a standard research measurement tool without discussion of neurodata ethics. | N9: RQ6 — Excerpt: “No evidence found.” | Explanation: The article is focused on the results of a training intervention for social anxiety and does not contain any discussion regarding the security, privacy, or integrity protocols for the neural data collected via EEG. | O9: Não há menção a segurança ou privacidade de dados neurais. | P9: Sim | Q9: Sim | R9: =IF(OR(P9="",Q9=""),"",IF(P9=Q9,"Igual","Diferente")) -> Igual
L10: RQ7 | M10: RQ7 — Excerpt: “No evidence found.” | Explanation: The paper does not mention emerging trends involving BCIs, AI integration, or personalized neurostimulation. | N10: RQ7 — Excerpt: “No evidence found.” | Explanation: The article is an original research paper detailing the results of an experiment and does not discuss or identify emerging trends regarding the future integration of BCIs with artificial intelligence or personalized neurostimulation. | O10: O artigo não aborda integração com IA ou neuroestimulação personalizada. | P10: Sim | Q10: Sim | R10: =IF(OR(P10="",Q10=""),"",IF(P10=Q10,"Igual","Diferente")) -> Igual
L11: RQ8 | M11: RQ8 — Excerpt: “No evidence found.” | Explanation: No ethical or philosophical reflections on “neurological expansion” or human capability amplification appear in the text. | N11: RQ8 — Excerpt: “No evidence found.” | Explanation: The article is a clinical study on anxiety treatment and does not engage with the broader ethical and philosophical aspects of "neurological expansion" or the general amplification of human capabilities. | O11: Não há discussão ética ou filosófica sobre expansão neurológica. | P11: Sim | Q11: Sim | R11: =IF(OR(P11="",Q11=""),"",IF(P11=Q11,"Igual","Diferente")) -> Igual
L12: RQ9 | M12: RQ9 — Excerpt: “No evidence found.” | Explanation: The article does not identify research gaps regarding BCIs; its discussion focuses only on working memory training, cognitive transfer, attentional bias, social anxiety, and EEG markers. | N12: RQ9 — Excerpt: “However, given methodological limitations, these results must be regarded as preliminary, and future research should further unravel the causal re-lation among the various indices of social anxiety and the eﬀect of WM training thereupon.” | Explanation: The key research gap identified in the conclusion is the need for future studies to fully determine and explain the causal relationship between the working memory training intervention and the observed changes in symptoms and neural indices of social anxiety. | O12: O artigo aponta lacunas sobre treinamento de memória e ansiedade social, mas não sobre o contexto BCIs: “These data provide preliminary evidence of the usefulness of WM trainings to reduce potential indices of SA, but further research is necessary to unravel the causal relation among these indices.” | P12: Sim | Q12: Não | R12: =IF(OR(P12="",Q12=""),"",IF(P12=Q12,"Igual","Diferente")) -> Diferente | S12: O gemini não considerou o contexto que deveria está ligado a BCIs
A13: ES02 | B13: Journal | C13: Kumar S, Zomorrodi R, Ghazala Z, Goodman MS, Blumberger DM, Daskalakis ZJ, Fischer CE, Mulsant BH, Pollock BG, Rajji TK. Effects of repetitive paired associative stimulation on brain plasticity and working memory in Alzheimer's disease: a pilot randomized double-blind-controlled trial. Int Psychogeriatr. 2023 Mar;35(3):143-155. doi: 10.1017/S1041610220003518. Epub 2020 Nov 16. PMID: 33190659. | D13: international psychogeriatrics | E13: Effects of repetitive paired associative stimulation on brain plasticity and working memory in Alzheimer's disease: a pilot randomized double-blind-controlled trial | F13: PubMed | G13: 2020 | H13: Sanjeev Kumar, Reza Zomorrodi, Zaid Ghazala, Michelle S Goodman, Daniel M Blumberger, Zafiris J Daskalakis, Corinne E Fischer, Benoit H Mulsant, Bruce G Pollock, Tarek K Rajji | I13: Canada | J13: Neurociência; Neurologia; Reabilitação Cognitiva | K13: PubMed | L13: RQ1 | M13: RQ1 — Excerpt: “No evidence found.” | Explanation: The article contains no references to Brain-Computer Interfaces (BCIs), whether invasive, non-invasive, or hybrid. | N13: RQ1 — Excerpt: “No evidence found.” | Explanation: The article is a specific clinical trial on repetitive paired associative stimulation (rPAS)/Transcranial Magnetic Stimulation (TMS) for Alzheimer's disease. It does not contain a general summary or comparative analysis of the most used types (invasive, non-invasive, hybrid) of Brain-Computer Interfaces across all mental health applications. | O13: Este estudo não utiliza diretamente BCIs clássicos, mas sim estimulação cerebral não invasiva: “Pilot randomized double-blind-controlled trial of repetitive paired associative stimulation (rPAS), a paradigm that combines transcranial magnetic stimulation (TMS) of the dorsolateral prefrontal cortex (DLPFC) with peripheral median nerve stimulation.” Isso se aproxima de BCI não-invasivo, pois envolve TMS + EEG para medir plasticidade e desempenho cognitivo mas não é de fato. | P13: Parcialmente | Q13: Parcialmente | R13: =IF(OR(P13="",Q13=""),"",IF(P13=Q13,"Igual","Diferente")) -> Igual | S13: Algumas coisas podem ser consideradas por se aproximarem de BCIs não invasivos
L14: RQ2 | M14: RQ2 — Excerpt: “No evidence found.” | Explanation: The paper does not discuss mental disorders in relation to BCIs. Any mental health content in the article is unrelated to brain–computer interfaces. | N14: RQ2 — Excerpt: “No evidence found.” | Explanation: The research article focuses specifically on Alzheimer's disease (AD) and its related cognitive deficits. It does not provide a comprehensive review or a list of which mental disorders (like depression, anxiety, or schizophrenia) have received the most attention in the broader field of BCI research. | O14: O artigo trata especificamente da doença de alzheimer, mas não em relação a BCIs. | P14: Sim | Q14: Sim | R14: =IF(OR(P14="",Q14=""),"",IF(P14=Q14,"Igual","Diferente")) -> Igual
L15: RQ3 | M15: RQ3 — Excerpt: “No evidence found.” | Explanation: The study does not evaluate BCI effectiveness, and therefore contains no metrics, evaluation methods, or outcomes related to BCIs. | N15: RQ3 — Excerpt: “DLPFC plasticity was assessed using single session PAS combined with electroencephalography (EEG) at baseline and on days 1, 7, and 14 post-rPAS. Working memory and theta-gamma coupling were assessed at the same time points using the N-back task and EEG.” | Explanation: In this study using a neurostimulation paradigm, the key metrics were DLPFC plasticity (measured by PAS-LTP via EEG), working memory performance (measured by the N-back task/A' score), and the corresponding theta-gamma coupling (measured by the Modulation Index via EEG). | O15: O artigo usa várias métricas, mas não relacionadas a BCIs: 1. Plasticidade cortical (PAS-LTP) medida por TMS-EEG. 2. Desempenho em memória de trabalho via N-back task. 3. Oscilações neurais: theta–gamma coupling. | P15: Parcialmente | Q15: Parcialmente | R15: =IF(OR(P15="",Q15=""),"",IF(P15=Q15,"Igual","Diferente")) -> Igual | S15: O GPT não destacou as metricas, mesmo que não relacionadas ao BCIs. O Gemini não destacou que as metricas não se relacionavam ao BCIs.
L16: RQ4 | M16: RQ4 — Excerpt: “No evidence found.” | Explanation: Although the article may involve cognitive or behavioral constructs, it does not describe the use of BCIs for enhancing memory, attention, or learning. | N16: RQ4 — Excerpt: “Thus, DLPFC plasticity could be an appropriate potential target and an intermediate marker for interventions aimed at enhancing work- ing memory in AD.” | Explanation: The article specifically addresses the use of rPAS (a TMS paradigm related to neurostimulation) as an intervention aimed at enhancing the cognitive ability of working memory by targeting DLPFC plasticity in patients with Alzheimer’s disease. | O16: O artigo mostra que o rPAS foi usado para tentar melhorar memória de trabalho em pacientes com Alzheimer. | P16: Sim | Q16: Parcialmente | R16: =IF(OR(P16="",Q16=""),"",IF(P16=Q16,"Igual","Diferente")) -> Diferente
L17: RQ5 | M17: RQ5 — Excerpt: “No evidence found.” | Explanation: There is no discussion of technical, clinical, or ethical barriers to the adoption of BCIs. | N17: RQ5 — Excerpt: “The top reason for failing screen was the travel and time commitment to the study, which raises the importance of adapting noninvasive brain stimulation to less mobile popula- tions such as AD.” | Explanation: While the article does not provide a comprehensive list of all technical, clinical, and ethical barriers in the field, it highlights a major logistical/clinical barrier in its own study: the high time commitment of the noninvasive brain stimulation protocol limited recruitment from less mobile patient populations | O17: O artigo não discute barreiras éticas ou técnicas de forma ampla. Ele apenas menciona limitações metodológicas. | P17: Sim | Q17: Parcialmente | R17: =IF(OR(P17="",Q17=""),"",IF(P17=Q17,"Igual","Diferente")) -> Diferente
L18: RQ6 | M18: RQ6 — Excerpt: “No evidence found.” | Explanation: The article does not address neural data security, privacy, or integrity in the context of BCIs. | N18: RQ6 — Excerpt: “No evidence found.” | Explanation: The article confirms that the study was approved by an Ethics Board and participants provided informed consent, but it does not contain any discussion, statement, or protocol details regarding the specific issues of security, privacy, or integrity of the collected neural (EEG) data. | O18: Não há menção a segurança ou privacidade dos dados neurais. | P18: Sim | Q18: Sim | R18: =IF(OR(P18="",Q18=""),"",IF(P18=Q18,"Igual","Diferente")) -> Igual
L19: RQ7 | M19: RQ7 — Excerpt: “No evidence found.” | Explanation: The paper does not mention emerging BCI trends, nor AI-BCI integration or personalized neurostimulation. | N19: RQ7 — Excerpt: “No evidence found.” | Explanation: The article focuses on future directions for the specific rPAS protocol (e.g., longer duration, alternative stimulation sites) but does not address emerging trends in the integration of BCIs with artificial intelligence or generalized personalized neurostimulation. | O19: O artigo não aborda IA ou neuroestimulação personalizada. | P19: Sim | Q19: Sim | R19: =IF(OR(P19="",Q19=""),"",IF(P19=Q19,"Igual","Diferente")) -> Igual
L20: RQ8 | M20: RQ8 — Excerpt: “No evidence found.” | Explanation: The article includes no ethical or philosophical discussion regarding neural enhancement or “neurological expansion.” | N20: RQ8 — Excerpt: “No evidence found.” | Explanation: The research is a clinical trial focused on a therapeutic intervention for a disease (Alzheimer's). It does not contain any philosophical or ethical commentary on the broader concepts of "neurological expansion" or the amplification of general human capabilities. | O20: Não há discussão ética ou filosófica sobre expansão neurológica. | P20: Sim | Q20: Sim | R20: =IF(OR(P20="",Q20=""),"",IF(P20=Q20,"Igual","Diferente")) -> Igual
L21: RQ9 | M21: RQ9 — Excerpt: “No evidence found.” | Explanation: The paper does not identify research gaps related to BCI applications in mental health or cognitive enhancement. | N21: RQ9 — Excerpt: “Future well-powered studies targeting such a population are needed, and if successful, additional studies should assess the effects of rPAS on other biological markers and behavioral symptoms of AD and as well as focus on overcoming barriers to implementation of rPAS for clinical use.” | Explanation: The primary research gaps highlighted are the need for larger, adequately powered studies, the need to assess effects on biological markers and behavioral symptoms, and the requirement to overcome implementation barriers for the neurostimulation technique to be translated into effective clinical care. | O21: O artigo aponta lacunas da abordagem de tratamento rPAS, mas não relacionadas ao BCIs ou coisas relacionadas. | P21: Sim | Q21: Não | R21: =IF(OR(P21="",Q21=""),"",IF(P21=Q21,"Igual","Diferente")) -> Diferente | S21: O gemini não levou em conta a necissade da relação com o tema de pesquisa da revisão sistematica.
A22: ES03 | B22: Journal | C22: Zhang K, Ji Y, Guo X, Gao T, Zhang X, Yu X, Wang J. The aperiodic and periodic activities of EEG dynamically relate with cognitive performance in schizophrenia. Schizophr Res Cogn. 2025 Jul 31;42:100383. doi: 10.1016/j.scog.2025.100383. PMID: 40792221; PMCID: PMC12337643. | D22: Schizophrenia Research: Cognition | E22: The aperiodic and periodic activities of EEG dynamically relate with cognitive performance in schizophrenia | F22: PubMed | G22: 2025 | H22: Kexin Zhang, Yunfei Ji, Xiaodong Guo, Tianqi Gao, Xuemin Zhang, Xin Yu, Jing Wang | I22: China | K22: PubMed | L22: RQ1 | M22: Excerpt: “No evidence found.” — Explanation: The article studies EEG aperiodic/periodic activity in schizophrenia and does not mention any Brain-Computer Interface (BCI) technology. | N22: No evidence found. The article describes the use of EEG, a non-invasive technique, in a research study on schizophrenia but does not provide a general review or comparison of the most used BCI types (invasive, non-invasive, hybrid) in mental health applications. | O22: Este estudo não usa diretamente BCIs, mas sim EEG (eletroencefalografia) para investigar atividade periódica e aperiódica em pacientes com esquizofrenia: “Before and after the language comprehension tasks (humor, metaphor and irony), the 5-min eyes-closed and eyes-open EEG signals were collected respectively.” | P22: Sim | Q22: Sim | R22: =IF(OR(P22="",Q22=""),"",IF(P22=Q22,"Igual","Diferente")) -> Igual
L23: RQ2 | M23: Excerpt: “No evidence found.” — Explanation: The study only involves schizophrenia and does not examine BCIs or their application to any mental disorders. | N23: No evidence found. The article focuses on schizophrenia (SCZ) and mentions related studies on chronic psychotic disorders and trait anxiety only in passing, but it does not review or state which mental disorder has received the most attention in BCI research. | O23: O artigo foca em esquizofrenia, mas não é relacionada ao uso de BCIs | P23: Sim | Q23: Sim | R23: =IF(OR(P23="",Q23=""),"",IF(P23=Q23,"Igual","Diferente")) -> Igual
L24: RQ3 | M24: Excerpt: “Power spectral density (PSD) helped to decompose EEG signals…”, “…aperiodic exponent and periodic power were extracted…”, and “Cognitive performance was assessed using the total Brief Assessment of Cognition in Schizophrenia (BACS).” main — Explanation: The study evaluates EEG effectiveness using PSD, aperiodic exponent, alpha/beta power, and correlates them with BACS cognitive test scores. These are EEG metrics, not BCI evaluation metrics. | N24: No evidence found. The paper describes metrics (BACS, Z scores) and methods (Pearson correlation, ANOVA) for assessing cognitive deficits in SCZ, but it does not discuss how to measure the effectiveness of BCIs in treatment. | O24: O estudo utiliza: EEG (aperiodic exponent, alpha e beta band power). Brief Assessment of Cognition in Schizophrenia (BACS). Tasks de compreensão de linguagem figurativa (humor, metáfora, ironia). | P24: Sim | Q24: Parcialmente | R24: =IF(OR(P24="",Q24=""),"",IF(P24=Q24,"Igual","Diferente")) -> Diferente
L25: RQ4 | M25: Excerpt: “The aperiodic exponent…showed significantly negative correlation with Z scores of humor comprehension tasks…” and “pre-tasks aperiodic exponent…positively correlated with T scores of attention and speed of information processing.” main — Explanation: The article links EEG spectral features to cognitive functions such as attention, processing speed, and language comprehension, but does not use BCIs for cognitive enhancement. | N25: No evidence found. The paper states that the aperiodic exponent relates to cognitive functions like "attention (Tagliazucchi et al., 2013), working memory (Kardan et al., 2020), motor performance (Immink et al., 2021) and academic learning (Cross et al., 2022)"1111, but it does not describe the use of BCIs for enhancing these abilities. | O25: O artigo mostra correlações entre EEG(não com BCIs) e desempenho cognitivo (atenção, velocidade de processamento, compreensão de humor/metáfora): “The pre-tasks aperiodic exponent in posterior location positively correlated with T scores of attention and speed of information processing.” | P25: Sim | Q25: Sim | R25: =IF(OR(P25="",Q25=""),"",IF(P25=Q25,"Igual","Diferente")) -> Igual
L26: RQ5 | M26: Excerpt: “No evidence found.” — Explanation: The paper does not discuss any technical, clinical, or ethical barriers to the adoption of BCIs. It only discusses EEG analysis limitations. | N26: No evidence found. The article discusses research limitations and heterogeneity in EEG studies but does not address the broader technical, clinical, and ethical barriers that limit the adoption of BCIs in therapeutic or human enhancement contexts. | O26: O artigo não discute barreiras éticas ou técnicas de BCI. | P26: Sim | Q26: Sim | R26: =IF(OR(P26="",Q26=""),"",IF(P26=Q26,"Igual","Diferente")) -> Igual
L27: RQ6 | M27: Excerpt: “No evidence found.” — Explanation: The study does not mention data security, privacy, or integrity concerns related to BCIs or neural data beyond basic ethical approval. | N27: No evidence found. The article mentions obtaining "written informed consent" 2 and ethical approval for the study, but it does not discuss technical or policy mechanisms regarding the security, privacy, or integrity of the collected neural data. | O27: Não há menção a segurança ou privacidade dos dados neurais. | P27: Sim | Q27: Sim | R27: =IF(OR(P27="",Q27=""),"",IF(P27=Q27,"Igual","Diferente")) -> Igual
L28: RQ7 | M28: Excerpt: “No evidence found.” — Explanation: The study does not discuss AI, neurostimulation, personalization, or future trends in BCI technology. | N28: Excerpt: "Finally, future research can be integrated with other modalities (e.g., fMRI, neurostimulation) to enhance spatial resolution or mechanistic insight." 3 — Explanation: The authors suggest that future research, including work on neurophysiological parameters like those studied, should be integrated with other modalities such as fMRI and neurostimulation to improve understanding. | O28: O artigo não aborda integração com IA ou neuroestimulação personalizada. | P28: Sim | Q28: Não | R28: =IF(OR(P28="",Q28=""),"",IF(P28=Q28,"Igual","Diferente")) -> Diferente
L29: RQ8 | M29: Excerpt: “No evidence found.” — Explanation: The article does not address ethical or philosophical issues related to neurological expansion or enhancement. | N29: No evidence found. The article is a research study on neurophysiology and schizophrenia and does not include a discussion of the ethical or philosophical implications of "neurological expansion" or the amplification of human capabilities. | O29: Não há discussão ética ou filosófica sobre expansão neurológica. | P29: Sim | Q29: Sim | R29: =IF(OR(P29="",Q29=""),"",IF(P29=Q29,"Igual","Diferente")) -> Igual
L30: RQ9 | M30: Excerpt: “Future studies should… integrate with other modalities (e.g., fMRI, neurostimulation) to enhance spatial resolution or mechanistic insight.” main — Explanation: The reported research gaps relate only to EEG-based cognition studies in schizophrenia, not BCIs; there is no mention of BCI applications. | N30: Excerpt: "Future experiments necessitate the development of validated scales or paradigms that have undergone rigorous reliability and validity testing." 4 — Explanation: The authors highlight the need for rigorously tested and validated scales and experimental paradigms as a key research gap to ensure the quality and reliability of future assessments in mental healthcare. | O30: O artigo aponta lacunas sobre a necessidade de investigar melhor a relação entre aperiodic exponent e desempenho cognitivo em esquizofrenia: “Our findings confirmed the higher aperiodic exponent with lower alpha and beta band in SCZ… The findings suggest that aperiodic exponent holds strong cognitive functional implications in SCZ.” | P30: Sim | Q30: Sim | R30: =IF(OR(P30="",Q30=""),"",IF(P30=Q30,"Igual","Diferente")) -> Igual
A31: ES04 | B31: Journal | C31: Enriquez-Geppert S, Krc J, O'Higgins FJ, Lietz M. Psilocybin-assisted neurofeedback for the improvement of executive functions: a randomized semi-naturalistic-lab feasibility study. Philos Trans R Soc Lond B Biol Sci. 2024 Dec 2;379(1915):20230095. doi: 10.1098/rstb.2023.0095. Epub 2024 Oct 21. PMID: 39428872; PMCID: PMC11513162. | D31: Philosophical Transactions of the Royal Society B | E31: Psilocybin-assisted neurofeedback for the improvement of executive functions: a randomized... feasibility study | F31: https://pubmed.ncbi.nlm.nih.gov/39428872/ | G31: 2024 | H31: Enriquez-Geppert S, et al. | I31: Netherlands | K31: PubMed | L31: RQ1 | M31: Excerpt: “No evidence found.” — Explanation: The article contains no discussion of Brain-Computer Interfaces (invasive, non-invasive, or hybrid) in any context. | N31: Excerpt: “Viviani & Velessi's [50] systematic review underscored that NF protocols targeting fm-theta are the most successful EEG protocols thus far regarding the improvement of EFs.” 1 Explanation: The article identifies frontal-midline theta neurofeedback (a non-invasive EEG method) as the most successful protocol for improving executive functions. | O31: Este estudo utiliza EEG neurofeedback (NF), que é uma forma de BCI não-invasiva. | P31: Não | Q31: Sim | R31: =IF(OR(P31="",Q31=""),"",IF(P31=Q31,"Igual","Diferente")) -> Diferente
L32: RQ2 | M32: Excerpt: “No evidence found.” — Explanation: The article does not mention any mental disorders (e.g., depression, anxiety, schizophrenia, ADHD) in relation to BCIs. | N32: No evidence found. Explanation: The article mentions that executive function deficits are "common in psychiatric disorders" 2 and references depression, stroke, and dementia in specific contexts, but it does not provide a general review ranking which disorders have received the most attention in BCI research. | O32: O artigo não foca em um transtorno específico, mas em déficits de funções executivas transdiagnósticos (presentes em várias condições psiquiátricas). | P32: Sim | Q32: Sim | R32: =IF(OR(P32="",Q32=""),"",IF(P32=Q32,"Igual","Diferente")) -> Igual
L33: RQ3 | M33: Excerpt: “No evidence found.” — Explanation: The text includes no metrics, evaluation methods, or outcome measures related to assessing BCI effectiveness. | N33: Excerpt: “Following three domains were assessed: (i) general placebo and expectancy (by general susceptibility and optimism, as well NF and psilocybin-assisted NF-specific experiences, attitudes and expectations), (ii) EFs (by self-rated EFs in daily life and four computerized experimental EF tasks), and (iii) functional abilities (by participant's priorities).” 3 Explanation: The authors evaluated effectiveness using a combination of placebo/expectancy questionnaires, objective computerized tasks, subjective daily life self-reports, and personalized functional goal ratings. | O33: O estudo usa: EEG frontal-midline theta power (indicador neural). Quatro tarefas de funções executivas: working memory updating, set-shifting, conflict monitoring, motor inhibition. Autoavaliações (BRIEF-A) sobre funções executivas na vida diária. Relatos de metas individuais de treinamento. | P33: Não | Q33: Sim | R33: =IF(OR(P33="",Q33=""),"",IF(P33=Q33,"Igual","Diferente")) -> Diferente
L34: RQ4 | M34: Excerpt: “No evidence found.” — Explanation: The paper does not discuss BCIs for enhancing memory, attention, learning, or other cognitive abilities. | N34: Excerpt: “Jackson et al. [42] observed a modest yet significant impact on episodic memory across both healthy and clinical groups... Significantly, fm-theta NF... has been identified as particularly effective in enhancing EFs in healthy individuals.” 4444 Explanation: The text cites previous studies showing that neurofeedback has been used to achieve significant improvements in episodic memory and executive functions (which include attention) in various populations. | O34: O artigo mostra que o neurofeedback assistido por psilocibina foi usado para melhorar funções executivas (memória de trabalho, atenção, inibição, monitoramento). | P34: Não | Q34: Sim | R34: =IF(OR(P34="",Q34=""),"",IF(P34=Q34,"Igual","Diferente")) -> Diferente
L35: RQ5 | M35: Excerpt: “No evidence found.” — Explanation: No technical, clinical, or ethical barriers to BCI adoption are mentioned or implied anywhere in the article. | N35: Excerpt: “Notably, inter-individual variability in learning to self-regulate brain activity, along with the presence of 'non-responders' [52,53], demands focused attention and solutions.” 5 Explanation: The authors identify the variability in learning success and the existence of "non-responders" (participants who fail to learn self-regulation) as primary clinical barriers to the adoption and efficacy of neurofeedback. | O35: O artigo menciona desafios como: Variabilidade individual (existência de “non-responders”). Necessidade de estudos maiores e controles ativos. Questões éticas do uso de psicodélicos (psilocibina) em conjunto com Neurofeedback | P35: Não | Q35: Sim | R35: =IF(OR(P35="",Q35=""),"",IF(P35=Q35,"Igual","Diferente")) -> Diferente
L36: RQ6 | M36: Excerpt: “No evidence found.” — Explanation: The article provides no coverage of security, privacy, or integrity of neural data. | N36: No evidence found. Explanation: While the article mentions obtaining informed consent 6and storing data on the OSF repository7, it does not discuss specific technical measures regarding the security, privacy, or integrity of the neural data. | O36: O artigo não discute segurança ou privacidade dos dados neurais. | P36: Sim | Q36: Sim | R36: =IF(OR(P36="",Q36=""),"",IF(P36=Q36,"Igual","Diferente")) -> Igual
L37: RQ7 | M37: Excerpt: “No evidence found.” — Explanation: The article contains no discussion of emerging BCI trends, AI integration, or personalized neurostimulation. | N37: Excerpt: “Recent advancements in NF methodology encompass real-time brain activity decoding [54], personalized NF tailored to individual anatomical and functional networks [55] and innovative NF techniques involving semantically guidance through mental states [56].” 8 Explanation: The article outlines emerging trends such as real-time decoding, personalization based on individual anatomy, and semantic guidance as key future directions for neurofeedback integration. | O37: O artigo menciona tendências como: Personalized NF(Neurofeedback Personalizado) adaptado a redes anatômicas e funcionais individuais. Uso de psicodélicos como potenciadores de neuroplasticidade em conjunto com Neurofeedback. | P37: Não | Q37: Sim | R37: =IF(OR(P37="",Q37=""),"",IF(P37=Q37,"Igual","Diferente")) -> Diferente
L38: RQ8 | M38: Excerpt: “No evidence found.” — Explanation: Ethical or philosophical issues related to neurological expansion or human capability amplification do not appear in the article. | N38: No evidence found. Explanation: The article focuses on the feasibility and efficacy of a specific clinical intervention (psilocybin-assisted neurofeedback) and does not address the broader ethical or philosophical implications of neurological expansion. | O38: O artigo toca em aspectos éticos do uso de psicodélicos para amplificação cognitiva, mas não discute profundamente filosofia da “expansão neurológica”. | P38: Sim | Q38: Sim | R38: =IF(OR(P38="",Q38=""),"",IF(P38=Q38,"Igual","Diferente")) -> Igual
L39: RQ9 | M39: Excerpt: “No evidence found.” — Explanation: The article does not address research gaps related to BCI technology, mental healthcare, or cognitive enhancement. | N39: Excerpt: “A thorough study with regular sessions and an active control group is crucial to evaluate EFs improvement and their specificity in future.” 9 Explanation: The authors conclude that to validate the method as an effective tool, future research must address current gaps by increasing the number of sessions and incorporating an active control group to rule out non-specific effects. | O39: O artigo aponta lacunas: Necessidade de estudos maiores e com grupo controle ativo. Avaliar especificidade dos ganhos em funções executivas. | P39: Não | Q39: Sim | R39: =IF(OR(P39="",Q39=""),"",IF(P39=Q39,"Igual","Diferente")) -> Diferente
A40: ES05 | B40: Journal | C40: Zemla K, Sedek G, Wróbel K, Postepski F, Wojcik GM. Investigating the Impact of Guided Imagery on Stress, Brain Functions, and Attention: A Randomized Trial. Sensors (Basel). 2023 Jul 7;23(13):6210. doi: 10.3390/s23136210. PMID: 37448060; PMCID: PMC10346678. | D40: Sensors (Basel) | E40: Investigating the Impact of Guided Imagery on Stress, Brain Functions, and Attention: A Randomized Trial | F40: https://pubmed.ncbi.nlm.nih.gov/37448060/ | G40: 2023 | H40: Zemla K, et al. | I40: Poland | K40: PubMed | L40: RQ1 | M40: No evidence Found | N40: No evidence Found | O40: Este estudo não usa diretamente BCIs clássicos, mas sim EEG para medir atividade cerebral durante guided imagery (GI). trata-se de um método não-invasivo (EEG). | P40: Não | Q40: Não | R40: =IF(OR(P40="",Q40=""),"",IF(P40=Q40,"Igual","Diferente")) -> Igual | S40: As LMMs não consideram EGG como metodo não invasivo.
L41: RQ2 | M41: No evidence Found | N41: No evidence Found | O41: O artigo não foca em um transtorno clínico específico, mas em redução de estresse e ansiedade em participantes saudáveis. | P41: Sim | Q41: Sim | R41: =IF(OR(P41="",Q41=""),"",IF(P41=Q41,"Igual","Diferente")) -> Igual
L42: RQ3 | M42: RQ3 Excerpt: “the effectiveness of the session in reducing stress was assessed through monitoring beta power reductions and alpha state increases using EEG data recordings and self-reported questionnaires.” — Explanation: The article explicitly lists EEG band power (alpha, beta) changes and self-report questionnaires as outcome metrics used to assess intervention effectiveness; attentional-task error rates (Stroop, anti-saccade, Go/No-go) are also presented as measurable outcomes. | N42: No evidence Found | O42: O estudo usa: EEG (alpha e beta power). Testes de funções executivas: Stroop, Go/No-go, Anti-saccade. Questionários de ansiedade e estresse (STAI, auto-relatos). | P42: Sim | Q42: Não | R42: =IF(OR(P42="",Q42=""),"",IF(P42=Q42,"Igual","Diferente")) -> Diferente
L43: RQ4 | M43: No evidence Found | N43: No evidence Found | O43: O artigo mostra que guided imagery + EEG pode melhorar atenção e controle executivo: “The findings suggest that guided imagery has the potential to enhance attentional control by augmenting the alpha power and reducing stress levels.” | P43: Não | Q43: Não | R43: =IF(OR(P43="",Q43=""),"",IF(P43=Q43,"Igual","Diferente")) -> Igual
L44: RQ5 | M44: No evidence Found | N44: No evidence Found | O44: O artigo não discute barreiras éticas ou técnicas de BCI. | P44: Sim | Q44: Sim | R44: =IF(OR(P44="",Q44=""),"",IF(P44=Q44,"Igual","Diferente")) -> Igual
L45: RQ6 | M45: No evidence Found | N45: No evidence Found | O45: Não há menção a segurança ou privacidade dos dados neurais. | P45: Sim | Q45: Sim | R45: =IF(OR(P45="",Q45=""),"",IF(P45=Q45,"Igual","Diferente")) -> Igual
L46: RQ7 | M46: RQ7 Excerpt: “Moreover, a notable feature of this research involved the application of multi-sensor EEG signal classification and a GLM for the categorization of two mental states. These findings offer compelling evidence regarding the potential for developing innovative therapies in the domain of human–machine interactions ... For instance, the study titled ‘Golden Subject Is Everyone: A Subject Transfer Neural Network for Motor Imagery-based Brain Computer Interfaces’ [106] explores the use of neural networks to transfer knowledge between individuals in the context of motor-imagery-based brain–computer interfaces. The researchers propose a new approach that allows data from one participant to be used to train a neural network, which can then be applied to predict and interpret brain signals from a different participant. The findings indicate that this method has potential and could lead to the development of more inclusive and widely applicable brain–computer interfaces.” — Explanation: The article cites machine-learning / neural-network approaches and subject-transfer for motor-imagery BCIs as an emerging direction, indicating integration of AI methods to improve BCI generalization and applicability. | N46: Excerpt: "For instance, the study titled “Golden Subject Is Everyone: A Subject Transfer Neural Net work for Motor Imagery-based Brain Computer Interfaces” [106] explores the use of neural networks to transfer knowledge between individuals in the context of motor-imagery-based brain–computer interfaces." — Explanation: The article references a related BCI study in its discussion, highlighting the emerging trend of integrating artificial intelligence (neural networks) to create more generalized, personalized BCI applications by transferring knowledge between subjects. | O46: O artigo aborda IA ou neuroestimulação personalizada. | P46: Sim | Q46: Sim | R46: =IF(OR(P46="",Q46=""),"",IF(P46=Q46,"Igual","Diferente")) -> Igual
L47: RQ8 | M47: No evidence Found | N47: No evidence Found | O47: Não há discussão ética ou filosófica sobre expansão neurológica. | P47: Sim | Q47: Sim | R47: =IF(OR(P47="",Q47=""),"",IF(P47=Q47,"Igual","Diferente")) -> Igual
L48: RQ9 | M48: RQ9 Excerpt: “These limitations underscore the need for future research with larger and more diverse samples, longer follow-up periods, and additional control groups. By addressing these methodological considerations, a more comprehensive understanding of the effectiveness and potential limitations of guided imagery can be achieved, not only in the context of stress management but also in terms of enhancing attentional control test results.” — Explanation: While focused on guided imagery, the authors explicitly state research gaps (larger/diverse samples, longer follow-up, more control groups) that are relevant general recommendations for future work linking EEG/BCI research to cognitive and clinical outcomes. | N48: No evidence Found | O48: O artigo aponta lacunas, indica que há pouca pesquisa sobre GI + EEG: “Given the limited existing research on the specific impact of guided imagery on attention control, the study’s findings carry notable significance.” | P48: Parcialmente | Q48: Não | R48: =IF(OR(P48="",Q48=""),"",IF(P48=Q48,"Igual","Diferente")) -> Diferente
A49: ES06 | B49: Journal | C49: Chan WL, Olbrich S, Jiang X, Zhang H, Ip CT, Brunovsky M. Subanesthetic ketamine alters EEG signal complexity: Implications for treatment stratification in depression. J Affect Disord. 2025 Oct 1;386:119477. doi: 10.1016/j.jad.2025.119477. Epub 2025 May 24. PMID: 40419149. | D49: Journal of Affective Disorders | E49: Subanesthetic ketamine alters EEG signal complexity: Implications for treatment stratification in depression | F49: https://pubmed.ncbi.nlm.nih.gov/40419149/ | G49: 2025 | H49: Chan WL, et al. | I49: Czech Republic | K49: PubMed | L49: RQ1 | M49: No evidence Found | N49: No evidence Found | O49: O estudo usa EEG não-invasivo para medir complexidade de sinais cerebrais durante infusão de ketamina em pacientes com depressão. | P49: Não | Q49: Não | R49: =IF(OR(P49="",Q49=""),"",IF(P49=Q49,"Igual","Diferente")) -> Igual
I50: Switzerland | L50: RQ2 | M50: No evidence Found | N50: No evidence Found | O50: O artigo foca em major depressive disorder (MDD), especialmente na forma resistente ao tratamento (TRD): “Major depressive disorder, particularly its treatment-resistant form (TRD), poses significant treatment challenges.” | P50: Não | Q50: Não | R50: =IF(OR(P50="",Q50=""),"",IF(P50=Q50,"Igual","Diferente")) -> Igual
L51: RQ3 | M51: No evidence Found | N51: No evidence Found | O51: O estudo usa: Montgomery-Åsberg Depression Rating Scale (MADRS) para avaliar sintomas clínicos. EEG Lempel-Ziv complexity (LZCT e LZCS) como biomarcadores de resposta. | P51: Não | Q51: Não | R51: =IF(OR(P51="",Q51=""),"",IF(P51=Q51,"Igual","Diferente")) -> Igual
L52: RQ4 | M52: No evidence Found | N52: No evidence Found | O52: O artigo não trata de memória ou atenção diretamente, mas mostra que EEG pode prever resposta antidepressiva e está ligado a neuroplasticidade. | P52: Parcialmente | Q52: Parcialmente | R52: =IF(OR(P52="",Q52=""),"",IF(P52=Q52,"Igual","Diferente")) -> Igual
L53: RQ5 | M53: No evidence Found | N53: Excerpt: "Additionally, the use of a 22-channel EEG cap restricted spatial resolution, likely to constrain the ability of $LZC_{S}$ to detect topographic variability. [...] Moreover, the small sample size may compromise the statistical power and robustness of our conclu- sions. The use of a single-blind, fixed-sequence design introduces po- tential biases." 1111 — Explanation: The authors list methodological drawbacks of their study that apply as technical barriers (limited EEG channels for spatial resolution) and clinical/design barriers (small sample size and fixed-sequence design) for research in the field. | O53: O artigo menciona limitações técnicas: Pequeno tamanho da amostra. Resultados inconsistentes entre regiões cerebrais. Complexidade excessiva pode não se traduzir em melhora clínica. | P53: Não | Q53: Sim | R53: =IF(OR(P53="",Q53=""),"",IF(P53=Q53,"Igual","Diferente")) -> Diferente
L54: RQ6 | M54: No evidence Found | N54: No evidence Found | O54: O artigo não discute segurança ou privacidade dos dados neurais. | P54: Sim | Q54: Sim | R54: =IF(OR(P54="",Q54=""),"",IF(P54=Q54,"Igual","Diferente")) -> Igual
L55: RQ7 | M55: No evidence Found | N55: No evidence Found | O55: O artigo não menciona IA ou neuroestimulação personalizada. | P55: Sim | Q55: Sim | R55: =IF(OR(P55="",Q55=""),"",IF(P55=Q55,"Igual","Diferente")) -> Igual
L56: RQ8 | M56: No evidence Found | N56: No evidence Found | O56: Não há discussão ética ou filosófica sobre expansão neurológica. | P56: Sim | Q56: Sim | R56: =IF(OR(P56="",Q56=""),"",IF(P56=Q56,"Igual","Diferente")) -> Igual
L57: RQ9 | M57: No evidence Found | N57: No evidence Found | O57: O artigo aponta lacunas: Necessidade de validar LZC como biomarcador preditivo. Explorar melhor a relação entre complexidade neural e resposta clínica. “The utility of LZC in predicting treatment response to ketamine, particularly in TRD, has not been systematically validated.” | P57: Não | Q57: Não | R57: =IF(OR(P57="",Q57=""),"",IF(P57=Q57,"Igual","Diferente")) -> Igual
A58: ES07 | B58: Journal | C58: Jaiswal S, Purpura SR, Manchanda JK, Nan J, Azeez N, Ramanathan D, Mishra J. Design and Implementation of a Brief Digital Mindfulness and Compassion Training App for Health Care Professionals: Cluster Randomized Controlled Trial. JMIR Ment Health. 2024 Jan 22;11:e49467. doi: 10.2196/49467. PMID: 38252479; PMCID: PMC10845023. | D58: JMIR Ment Health | E58: Design and Implementation of a Brief Digital Mindfulness and Compassion Training App...: Cluster Randomized Controlled Trial | F58: https://pubmed.ncbi.nlm.nih.gov/38252479/ | G58: 2024 | H58: Jaiswal S, et al. | I58: United States | K58: PubMed | L58: RQ1 | M58: No evidence Found | N58: No evidence Found | O58: O estudo usa EEG não-invasivo para medir atividade neural durante tarefas de atenção à respiração, antes e depois do treinamento digital. trata-se de BCI não-invasiva (EEG). | P58: Não | Q58: Não | R58: =IF(OR(P58="",Q58=""),"",IF(P58=Q58,"Igual","Diferente")) -> Igual
L59: RQ2 | M59: No evidence Found | N59: No evidence Found | O59: O artigo não foca em um transtorno específico, mas em burnout e estresse ocupacional em profissionais de saúde. | P59: Sim | Q59: Sim | R59: =IF(OR(P59="",Q59=""),"",IF(P59=Q59,"Igual","Diferente")) -> Igual
L60: RQ3 | M60: No evidence Found | N60: Excerpt: “We evaluated the primary outcomes of change in mindfulness and self-compassion and monitored sessions of training engagement. [...] Finally, this study also uniquely assayed objective neurophysiological plasticity associated with the training alongside subjective behavioral changes. For this, we measured electroencephalography (EEG)-based brain signals on an interoceptive attention-to-breathing task, assessed before and after training.” — Explanation: The study used a combination of subjective behavioral assessments (mindfulness and self-compassion scales) and objective neurophysiological measures (EEG-based brain signals) to track the training's effectiveness. | O60: O estudo usa: Escalas comportamentais: Self-Compassion Scale, Mindful Attention Awareness Scale, Maslach Burnout Inventory. EEG source imaging para medir atividade em redes neurais (Default Mode Network, FPN, CON). | P60: Não | Q60: Sim | R60: =IF(OR(P60="",Q60=""),"",IF(P60=Q60,"Igual","Diferente")) -> Diferente
L61: RQ4 | M61: No evidence Found | N61: Excerpt: “Overall, this digital meditative practice is considered closed loop because of its performance-adaptive feature [22,23]. Consistent attention to breathing is emphasized over other types of breathing techniques, such as deep breathing. The moment-to-moment performance tracking further allows quantification of the attentive focus during each session, which is not possible with traditional nondigital meditation.” — Explanation: The "closed-loop," performance-adaptive digital system allows for the tracking and quantification of "attentive focus" during breath monitoring, which serves as a cognitive training and enhancement mechanism. | O61: O artigo mostra que o treinamento digital com EEG está associado a melhora em atenção plena e autocompaixão, além de supressão da DMN (rede cerebral ligada a divagação mental e ruminação). | P61: Não | Q61: Sim | R61: =IF(OR(P61="",Q61=""),"",IF(P61=Q61,"Igual","Diferente")) -> Diferente
L62: RQ5 | M62: No evidence Found | N62: Excerpt: “As per the limitations of this study, the sample size and nonactive control group are the primary limitations, although it is worth noting that this is the first ever implementation of the digital WellMind intervention in health care professionals. [...] These challenges include a clear lack of time for physicians as well as concerns regarding confidentiality and discrimination within this workforce.” — Explanation: The article points out methodological limitations (small sample size, nonactive control group) as clinical barriers, and also highlights adoption barriers like lack of time for healthcare professionals, and ethical concerns over confidentiality and discrimination. | O62: artigo não discute barreiras éticas em profundidade, mas menciona limitações: Pequeno tamanho da amostra. Treinamento individual não altera burnout significativamente (precisa de intervenção organizacional). | P62: Não | Q62: Sim | R62: =IF(OR(P62="",Q62=""),"",IF(P62=Q62,"Igual","Diferente")) -> Diferente
L63: RQ6 | M63: No evidence Found | N63: Excerpt: “This digital program is Health Insurance Portability and Accountability Act (HIPAA) compliant and secured by password protection, and each user interacts through an alphanumeric study ID that is not linked to any personal health information. [...] All data is de-identified, and up to US $150 in compensation was provided as an e-Gift card to all participants for completing all aspects of the study, including assessments and intervention procedures.” — Explanation: The study addresses security and privacy by ensuring the app is HIPAA compliant, secured by password, uses de-identified alphanumeric IDs not linked to personal health information, and confirms all collected data is de-identified. | O63: O estudo menciona que o app apresentando e usado no estudo é protegido por senha, garantindo privacidade dos dados: “This digital program is Health Insurance Portability and Accountability Act (HIPAA) compliant and secured by password protection.” | P63: Não | Q63: Sim | R63: =IF(OR(P63="",Q63=""),"",IF(P63=Q63,"Igual","Diferente")) -> Diferente
L64: RQ7 | M64: No evidence Found | N64: Excerpt: “Also, individuals with high DMN activity at baseline experienced greater DMN suppression with training, suggesting baseline DMN activity as an individual-specific neural marker to determine who may benefit most from such training.” — Explanation: The finding that a baseline neural state (DMN activity) predicts the magnitude of training benefit is an emerging trend, indicating the potential for using individual-specific neural markers to personalize treatment and maximize efficacy. | O64: O artigo não fala de IA ou neuroestimulação personalizada, mas mostra tendência de treinamentos digitais escaláveis e adaptativos. | P64: Não | Q64: Sim | R64: =IF(OR(P64="",Q64=""),"",IF(P64=Q64,"Igual","Diferente")) -> Diferente
L65: RQ8 | M65: No evidence Found | N65: No evidence Found | O65: O artigo não discute aspectos éticos ou filosóficos de expansão neurológica. | P65: Sim | Q65: Sim | R65: =IF(OR(P65="",Q65=""),"",IF(P65=Q65,"Igual","Diferente")) -> Igual
L66: RQ9 | M66: No evidence Found | N66: Excerpt: “The use of an active control group (e.g., providing a different, non-mindfulness, or non-compassion digital training) is necessary in the future to rule out effects related to time, contact, and expectation differences.” — Explanation: A key methodological gap is the need for an active control group (rather than a no-contact group) to conclusively confirm that the positive effects are due to the specific intervention and not simply the result of time, contact, or user expectation. | O66: O artigo aponta lacunas: Necessidade de estudos maiores. Integração com intervenções organizacionais para impacto em burnout. | P66: Não | Q66: Sim | R66: =IF(OR(P66="",Q66=""),"",IF(P66=Q66,"Igual","Diferente")) -> Diferente
A67: ES08 | B67: Journal | C67: Horváth D, Négyesi J, Rácz M, Győri T, Matics Z, Puskin A, Csipor J, Rácz L. Feasibility of a novel neurofeedback system: a parallel randomized single-blinded pilot study. Sci Rep. 2023 Oct 13;13(1):17353. doi: 10.1038/s41598-023-44545-1. PMID: 37833489; PMCID: PMC10576027. | D67: Scientific Reports | E67: Feasibility of a novel neurofeedback system: a parallel randomized single-blinded pilot study | F67: https://pubmed.ncbi.nlm.nih.gov/37833489/ | G67: 2023 | H67: Horváth D, et al. | I67: Hungary | K67: PubMed | L67: RQ1 | M67: No evidence Found | N67: No evidence Found | O67: O estudo usa neurofeedback (NF) via EEG não-invasivo, com um novo sistema chamado neuroMoon (nM). | P67: Não | Q67: Não | R67: =IF(OR(P67="",Q67=""),"",IF(P67=Q67,"Igual","Diferente")) -> Igual
L68: RQ2 | M68: No evidence Found | N68: Excerpt: “There is a growing body of literature that supports the effectiveness of NF, particularly in the field of cognitive functions and attention-deficit/hyperactivity disorder (ADHD)”. — Explanation: The article specifically points out that neurofeedback research shows effectiveness for cognitive function and Attention-Deficit/Hyperactivity Disorder (ADHD), suggesting these areas have received significant attention. | O68: Este artigo não foca em transtornos clínicos, mas em atletas jovens saudáveis, avaliando cognição e desempenho perceptual-cognitivo. | P68: Parcialmente | Q68: Sim | R68: =IF(OR(P68="",Q68=""),"",IF(P68=Q68,"Igual","Diferente")) -> Diferente
L69: RQ3 | M69: No evidence Found | N69: Excerpt: “The NF protocol used is aimed at increasing the sensorimotor rhythm-theta ratio (SMR/T)... To assess the success of the nM neurofeedback training, Mann-Whitney U test was performed to com- pare the differences between the real and sham nM groups. Furthermore, to establish the relationship between behavioral and EEG changes, a comprehensive correlation analysis was performed.”. — Explanation: The effectiveness is measured primarily by tracking changes in the SMR/T EEG ratio and comparing these neurophysiological metrics using statistical tests (Mann-Whitney U, correlation analysis) against behavioral outcomes. | O69: O estudo usa: Vienna Test System (VTS): Stroop, Trail-Making, Task-Switching, Reaction Test, Determination Test. Digit Span Backwards (DSB) para memória de trabalho. EEG medidas (SMR/T ratio) durante Neurofeedback. | P69: Não | Q69: Sim | R69: =IF(OR(P69="",Q69=""),"",IF(P69=Q69,"Igual","Diferente")) -> Diferente
L70: RQ4 | M70: No evidence Found | N70: Excerpt: “This closed-loop method helps individuals to control or modify their cortical activity through learned self-regulation, with the aim of improving alertness, reducing anxiety and enhancing cognitive abilities such as attention, memory, and behavior.”. — Explanation: Brain-Computer Interfaces in the form of Neurofeedback (NF) are described as a closed-loop technique that aims to enhance cognitive abilities, including attention and memory, through learned self-regulation of brain function. | O70: O artigo mostra que o neurofeedback (SMR/T ratio) foi usado para melhorar atenção, memória de trabalho e velocidade de reação. | P70: Não | Q70: Sim | R70: =IF(OR(P70="",Q70=""),"",IF(P70=Q70,"Igual","Diferente")) -> Diferente
L71: RQ5 | M71: No evidence Found | N71: Excerpt: “An additional challenge of lightweight EEG hardware is the lack of working electrodes above the areas that are most frequently used in SMR/T NF procedures, most notably, Cz/Pz locations.”. — Explanation: A main technical barrier is the design limitation of portable/lightweight EEG devices, which often lack the necessary number and strategic placement of electrodes (like Cz/Pz) required for optimal Neurofeedback procedures. | O71: O artigo aponta limitações: Melhorias também ocorreram no grupo sham, sugerindo efeito placebo. Pequeno tamanho da amostra. | P71: Não | Q71: Parcialmente | R71: =IF(OR(P71="",Q71=""),"",IF(P71=Q71,"Igual","Diferente")) -> Diferente
L72: RQ6 | M72: No evidence Found | N72: No evidence Found | O72: O artigo não discute segurança ou privacidade dos dados neurais. | P72: Sim | Q72: Sim | R72: =IF(OR(P72="",Q72=""),"",IF(P72=Q72,"Igual","Diferente")) -> Igual
L73: RQ7 | M73: No evidence Found | N73: No evidence Found | O73: artigo não menciona IA ou neuroestimulação personalizada, mas mostra tendência de headsets portáteis de EEG com Neurofeedback gamificado. | P73: Sim | Q73: Sim | R73: =IF(OR(P73="",Q73=""),"",IF(P73=Q73,"Igual","Diferente")) -> Igual
L74: RQ8 | M74: No evidence Found | N74: No evidence Found | O74: O artigo não discute aspectos éticos ou filosóficos. | P74: Sim | Q74: Sim | R74: =IF(OR(P74="",Q74=""),"",IF(P74=Q74,"Igual","Diferente")) -> Igual
L75: RQ9 | M75: No evidence Found | N75: Excerpt: “However, considering that the sham stimulation also induced similar improvements in cognitive abilities, future studies should clearly determine the cognitive measures that could benefit from NF training.”. — Explanation: A crucial research gap is the need to isolate the true effects of Neurofeedback, as the control (sham) stimulation produced similar cognitive improvements, making it difficult to determine which specific measures benefit from the real training. | O75: O artigo aponta lacunas: Necessidade de estudos maiores. Determinar quais medidas cognitivas realmente se beneficiam do Neurofeedback | P75: Não | Q75: Sim | R75: =IF(OR(P75="",Q75=""),"",IF(P75=Q75,"Igual","Diferente")) -> Diferente
A76: ES09 | B76: Journal | C76: Krylova, Marina et al. “Comprehensive Mitigation of Peripheral and Central Stress Responses by Nx4: Insights From EEG and Heart Rate Variability in Post‐Stress Resting State.” Human Psychopharmacology 40 (2025): n. pag. | D76: Clinical Pharmacology | E76: Comprehensive Mitigation of Peripheral and Central Stress Responses by Nx4: Insights From EEG and Heart Rate Variability... | F76: https://onlinelibrary.wiley.com/doi/10.1002/hup.70020?af=R 10.1002/hup.70020 | G76: 2025 | H76: Krylova M, et al. | I76: Germany | K76: PubMed | L76: RQ1 | M76: No evidence Found | N76: No evidence Found | O76: Artigo indisponivel publicamente | R76: =IF(OR(P76="",Q76=""),"",IF(P76=Q76,"Igual","Diferente"))
L77: RQ2 | M77: No evidence Found | N77: No evidence Found | R77: =IF(OR(P77="",Q77=""),"",IF(P77=Q77,"Igual","Diferente"))
L78: RQ3 | M78: No evidence Found | N78: No evidence Found | R78: =IF(OR(P78="",Q78=""),"",IF(P78=Q78,"Igual","Diferente"))
L79: RQ4 | M79: No evidence Found | N79: No evidence Found | R79: =IF(OR(P79="",Q79=""),"",IF(P79=Q79,"Igual","Diferente"))
L80: RQ5 | M80: No evidence Found | N80: No evidence Found | R80: =IF(OR(P80="",Q80=""),"",IF(P80=Q80,"Igual","Diferente"))
L81: RQ6 | M81: No evidence Found | N81: No evidence Found | R81: =IF(OR(P81="",Q81=""),"",IF(P81=Q81,"Igual","Diferente"))
L82: RQ7 | M82: No evidence Found | N82: No evidence Found | R82: =IF(OR(P82="",Q82=""),"",IF(P82=Q82,"Igual","Diferente"))
L83: RQ8 | M83: No evidence Found | N83: No evidence Found | R83: =IF(OR(P83="",Q83=""),"",IF(P83=Q83,"Igual","Diferente"))
L84: RQ9 | M84: No evidence Found | N84: No evidence Found | R84: =IF(OR(P84="",Q84=""),"",IF(P84=Q84,"Igual","Diferente"))
A85: ES10 | B85: Journal | C85: Xin Zhao, Chen Dang, Joseph H.R. Maes, Effects of working memory training on EEG, cognitive performance, and self-report indices potentially relevant for social anxiety, Biological Psychology, Volume 150, 2020, 107840, ISSN 0301-0511, https://doi.org/10.1016/j.biopsycho.2019.107840. (https://www.sciencedirect.com/science/article/pii/S0301051119306246) Abstract: Social anxiety (SA) is quite common and associated with multiple comorbidities. Here, we examined the effects of working memory (WM) training on various indices potentially related to SA. Pre-selected university students with elevated self-reported SA symptoms were assigned to a WM training (n = 21) or an active control treatment condition (n = 21). Pre- and post-treatment assessments were made using questionnaires related to (social) anxiety and depression, and tasks measuring WM, interference control, and attentional biases towards, and event-related potentials (ERPs) elicited by, angry faces. The training enhanced WM transfer task performance, reduced SA symptoms, and changed the amplitude of the P1, N170, P2, and N2 ERP components. However, the latter changes did not mediate the effect of WM training on SA symptoms. These data provide preliminary evidence of the usefulness of WM trainings to reduce potential indices of SA, but further research is necessary to unravel the causal relation among these indices. Keywords: Social anxiety; Working memory training; Attentional bias; Event-related potentials; Students | D85: Biological Psychology | E85: Effects of working memory training on EEG, cognitive performance, and self-report indices potentially relevant for social anxiety | F85: https://doi.org/10.1016/j.biopsycho.2019.107840 | G85: 2020 | H85: Zhao, Xin; Dang, Chen; Maes, Joseph H.R. | I85: Netherlands | K85: Science Direct | L85: RQ1 | M85: Excerpt: “Brain-computer interfaces are divided into non-invasive, semi-invasive, and invasive brain-computer interfaces.” — Explanation: The article defines the three major types of BCI (non-invasive, semi-invasive, invasive) and claims that all are considered for mental-illness treatment. | N85: No evidence Found | O85: O estudo usa EEG não-invasivo para medir event-related potentials (ERPs) durante tarefas cognitivas e emocionais. | P85: Sim | Q85: Não | R85: =IF(OR(P85="",Q85=""),"",IF(P85=Q85,"Igual","Diferente")) -> Diferente | S85: O GPT começou a considerar o EGG não invasivo como BCI não invasivo.
L86: RQ2 | M86: Excerpt: “At present, brain-computer interface has made great progress in the treatment of depression, autism and Cognitive impairment disease … At present, experts are working on the study of diseases such as schizophrenia.” — Explanation: The article lists depression, autism, cognitive impairment conditions, and schizophrenia as mental disorders receiving attention in BCI research. | N86: Excerpt: “Social anxiety (SA) refers to a negative emotional experience caused by people's fear of negative evaluation by others in social situations. Social anxiety disorder (SAD) or social phobia are extreme manifestations of social anxiety. SAD is quite common... and shows a strong comorbidity with various other negative conditions and behaviors, such as drug dependence, sleep disorder, depression, mood disorder...” Explanation: The study primarily investigates Social Anxiety (SA) and Social Anxiety Disorder (SAD), while noting its links to depression and other conditions. | O86: O artigo foca em social anxiety (SA) e sintomas relacionados. | P86: Parcialmente | Q86: Sim | R86: =IF(OR(P86="",Q86=""),"",IF(P86=Q86,"Igual","Diferente")) -> Diferente
L87: RQ3 | M87: Excerpt: “EEG is used to record the brain waves produced by the brain, and by analyzing different frequencies of brain waves, it shows the patient's sleep state and the depth and duration of sleep.” — Explanation: For mental-illness applications (e.g. sleep disorders), the article specifies EEG signal-analysis (brain-wave frequency, sleep state, depth and duration) as a metric for evaluation. | N87: Excerpt: “Pre- and post-treatment assessments were made using questionnaires related to (social) anxiety and depression, and tasks measuring WM, interference control, and attentional biases towards, and event-related potentials (ERPs) elicited by, angry faces.” Explanation: The effectiveness of the intervention was evaluated using a combination of self-report questionnaires, behavioral tasks (dot-probe, Stroop, n-back), and neurophysiological metrics (specifically EEG Event-Related Potentials like P1, N170, P2, and N2). | O87: O estudo usa: Questionários: Liebowitz Social Anxiety Scale (LSAS), STAI-T, Beck Depression Inventory. Tarefas cognitivas: n-back (treino), Stroop (interferência), dot-probe (atenção a faces). EEG/ERP: P1, N170, P2, N2 amplitudes. | P87: Sim | Q87: Sim | R87: =IF(OR(P87="",Q87=""),"",IF(P87=Q87,"Igual","Diferente")) -> Igual
L88: RQ4 | M88: No evidence Found | N88: Excerpt: “WM, specifically WM updating, is an important component of executive functions (Miyake et al., 2000) and strongly linked to the concept of controlled or executive attention (Engle, 2002)... Accordingly, WM updating training might generally enhance attentional control and reduce the influence of more automatic, bottom-up processes putatively underlying symptoms of SA(D).” Explanation: The study explores using Working Memory (WM) training as a method to enhance executive functions (EF) and attentional control, aiming to strengthen the "top-down" cognitive system to regulate anxiety. | O88: O artigo mostra que o treino de memória de trabalho (WM) reduziu sintomas de ansiedade social e melhorou desempenho em tarefas cognitivas. | P88: Não | Q88: Sim | R88: =IF(OR(P88="",Q88=""),"",IF(P88=Q88,"Igual","Diferente")) -> Diferente
L89: RQ5 | M89: Excerpt: “Invasive brain-computer interface may impair parts of the brain's function over time and may be associated with reactive glial cell proliferation and inflammatory responses. … aging, corrosion and replacement of electrodes or chips are also serious problems. … high price of materials, and ethical issues such as privacy leakage after implantation of brain-computer interfaces.” — Explanation: The article identifies technical (electrode degradation, biocompatibility), clinical (long-term safety), and ethical/privacy barriers limiting BCI adoption. | N89: Excerpt: “In recent years, doubts have been raised with respect to the reliability and validity of dot-probe task-based measures of attentional bias. For example, Kappenman, Farrens, Luck, and Proudfit, (2014) and Schmuckle (2005) found a weak internal consistency and/or retest reliability associated with the standard outcome measures of this task.” Explanation: The authors highlight technical/clinical barriers regarding the reliability and validity of standard assessment tools (specifically the dot-probe task) used to measure attentional biases in this field. | O89: O artigo aponta limitações: Resultados preliminares (pequena amostra) e Limites tecnicos. | P89: Sim | Q89: Sim | R89: =IF(OR(P89="",Q89=""),"",IF(P89=Q89,"Igual","Diferente")) -> Igual
L90: RQ6 | M90: Excerpt: “ethical issues such as privacy leakage after implantation of brain-computer interfaces.” — Explanation: The article mentions privacy leakage as an ethical/data-security concern, touching on the issue of neural-data integrity/security. | N90: No evidence Found | O90: O artigo não discute segurança ou privacidade dos dados neurais. | P90: Não | Q90: Sim | R90: =IF(OR(P90="",Q90=""),"",IF(P90=Q90,"Igual","Diferente")) -> Diferente
L91: RQ7 | M91: No evidence Found | N91: No evidence Found | O91: O artigo não aborda IA ou neuroestimulação personalizada. | P91: Sim | Q91: Sim | R91: =IF(OR(P91="",Q91=""),"",IF(P91=Q91,"Igual","Diferente")) -> Igual
L92: RQ8 | M92: No evidence Found | N92: No evidence Found | O92: Não há discussão ética ou filosófica sobre expansão neurológica. | P92: Sim | Q92: Sim | R92: =IF(OR(P92="",Q92=""),"",IF(P92=Q92,"Igual","Diferente")) -> Igual
L93: RQ9 | M93: Excerpt: “the application of this technology is still in its infancy … more research and experiments are needed to verify its effectiveness and safety.” — Explanation: The authors explicitly note that BCI applications for mental illness remain nascent and call for further research to establish effectiveness and safety, indicating research gaps. | N93: Excerpt: “These data provide preliminary evidence of the usefulness of WM trainings to reduce potential indices of SA, but further research is necessary to unravel the causal relation among these indices.” Explanation: The conclusion identifies a research gap concerning the causal mechanisms between cognitive training, symptom reduction, and neurophysiological changes, necessitating further study to confirm how these factors influence each other. | O93: O artigo aponta lacunas: Necessidade de mais estudos para confirmar relação causal entre treino, ERPs e melhora clínica. | P93: Sim | Q93: Sim | R93: =IF(OR(P93="",Q93=""),"",IF(P93=Q93,"Igual","Diferente")) -> Igual
A94: ES11 | B94: Journal | C94: Zozan Guleken, Gökçer Eskikurt, Sacit Karamürsel, Investigation of the effects of transcranial direct current stimulation and neurofeedback by continuous performance test, Neuroscience Letters, Volume 716, 2020, 134648, ISSN 0304-3940, https://doi.org/10.1016/j.neulet.2019.134648. (https://www.sciencedirect.com/science/article/pii/S0304394019307517) Abstract: Transcranial direct current stimulation (tDCS) is a noninvasive neuromodulation technique based on weak direct current stimulation through the scalp. Neurofeedback (NFB) is a learning strategy that may help alter to brain wave parameters, by monitoring electroencephalography (EEG) feedback via special programs. We aimed to investigate the supportive effects of tDCS in addition to NFB training. 16 healthy volunteers were divided equally into two groups. One of the groups was trained by NFB with the sensorimotor rhythm (SMR) protocol; 2 days per week, 10 sessions of 30 min, the other group received 10 min of tDCS before each NFB sessions. Continuous Performance Test (CPT) was used to measure, response time and suppression and to determine selective attention condition. Also, Beck Depression and Anxiety Inventories were used to exclude people with depression and anxiety. Depression scores of NFB + tDCS group were decreased significantly. CPT scores were better at last sessions for both groups compared to the first sessions. Sessions were analyzed by comparing 1st, 2nd, 5th and 10th sessions. While the NFB + tDCS group had statistically significant changes at theta/beta ratios with SMR and alpha band amplitudes, NFB group statistics had changed at theta/SMR ratios. NFB training shows its effects at the end of 10 sessions. Despite an increase in the latencies of correct and commission responses on the task of CPT, additional use of tDCS improves cognitive performance. Also, tDCS has a supportive effect on the healthy participants who have mild anxiety and depression; also inhibition deficits of subjects were clear. Keywords: Neurofeedback; Transcranial direct current stimulation; Continuous performance test; Sensorimotor rhythm; Inhibition; Neuromodulation | D94: Neuroscience Letters | E94: Investigation of the effects of transcranial direct current stimulation and neurofeedback by continuous performance test | F94: https://doi.org/10.1016/j.neulet.2019.134648 | G94: 2020 | H94: Guleken, Zozan; Eskikurt, Gökçer; Karamürsel, Sacit | I94: Turkey | K94: Science Direct | L94: RQ1 | M94: Excerpt: “Transcranial direct current stimulation (tDCS) is a noninvasive neuromodulation technique based on weak direct current stimulation through the scalp.” — Explanation: This article describes the BCI methods used (tDCS and neurofeedback via EEG) as noninvasive, showing that non‑invasive BCIs are the dominant type in this mental‑health / cognitive‑performance context. | N94: Excerpt: “Transcranial direct current stimulation (tDCS) is a noninvasive neuromodulation technique based on weak direct current stimulation through the scalp. Neurofeedback (NFB) is a learning strategy that may help alter to brain wave parameters...” Explanation: The article defines and utilizes two non-invasive techniques: Transcranial Direct Current Stimulation (tDCS) and Neurofeedback (NFB) , classifying them as non-invasive neuromodulation and learning strategies respectively. | O94: O estudo usa duas técnicas não-invasivas: Neurofeedback (NFB) via EEG. Transcranial Direct Current Stimulation (tDCS). | P94: Sim | Q94: Sim | R94: =IF(OR(P94="",Q94=""),"",IF(P94=Q94,"Igual","Diferente")) -> Igual
L95: RQ2 | M95: Excerpt: “tDCS … had positive results on patients addicted to smoke, drug, alcohol, methamphetamines and cocaine who have problems with selective attention [5–7].” And also: “tDCS has positive effects on psychiatric disorders and may be used as an additional treatment tool.” — Explanation: Though the present study used healthy volunteers, the authors reference prior research on substance‑use disorders (“addicted to smoke, drug, alcohol, … methamphetamines and cocaine”) and more broadly “psychiatric disorders,” implying that addiction and related disorders have received attention in BCI applications. | N95: Excerpt: “Also, tDCS has a supportive effect on the healthy participants who have mild anxiety and depression...” Explanation: While the study was conducted on healthy volunteers, it specifically investigated the effects on mild anxiety and depression symptoms, and used clinical inventories for these conditions. | O95: O artigo não foca em pacientes clínicos, mas em voluntários saudáveis. Ainda assim, mede depressão e ansiedade leves com inventários de Beck. | P95: Sim | Q95: Sim | R95: =IF(OR(P95="",Q95=""),"",IF(P95=Q95,"Igual","Diferente")) -> Igual
L96: RQ3 | M96: Excerpt: “Continuous Performance Test (CPT) was used to measure, response time and suppression and to determine selective attention condition.” And: “Through NFB applications, average amplitudes of the delta, theta, alpha, SMR, beta1, beta2 bands and theta/SMR and theta/beta ratios were obtained.” And also: “Also, pre- and after-training BDI and BAI scores were compared.” — Explanation: The study uses behavioral metrics (CPT: correct/commission/omission responses and reaction times), EEG spectral measures (amplitude of various bands and band‑ratios), and self-report inventories for depression/anxiety (BDI/BAI) to evaluate effectiveness of the BCI interventions. | N96: Excerpt: “Continuous Performance Test (CPT) was used to measure, response time and suppression and to determine selective attention condition. Also, Beck Depression and Anxiety Inventories were used...” Explanation: The study evaluated effectiveness using the Continuous Performance Test (CPT) for cognitive metrics (attention, response time) and the Beck Depression and Anxiety Inventories (BDI, BAI) for psychological symptom scoring. | O96: O estudo usa: Continuous Performance Test (CPT) para atenção seletiva e inibição. Inventários Beck de Depressão (BDI) e Ansiedade (BAI). EEG bandas (theta, alpha, SMR, beta) e suas razões. | P96: Sim | Q96: Sim | R96: =IF(OR(P96="",Q96=""),"",IF(P96=Q96,"Igual","Diferente")) -> Igual
L97: RQ4 | M97: Excerpt: “The test aimed to observe random changes to the given stimuli.” (CPT measuring selective attention, response time and suppression). And: “In this study, the selective attention and inhibition effect of the theta/SMR protocol supports previous studies.” — Explanation: The article shows that BCI (NFB, with or without tDCS) was used to enhance cognitive functions such as selective attention and response inhibition. Although memory is not directly measured, attention and inhibitory control—key cognitive abilities—are assessed. | N97: Excerpt: “Despite an increase in the latencies of correct and commission responses on the task of CPT, additional use of tDCS improves cognitive performance.” Explanation: The research specifically aimed to enhance cognitive abilities, finding that the addition of tDCS to Neurofeedback training improves cognitive performance as measured by the CPT. | O97: O artigo mostra que NFB e tDCS melhoraram: Atenção seletiva (menos erros no CPT). Inibição (redução de comissões e omissões). Desempenho cognitivo (melhora em bandas EEG ligadas à atenção e memória). | P97: Sim | Q97: Sim | R97: =IF(OR(P97="",Q97=""),"",IF(P97=Q97,"Igual","Diferente")) -> Igual
L98: RQ5 | M98: Excerpt: “additional trainings and tDCS applications are needed in a larger subject group using different protocols to improve values of tDCS studies.” — Explanation: The only “limitation” mentioned is the small sample size and the need for further studies with larger groups and varied protocols. The article does not discuss technical or ethical barriers explicitly, so broader barriers remain unaddressed. | N98: No evidence Found | O98: O artigo aponta limitações: Pequeno tamanho da amostra (n=16). Resultados preliminares em voluntários saudáveis (não pacientes). Necessidade de mais sessões para efeitos robustos. | P98: Sim | Q98: Não | R98: =IF(OR(P98="",Q98=""),"",IF(P98=Q98,"Igual","Diferente")) -> Diferente
L99: RQ6 | M99: No evidence Found | N99: No evidence Found | O99: O artigo não discute segurança ou privacidade dos dados neurais. | P99: Sim | Q99: Sim | R99: =IF(OR(P99="",Q99=""),"",IF(P99=Q99,"Igual","Diferente")) -> Igual
L100: RQ7 | M100: No evidence Found | N100: No evidence Found | O100: O artigo não menciona IA | P100: Sim | Q100: Sim | R100: =IF(OR(P100="",Q100=""),"",IF(P100=Q100,"Igual","Diferente")) -> Igual
...

Sheet Questões + Prompt
A1: PROMPT | B1: Task: Read the article and extract verbatim excerpts (exact text) that answer each Research Question (RQ). If the article does not answer an RQ, write: “No evidence found.” Also add a 1–2 sentence explanation for each answer. Return the final output as a table with two columns: | RQ | Response (Excerpt + Explanation) | Research Questions (do not modify): RQ1: What types of Brain-Computer Interfaces (invasive, non-invasive, hybrid) have been most used in mental health applications? RQ2: Which mental disorders have received the most attention in research involving BCIs (e.g., depression, anxiety, schizophrenia, ADHD)? RQ3: What metrics and evaluation methods are used to measure the effectiveness of BCIs in the treatment of mental disorders? RQ4: How have BCIs been used to enhance cognitive abilities such as memory, attention, and learning? RQ5: What are the main technical, clinical, and ethical barriers limiting the adoption of BCIs in therapeutic and human enhancement contexts? RQ6: How do current studies address issues of security, privacy, and integrity of neural data collected by BCIs? RQ7: What emerging trends point to the future of BCIs in integration with artificial intelligence and personalized neurostimulation? RQ8: How does the scientific literature address the ethical and philosophical aspects of "neurological expansion" and the amplification of human capabilities? RQ9: What research gaps still need to be explored for BCIs to become an effective and safe tool in mental healthcare and cognitive enhancement? Output Format (strict): Produce a table like this: RQ Response RQ1 Excerpt: “…” — Explanation: … RQ2 Excerpt: “…” — Explanation: … RQ3 Excerpt: “…” — Explanation: … RQ4 Excerpt: “…” — Explanation: … RQ5 Excerpt: “…” — Explanation: … RQ6 Excerpt: “…” — Explanation: … RQ7 Excerpt: “…” — Explanation: … RQ8 Excerpt: “…” — Explanation: … RQ9 Excerpt: “…” — Explanation: … Rules: – Use exact quoted text from the article (no paraphrasing). – Excerpt and Explanation must appear together in the same cell. – Choose the most relevant excerpt for each RQ. – If no answer exists, write “No evidence found.”
A2: RQ1: | B2: <<What types of Brain-Computer Interfaces (invasive, non-invasive, hybrid) have been most used in mental health applications?>> | C2: Quais tipos de Interfaces Cérebro-Computador (invasivas, não invasivas, híbridas) têm sido mais utilizadas em aplicações voltadas à saúde mental?
A3: RQ2: | B3: <<Which mental disorders have received the most attention in research involving BCIs (e.g., depression, anxiety, schizophrenia, ADHD)?>> | C3: Quais transtornos mentais têm recebido maior atenção nas pesquisas envolvendo BCIs (por exemplo, depressão, ansiedade, esquizofrenia, TDAH)?
A4: RQ3: | B4: <<What metrics and evaluation methods are used to measure the effectiveness of BCIs in the treatment of mental disorders?>> | C4: Quais métricas e métodos de avaliação são empregados para medir a eficácia das BCIs no tratamento de distúrbios mentais?
A5: RQ4: | B5: <<How have BCIs been used to enhance cognitive abilities such as memory, attention, and learning?>> | C5: De que forma as BCIs têm sido utilizadas para aprimorar capacidades cognitivas, como memória, atenção e aprendizado?
A6: RQ5: | B6: <<What are the main technical, clinical, and ethical barriers limiting the adoption of BCIs in therapeutic and human enhancement contexts?>> | C6: Quais são as principais barreiras técnicas, clínicas e éticas que limitam a adoção de BCIs em contextos terapêuticos e de amplificação humana?
A7: RQ6: | B7: <<How do current studies address issues of security, privacy, and integrity of neural data collected by BCIs?>> | C7: Como os estudos atuais abordam questões de segurança, privacidade e integridade dos dados neurais coletados por BCIs?
A8: RQ7: | B8: <<What emerging trends point to the future of BCIs in integration with artificial intelligence and personalized neurostimulation?>> | C8: Quais tendências emergentes apontam para o futuro das BCIs na integração com inteligência artificial e neuroestimulação personalizada?
A9: RQ8: | B9: <<How does the scientific literature address the ethical and philosophical aspects of "neurological expansion" and the amplification of human capabilities?>> | C9: Como a literatura científica trata os aspectos éticos e filosóficos da “expansão neurológica” e da amplificação das capacidades humanas?
A10: RQ9: | B10: <<What research gaps still need to be explored for BCIs to become an effective and safe tool in healthcare? mental e no aprimoramento cognitivo?>> | C10: Quais lacunas de pesquisa ainda precisam ser exploradas para que as BCIs se tornem uma ferramenta efetiva e segura na saúde mental e no aprimoramento cognitivo?

Sheet Extração
A1: ,sss
A2: LLM2: GEMINI
A3: ID do artigo | B3: Tipo de publicação | C3: Citação | D3: Local de publicação | E3: Título | F3: Link | G3: Ano | H3: Autores | I3: País | J3: Área de estudo | K3: Base de Dados | L3: RQ (Pergunta de Pesquisa) | M3: Extração LLM 1 (ChatGPT) | N3: Extração LLM 2 (Gemini) | O3: Extração validada (humana) | P3: ChatGPT acertou? | Q3: Gemini acertou? | R3: Concordância entre LLMs | S3: Observações / Comentários
A4: S1 | B4: Journal | C4: Zhao X, Dang C, Maes JHR. Effects of working memory training on EEG, cognitive performance, and self-report indices potentially relevant for social anxiety. Biol Psychol. 2020 Feb;150:107840. doi: 10.1016/j.biopsycho.2019.107840. Epub 2020 Jan 2. PMID: 31904404. | D4: Biological Psychology | E4: Effects of working memory training on EEG, cognitive performance, and self-report indices potentially relevant for social anxiety | F4: PubMed | G4: 2020 | H4: Xin Zhao, Chen Dang, Joseph H R Maes | I4: China | J4: Psicologia Cognitiva | K4: PubMed | L4: RQ1 | M4: RQ1 — Excerpt: “No evidence found.” | Explanation: The article does not mention any Brain-Computer Interfaces (invasive, non-invasive, or hybrid). It focuses exclusively on working memory training and EEG as a measurement tool, not as a BCI. | N4: RQ1 — Excerpt: “No evidence found.” | Explanation: The article is a specific experimental study on Working Memory training using EEG/ERPs as measurement tools and does not review or categorize the types of Brain-Computer Interfaces (invasive, non-invasive, hybrid) most used in general mental health applications. | O4: Este artigo não trata diretamente de BCIs. Ele aborda treinamento de memória de trabalho (WM training) e medidas de EEG/ERP em estudantes com sintomas de ansiedade social. Portanto, não responde à RQ1. | P4: Sim | Q4: Sim | R4: =IF(OR(P4="",Q4=""),"",IF(P4=Q4,"Igual","Diferente")) -> Igual | S4: As respostas das duas LLMs apresentam alta concordância tanto no trecho citado quanto na explicação. Trecho citado (Excerpt): Ambas indicam “No evidence found.”, mostrando total acordo na conclusão sobre a ausência de informações relevantes no artigo quanto a BCIs. Explicação (Explanation): As duas LLMs apontam que o artigo foca em treinamento de memória de trabalho usando EEG como ferramenta de medida, e não em BCIs. A diferença está no detalhamento: a segunda (Gemini) menciona explicitamente ERPs e enfatiza que o artigo não revisa ou categoriza os tipos de BCIs em aplicações gerais de saúde mental.
I5: Netherlands | L5: RQ2 | M5: RQ2 — Excerpt: “No evidence found.” | Explanation: The study examines only social anxiety and does not reference other mental disorders in the context of BCI usage, nor does it discuss BCIs at all. | N5: RQ2 — Excerpt: “No evidence found.” | Explanation: The study focuses exclusively on Social Anxiety (SA) and does not provide a review or comparison of which mental disorders (such as depression, anxiety, schizophrenia, ADHD) have received the most attention in research involving BCIs. | O5: O artigo foca especificamente em ansiedade sociall. Trecho que destaca isso: “Social anxiety (SA) is quite common and associated with multiple comorbidities. Here, we examined the effects of working memory (WM) training on various indices potentially related to SA.” | P5: Sim | Q5: Sim | R5: =IF(OR(P5="",Q5=""),"",IF(P5=Q5,"Igual","Diferente")) -> Igual
L6: RQ3 | M6: RQ3 — Excerpt: “No evidence found.” | Explanation: The paper does not evaluate any BCI effectiveness. Its metrics concern cognitive tasks (WM, Stroop, dot-probe), EEG components (P1, N170, P2, N2), and self-report scales—not BCI outcomes. | N6: RQ3 — Excerpt: “Pre- and post-treatment assessments were made using questionnaires related to (social) anxiety and depression, and tasks measuring WM, interference control, and attentional biases towards, and event-related potentials (ERPs) elicited by, angry faces.” | Explanation: The evaluation methods used in this neuro-cognitive study include self-report measures (questionnaires), behavioral performance on cognitive tasks (WM, interference control), and electrophysiological signals (ERPs) recorded by EEG. | O6: Embora não seja um estudo de BCI, ele usa tals métricas de avaliação de treinamento cognitivo: Questionários: Liebowitz Social Anxiety Scale (LSAS), State-Trait Anxiety Inventory (STAI-T), Beck Depression Inventory (BDI-13). Tarefas cognitivas: Automated Operation Span Task (Aospan), Stroop Task, Dot-Probe Task. Medidas neurofisiológicas: ERP componentes P1, N170, P2, N2. | P6: Sim | Q6: Parcialmente | R6: =IF(OR(P6="",Q6=""),"",IF(P6=Q6,"Igual","Diferente")) -> Diferente | S6: O GPT teve a mesma percepção que a extração Humana
L7: RQ4 | M7: RQ4 — Excerpt: “working memory (WM) training… enhanced WM transfer task performance” | Explanation: Although the study is unrelated to BCIs, it does address cognitive enhancement—specifically improvements in working memory through behavioral training, not through BCI technology. | N7: RQ4 — Excerpt: “One treatment that, at least theoretically, could enhance the inﬂuence of the top-down system by strengthening EF is working memory (WM) training. WM, speciﬁcally WM updating, is an important component of executive functions... Accordingly, WM updating training might generally enhance attentional control and reduce...” | Explanation: The article explains that WM training, which strengthens Executive Function (EF), is a mechanism that can theoretically enhance cognitive abilities like attentional control, which in turn helps reduce anxiety symptoms. | O7: O artigo não usa BCI, mas mostra que treinamento de memória de trabalho pode melhorar atenção e reduzir sintomas de ansiedade, segundo tal trecho: “The training enhanced WM transfer task performance, reduced SA symptoms, and changed the amplitude of the P1, N170, P2, and N2 ERP components.” | P7: Sim | Q7: Parcialmente | R7: =IF(OR(P7="",Q7=""),"",IF(P7=Q7,"Igual","Diferente")) -> Diferente | S7: O GPT teve a mesma percepção que a extração Humana
L8: RQ5 | M8: RQ5 — Excerpt: “No evidence found.” | Explanation: The article does not discuss technical, clinical, or ethical barriers related to the use of BCIs in therapy or human enhancement. | N8: RQ5 — Excerpt: “No evidence found.” | Explanation: The article is an experimental report, not a systematic review, and therefore does not discuss or list the main technical, clinical, and ethical barriers that generally limit the adoption of BCI technology. | O8: O artigo não discute barreiras técnicas/éticas de BCI. | P8: Sim | Q8: Sim | R8: =IF(OR(P8="",Q8=""),"",IF(P8=Q8,"Igual","Diferente")) -> Igual
L9: RQ6 | M9: RQ6 — Excerpt: “No evidence found.” | Explanation: Nothing in the study addresses data security, privacy, or integrity of neural data in the context of BCIs. EEG is used only as a standard research measurement tool without discussion of neurodata ethics. | N9: RQ6 — Excerpt: “No evidence found.” | Explanation: The article is focused on the results of a training intervention for social anxiety and does not contain any discussion regarding the security, privacy, or integrity protocols for the neural data collected via EEG. | O9: Não há menção a segurança ou privacidade de dados neurais. | P9: Sim | Q9: Sim | R9: =IF(OR(P9="",Q9=""),"",IF(P9=Q9,"Igual","Diferente")) -> Igual
L10: RQ7 | M10: RQ7 — Excerpt: “No evidence found.” | Explanation: The paper does not mention emerging trends involving BCIs, AI integration, or personalized neurostimulation. | N10: RQ7 — Excerpt: “No evidence found.” | Explanation: The article is an original research paper detailing the results of an experiment and does not discuss or identify emerging trends regarding the future integration of BCIs with artificial intelligence or personalized neurostimulation. | O10: O artigo não aborda integração com IA ou neuroestimulação personalizada. | P10: Sim | Q10: Sim | R10: =IF(OR(P10="",Q10=""),"",IF(P10=Q10,"Igual","Diferente")) -> Igual
L11: RQ8 | M11: RQ8 — Excerpt: “No evidence found.” | Explanation: No ethical or philosophical reflections on “neurological expansion” or human capability amplification appear in the text. | N11: RQ8 — Excerpt: “No evidence found.” | Explanation: The article is a clinical study on anxiety treatment and does not engage with the broader ethical and philosophical aspects of "neurological expansion" or the general amplification of human capabilities. | O11: Não há discussão ética ou filosófica sobre expansão neurológica. | P11: Sim | Q11: Sim | R11: =IF(OR(P11="",Q11=""),"",IF(P11=Q11,"Igual","Diferente")) -> Igual
L12: RQ9 | M12: RQ9 — Excerpt: “No evidence found.” | Explanation: The article does not identify research gaps regarding BCIs; its discussion focuses only on working memory training, cognitive transfer, attentional bias, social anxiety, and EEG markers. | N12: RQ9 — Excerpt: “However, given methodological limitations, these results must be regarded as preliminary, and future research should further unravel the causal re-lation among the various indices of social anxiety and the eﬀect of WM training thereupon.” | Explanation: The key research gap identified in the conclusion is the need for future studies to fully determine and explain the causal relationship between the working memory training intervention and the observed changes in symptoms and neural indices of social anxiety. | O12: O artigo aponta lacunas sobre treinamento de memória e ansiedade social, mas não sobre o contexto BCIs: “These data provide preliminary evidence of the usefulness of WM trainings to reduce potential indices of SA, but further research is necessary to unravel the causal relation among these indices.” | P12: Sim | Q12: Não | R12: =IF(OR(P12="",Q12=""),"",IF(P12=Q12,"Igual","Diferente")) -> Diferente | S12: O gemini não considerou o contexto que deveria está ligado a BCIs
A13: s2 | B13: Journal | C13: Kumar S, Zomorrodi R, Ghazala Z, Goodman MS, Blumberger DM, Daskalakis ZJ, Fischer CE, Mulsant BH, Pollock BG, Rajji TK. Effects of repetitive paired associative stimulation on brain plasticity and working memory in Alzheimer's disease: a pilot randomized double-blind-controlled trial. Int Psychogeriatr. 2023 Mar;35(3):143-155. doi: 10.1017/S1041610220003518. Epub 2020 Nov 16. PMID: 33190659. | D13: international psychogeriatrics | E13: Effects of repetitive paired associative stimulation on brain plasticity and working memory in Alzheimer's disease: a pilot randomized double-blind-controlled trial | F13: PubMed | G13: 2020 | H13: Sanjeev Kumar, Reza Zomorrodi, Zaid Ghazala, Michelle S Goodman, Daniel M Blumberger, Zafiris J Daskalakis, Corinne E Fischer, Benoit H Mulsant, Bruce G Pollock, Tarek K Rajji | I13: Canada | J13: Neurociência; Neurologia; Reabilitação Cognitiva | K13: PubMed | L13: RQ1 | M13: RQ1 — Excerpt: “No evidence found.” | Explanation: The article contains no references to Brain-Computer Interfaces (BCIs), whether invasive, non-invasive, or hybrid. | N13: RQ1 — Excerpt: “No evidence found.” | Explanation: The article is a specific clinical trial on repetitive paired associative stimulation (rPAS)/Transcranial Magnetic Stimulation (TMS) for Alzheimer's disease. It does not contain a general summary or comparative analysis of the most used types (invasive, non-invasive, hybrid) of Brain-Computer Interfaces across all mental health applications. | O13: Este estudo não utiliza diretamente BCIs clássicos, mas sim estimulação cerebral não invasiva: “Pilot randomized double-blind-controlled trial of repetitive paired associative stimulation (rPAS), a paradigm that combines transcranial magnetic stimulation (TMS) of the dorsolateral prefrontal cortex (DLPFC) with peripheral median nerve stimulation.” Isso se aproxima de BCI não-invasivo, pois envolve TMS + EEG para medir plasticidade e desempenho cognitivo mas não é de fato. | P13: Parcialmente | Q13: Parcialmente | R13: =IF(OR(P13="",Q13=""),"",IF(P13=Q13,"Igual","Diferente")) -> Igual | S13: Algumas coisas podem ser consideradas por se aproximarem de BCIs não invasivos
L14: RQ2 | M14: RQ2 — Excerpt: “No evidence found.” | Explanation: The paper does not discuss mental disorders in relation to BCIs. Any mental health content in the article is unrelated to brain–computer interfaces. | N14: RQ2 — Excerpt: “No evidence found.” | Explanation: The research article focuses specifically on Alzheimer's disease (AD) and its related cognitive deficits. It does not provide a comprehensive review or a list of which mental disorders (like depression, anxiety, or schizophrenia) have received the most attention in the broader field of BCI research. | O14: O artigo trata especificamente da doença de alzheimer, mas não em relação a BCIs. | P14: Sim | Q14: Sim | R14: =IF(OR(P14="",Q14=""),"",IF(P14=Q14,"Igual","Diferente")) -> Igual
L15: RQ3 | M15: RQ3 — Excerpt: “No evidence found.” | Explanation: The study does not evaluate BCI effectiveness, and therefore contains no metrics, evaluation methods, or outcomes related to BCIs. | N15: RQ3 — Excerpt: “DLPFC plasticity was assessed using single session PAS combined with electroencephalography (EEG) at baseline and on days 1, 7, and 14 post-rPAS. Working memory and theta-gamma coupling were assessed at the same time points using the N-back task and EEG.” | Explanation: In this study using a neurostimulation paradigm, the key metrics were DLPFC plasticity (measured by PAS-LTP via EEG), working memory performance (measured by the N-back task/A' score), and the corresponding theta-gamma coupling (measured by the Modulation Index via EEG). | O15: O artigo usa várias métricas, mas não relacionadas a BCIs: 1. Plasticidade cortical (PAS-LTP) medida por TMS-EEG. 2. Desempenho em memória de trabalho via N-back task. 3. Oscilações neurais: theta–gamma coupling. | P15: Parcialmente | Q15: Parcialmente | R15: =IF(OR(P15="",Q15=""),"",IF(P15=Q15,"Igual","Diferente")) -> Igual | S15: O GPT não destacou as metricas, mesmo que não relacionadas ao BCIs. O Gemini não destacou que as metricas não se relacionavam ao BCIs.
L16: RQ4 | M16: RQ4 — Excerpt: “No evidence found.” | Explanation: Although the article may involve cognitive or behavioral constructs, it does not describe the use of BCIs for enhancing memory, attention, or learning. | N16: RQ4 — Excerpt: “Thus, DLPFC plasticity could be an appropriate potential target and an intermediate marker for interventions aimed at enhancing work- ing memory in AD.” | Explanation: The article specifically addresses the use of rPAS (a TMS paradigm related to neurostimulation) as an intervention aimed at enhancing the cognitive ability of working memory by targeting DLPFC plasticity in patients with Alzheimer’s disease. | O16: O artigo mostra que o rPAS foi usado para tentar melhorar memória de trabalho em pacientes com Alzheimer. | P16: Sim | Q16: Parcialmente | R16: =IF(OR(P16="",Q16=""),"",IF(P16=Q16,"Igual","Diferente")) -> Diferente
L17: RQ5 | M17: RQ5 — Excerpt: “No evidence found.” | Explanation: There is no discussion of technical, clinical, or ethical barriers to the adoption of BCIs. | N17: RQ5 — Excerpt: “The top reason for failing screen was the travel and time commitment to the study, which raises the importance of adapting noninvasive brain stimulation to less mobile popula- tions such as AD.” | Explanation: While the article does not provide a comprehensive list of all technical, clinical, and ethical barriers in the field, it highlights a major logistical/clinical barrier in its own study: the high time commitment of the noninvasive brain stimulation protocol limited recruitment from less mobile patient populations | O17: O artigo não discute barreiras éticas ou técnicas de forma ampla. Ele apenas menciona limitações metodológicas. | P17: Sim | Q17: Parcialmente | R17: =IF(OR(P17="",Q17=""),"",IF(P17=Q17,"Igual","Diferente")) -> Diferente
L18: RQ6 | M18: RQ6 — Excerpt: “No evidence found.” | Explanation: The article does not address neural data security, privacy, or integrity in the context of BCIs. | N18: RQ6 — Excerpt: “No evidence found.” | Explanation: The article confirms that the study was approved by an Ethics Board and participants provided informed consent, but it does not contain any discussion, statement, or protocol details regarding the specific issues of security, privacy, or integrity of the collected neural (EEG) data. | O18: Não há menção a segurança ou privacidade dos dados neurais. | P18: Sim | Q18: Sim | R18: =IF(OR(P18="",Q18=""),"",IF(P18=Q18,"Igual","Diferente")) -> Igual
L19: RQ7 | M19: RQ7 — Excerpt: “No evidence found.” | Explanation: The paper does not mention emerging BCI trends, nor AI-BCI integration or personalized neurostimulation. | N19: RQ7 — Excerpt: “No evidence found.” | Explanation: The article focuses on future directions for the specific rPAS protocol (e.g., longer duration, alternative stimulation sites) but does not address emerging trends in the integration of BCIs with artificial intelligence or generalized personalized neurostimulation. | O19: O artigo não aborda IA ou neuroestimulação personalizada. | P19: Sim | Q19: Sim | R19: =IF(OR(P19="",Q19=""),"",IF(P19=Q19,"Igual","Diferente")) -> Igual
L20: RQ8 | M20: RQ8 — Excerpt: “No evidence found.” | Explanation: The article includes no ethical or philosophical discussion regarding neural enhancement or “neurological expansion.” | N20: RQ8 — Excerpt: “No evidence found.” | Explanation: The research is a clinical trial focused on a therapeutic intervention for a disease (Alzheimer's). It does not contain any philosophical or ethical commentary on the broader concepts of "neurological expansion" or the amplification of general human capabilities. | O20: Não há discussão ética ou filosófica sobre expansão neurológica. | P20: Sim | Q20: Sim | R20: =IF(OR(P20="",Q20=""),"",IF(P20=Q20,"Igual","Diferente")) -> Igual
L21: RQ9 | M21: RQ9 — Excerpt: “No evidence found.” | Explanation: The paper does not identify research gaps related to BCI applications in mental health or cognitive enhancement. | N21: RQ9 — Excerpt: “Future well-powered studies targeting such a population are needed, and if successful, additional studies should assess the effects of rPAS on other biological markers and behavioral symptoms of AD and as well as focus on overcoming barriers to implementation of rPAS for clinical use.” | Explanation: The primary research gaps highlighted are the need for larger, adequately powered studies, the need to assess effects on biological markers and behavioral symptoms, and the requirement to overcome implementation barriers for the neurostimulation technique to be translated into effective clinical care. | O21: O artigo aponta lacunas da abordagem de tratamento rPAS, mas não relacionadas ao BCIs ou coisas relacionadas. | P21: Sim | Q21: Não | R21: =IF(OR(P21="",Q21=""),"",IF(P21=Q21,"Igual","Diferente")) -> Diferente | S21: O gemini não levou em conta a necissade da relação com o tema de pesquisa da revisão sistematica.
A22: S3 | B22: Journal | C22: Zhang K, Ji Y, Guo X, Gao T, Zhang X, Yu X, Wang J. The aperiodic and periodic activities of EEG dynamically relate with cognitive performance in schizophrenia. Schizophr Res Cogn. 2025 Jul 31;42:100383. doi: 10.1016/j.scog.2025.100383. PMID: 40792221; PMCID: PMC12337643. | D22: Schizophrenia Research: Cognition | E22: The aperiodic and periodic activities of EEG dynamically relate with cognitive performance in schizophrenia | F22: PubMed | G22: 2025 | H22: Kexin Zhang, Yunfei Ji, Xiaodong Guo, Tianqi Gao, Xuemin Zhang, Xin Yu, Jing Wang | I22: China | K22: PubMed | L22: RQ1 | M22: Excerpt: “No evidence found.” — Explanation: The article studies EEG aperiodic/periodic activity in schizophrenia and does not mention any Brain-Computer Interface (BCI) technology. | N22: No evidence found. The article describes the use of EEG, a non-invasive technique, in a research study on schizophrenia but does not provide a general review or comparison of the most used BCI types (invasive, non-invasive, hybrid) in mental health applications. | O22: Este estudo não usa diretamente BCIs, mas sim EEG (eletroencefalografia) para investigar atividade periódica e aperiódica em pacientes com esquizofrenia: “Before and after the language comprehension tasks (humor, metaphor and irony), the 5-min eyes-closed and eyes-open EEG signals were collected respectively.” | P22: Sim | Q22: Sim | R22: =IF(OR(P22="",Q22=""),"",IF(P22=Q22,"Igual","Diferente")) -> Igual
L23: RQ2 | M23: Excerpt: “No evidence found.” — Explanation: The study only involves schizophrenia and does not examine BCIs or their application to any mental disorders. | N23: No evidence found. The article focuses on schizophrenia (SCZ) and mentions related studies on chronic psychotic disorders and trait anxiety only in passing, but it does not review or state which mental disorder has received the most attention in BCI research. | O23: O artigo foca em esquizofrenia, mas não é relacionada ao uso de BCIs | P23: Sim | Q23: Sim | R23: =IF(OR(P23="",Q23=""),"",IF(P23=Q23,"Igual","Diferente")) -> Igual
L24: RQ3 | M24: Excerpt: “Power spectral density (PSD) helped to decompose EEG signals…”, “…aperiodic exponent and periodic power were extracted…”, and “Cognitive performance was assessed using the total Brief Assessment of Cognition in Schizophrenia (BACS).” main — Explanation: The study evaluates EEG effectiveness using PSD, aperiodic exponent, alpha/beta power, and correlates them with BACS cognitive test scores. These are EEG metrics, not BCI evaluation metrics. | N24: No evidence found. The paper describes metrics (BACS, Z scores) and methods (Pearson correlation, ANOVA) for assessing cognitive deficits in SCZ, but it does not discuss how to measure the effectiveness of BCIs in treatment. | O24: O estudo utiliza: EEG (aperiodic exponent, alpha e beta band power). Brief Assessment of Cognition in Schizophrenia (BACS). Tasks de compreensão de linguagem figurativa (humor, metáfora, ironia). | P24: Sim | Q24: Parcialmente | R24: =IF(OR(P24="",Q24=""),"",IF(P24=Q24,"Igual","Diferente")) -> Diferente
L25: RQ4 | M25: Excerpt: “The aperiodic exponent…showed significantly negative correlation with Z scores of humor comprehension tasks…” and “pre-tasks aperiodic exponent…positively correlated with T scores of attention and speed of information processing.” main — Explanation: The article links EEG spectral features to cognitive functions such as attention, processing speed, and language comprehension, but does not use BCIs for cognitive enhancement. | N25: No evidence found. The paper states that the aperiodic exponent relates to cognitive functions like "attention (Tagliazucchi et al., 2013), working memory (Kardan et al., 2020), motor performance (Immink et al., 2021) and academic learning (Cross et al., 2022)"1111, but it does not describe the use of BCIs for enhancing these abilities. | O25: O artigo mostra correlações entre EEG(não com BCIs) e desempenho cognitivo (atenção, velocidade de processamento, compreensão de humor/metáfora): “The pre-tasks aperiodic exponent in posterior location positively correlated with T scores of attention and speed of information processing.” | P25: Sim | Q25: Sim | R25: =IF(OR(P25="",Q25=""),"",IF(P25=Q25,"Igual","Diferente")) -> Igual
L26: RQ5 | M26: Excerpt: “No evidence found.” — Explanation: The paper does not discuss any technical, clinical, or ethical barriers to the adoption of BCIs. It only discusses EEG analysis limitations. | N26: No evidence found. The article discusses research limitations and heterogeneity in EEG studies but does not address the broader technical, clinical, and ethical barriers that limit the adoption of BCIs in therapeutic or human enhancement contexts. | O26: O artigo não discute barreiras éticas ou técnicas de BCI. | P26: Sim | Q26: Sim | R26: =IF(OR(P26="",Q26=""),"",IF(P26=Q26,"Igual","Diferente")) -> Igual
L27: RQ6 | M27: Excerpt: “No evidence found.” — Explanation: The study does not mention data security, privacy, or integrity concerns related to BCIs or neural data beyond basic ethical approval. | N27: No evidence found. The article mentions obtaining "written informed consent" 2 and ethical approval for the study, but it does not discuss technical or policy mechanisms regarding the security, privacy, or integrity of the collected neural data. | O27: Não há menção a segurança ou privacidade dos dados neurais. | P27: Sim | Q27: Sim | R27: =IF(OR(P27="",Q27=""),"",IF(P27=Q27,"Igual","Diferente")) -> Igual
L28: RQ7 | M28: Excerpt: “No evidence found.” — Explanation: The study does not discuss AI, neurostimulation, personalization, or future trends in BCI technology. | N28: Excerpt: "Finally, future research can be integrated with other modalities (e.g., fMRI, neurostimulation) to enhance spatial resolution or mechanistic insight." 3 — Explanation: The authors suggest that future research, including work on neurophysiological parameters like those studied, should be integrated with other modalities such as fMRI and neurostimulation to improve understanding. | O28: O artigo não aborda integração com IA ou neuroestimulação personalizada. | P28: Sim | Q28: Não | R28: =IF(OR(P28="",Q28=""),"",IF(P28=Q28,"Igual","Diferente")) -> Diferente
L29: RQ8 | M29: Excerpt: “No evidence found.” — Explanation: The article does not address ethical or philosophical issues related to neurological expansion or enhancement. | N29: No evidence found. The article is a research study on neurophysiology and schizophrenia and does not include a discussion of the ethical or philosophical implications of "neurological expansion" or the amplification of human capabilities. | O29: Não há discussão ética ou filosófica sobre expansão neurológica. | P29: Sim | Q29: Sim | R29: =IF(OR(P29="",Q29=""),"",IF(P29=Q29,"Igual","Diferente")) -> Igual
L30: RQ9 | M30: Excerpt: “Future studies should… integrate with other modalities (e.g., fMRI, neurostimulation) to enhance spatial resolution or mechanistic insight.” main — Explanation: The reported research gaps relate only to EEG-based cognition studies in schizophrenia, not BCIs; there is no mention of BCI applications. | N30: Excerpt: "Future experiments necessitate the development of validated scales or paradigms that have undergone rigorous reliability and validity testing." 4 — Explanation: The authors highlight the need for rigorously tested and validated scales and experimental paradigms as a key research gap to ensure the quality and reliability of future assessments in mental healthcare. | O30: O artigo aponta lacunas sobre a necessidade de investigar melhor a relação entre aperiodic exponent e desempenho cognitivo em esquizofrenia: “Our findings confirmed the higher aperiodic exponent with lower alpha and beta band in SCZ… The findings suggest that aperiodic exponent holds strong cognitive functional implications in SCZ.” | P30: Sim | Q30: Sim | R30: =IF(OR(P30="",Q30=""),"",IF(P30=Q30,"Igual","Diferente")) -> Igual
A31: S4 | B31: Journal | C31: Enriquez-Geppert S, Krc J, O'Higgins FJ, Lietz M. Psilocybin-assisted neurofeedback for the improvement of executive functions: a randomized semi-naturalistic-lab feasibility study. Philos Trans R Soc Lond B Biol Sci. 2024 Dec 2;379(1915):20230095. doi: 10.1098/rstb.2023.0095. Epub 2024 Oct 21. PMID: 39428872; PMCID: PMC11513162. | D31: Philosophical Transactions of the Royal Society B | E31: Psilocybin-assisted neurofeedback for the improvement of executive functions: a randomized... feasibility study | F31: https://pubmed.ncbi.nlm.nih.gov/39428872/ | G31: 2024 | H31: Enriquez-Geppert S, et al. | I31: Netherlands | K31: PubMed | L31: RQ1 | M31: Excerpt: “No evidence found.” — Explanation: The article contains no discussion of Brain-Computer Interfaces (invasive, non-invasive, or hybrid) in any context. | N31: Excerpt: “Viviani & Velessi's [50] systematic review underscored that NF protocols targeting fm-theta are the most successful EEG protocols thus far regarding the improvement of EFs.” 1 Explanation: The article identifies frontal-midline theta neurofeedback (a non-invasive EEG method) as the most successful protocol for improving executive functions. | O31: Este estudo utiliza EEG neurofeedback (NF), que é uma forma de BCI não-invasiva. | P31: Não | Q31: Sim | R31: =IF(OR(P31="",Q31=""),"",IF(P31=Q31,"Igual","Diferente")) -> Diferente
L32: RQ2 | M32: Excerpt: “No evidence found.” — Explanation: The article does not mention any mental disorders (e.g., depression, anxiety, schizophrenia, ADHD) in relation to BCIs. | N32: No evidence found. Explanation: The article mentions that executive function deficits are "common in psychiatric disorders" 2 and references depression, stroke, and dementia in specific contexts, but it does not provide a general review ranking which disorders have received the most attention in BCI research. | O32: O artigo não foca em um transtorno específico, mas em déficits de funções executivas transdiagnósticos (presentes em várias condições psiquiátricas). | P32: Sim | Q32: Sim | R32: =IF(OR(P32="",Q32=""),"",IF(P32=Q32,"Igual","Diferente")) -> Igual
L33: RQ3 | M33: Excerpt: “No evidence found.” — Explanation: The text includes no metrics, evaluation methods, or outcome measures related to assessing BCI effectiveness. | N33: Excerpt: “Following three domains were assessed: (i) general placebo and expectancy (by general susceptibility and optimism, as well NF and psilocybin-assisted NF-specific experiences, attitudes and expectations), (ii) EFs (by self-rated EFs in daily life and four computerized experimental EF tasks), and (iii) functional abilities (by participant's priorities).” 3 Explanation: The authors evaluated effectiveness using a combination of placebo/expectancy questionnaires, objective computerized tasks, subjective daily life self-reports, and personalized functional goal ratings. | O33: O estudo usa: EEG frontal-midline theta power (indicador neural). Quatro tarefas de funções executivas: working memory updating, set-shifting, conflict monitoring, motor inhibition. Autoavaliações (BRIEF-A) sobre funções executivas na vida diária. Relatos de metas individuais de treinamento. | P33: Não | Q33: Sim | R33: =IF(OR(P33="",Q33=""),"",IF(P33=Q33,"Igual","Diferente")) -> Diferente
L34: RQ4 | M34: Excerpt: “No evidence found.” — Explanation: The paper does not discuss BCIs for enhancing memory, attention, learning, or other cognitive abilities. | N34: Excerpt: “Jackson et al. [42] observed a modest yet significant impact on episodic memory across both healthy and clinical groups... Significantly, fm-theta NF... has been identified as particularly effective in enhancing EFs in healthy individuals.” 4444 Explanation: The text cites previous studies showing that neurofeedback has been used to achieve significant improvements in episodic memory and executive functions (which include attention) in various populations. | O34: O artigo mostra que o neurofeedback assistido por psilocibina foi usado para melhorar funções executivas (memória de trabalho, atenção, inibição, monitoramento). | P34: Não | Q34: Sim | R34: =IF(OR(P34="",Q34=""),"",IF(P34=Q34,"Igual","Diferente")) -> Diferente
L35: RQ5 | M35: Excerpt: “No evidence found.” — Explanation: No technical, clinical, or ethical barriers to BCI adoption are mentioned or implied anywhere in the article. | N35: Excerpt: “Notably, inter-individual variability in learning to self-regulate brain activity, along with the presence of 'non-responders' [52,53], demands focused attention and solutions.” 5 Explanation: The authors identify the variability in learning success and the existence of "non-responders" (participants who fail to learn self-regulation) as primary clinical barriers to the adoption and efficacy of neurofeedback. | O35: O artigo menciona desafios como: Variabilidade individual (existência de “non-responders”). Necessidade de estudos maiores e controles ativos. Questões éticas do uso de psicodélicos (psilocibina) em conjunto com Neurofeedback | P35: Não | Q35: Sim | R35: =IF(OR(P35="",Q35=""),"",IF(P35=Q35,"Igual","Diferente")) -> Diferente
L36: RQ6 | M36: Excerpt: “No evidence found.” — Explanation: The article provides no coverage of security, privacy, or integrity of neural data. | N36: No evidence found. Explanation: While the article mentions obtaining informed consent 6and storing data on the OSF repository7, it does not discuss specific technical measures regarding the security, privacy, or integrity of the neural data. | O36: O artigo não discute segurança ou privacidade dos dados neurais. | P36: Sim | Q36: Sim | R36: =IF(OR(P36="",Q36=""),"",IF(P36=Q36,"Igual","Diferente")) -> Igual
L37: RQ7 | M37: Excerpt: “No evidence found.” — Explanation: The article contains no discussion of emerging BCI trends, AI integration, or personalized neurostimulation. | N37: Excerpt: “Recent advancements in NF methodology encompass real-time brain activity decoding [54], personalized NF tailored to individual anatomical and functional networks [55] and innovative NF techniques involving semantically guidance through mental states [56].” 8 Explanation: The article outlines emerging trends such as real-time decoding, personalization based on individual anatomy, and semantic guidance as key future directions for neurofeedback integration. | O37: O artigo menciona tendências como: Personalized NF(Neurofeedback Personalizado) adaptado a redes anatômicas e funcionais individuais. Uso de psicodélicos como potenciadores de neuroplasticidade em conjunto com Neurofeedback. | P37: Não | Q37: Sim | R37: =IF(OR(P37="",Q37=""),"",IF(P37=Q37,"Igual","Diferente")) -> Diferente
L38: RQ8 | M38: Excerpt: “No evidence found.” — Explanation: Ethical or philosophical issues related to neurological expansion or human capability amplification do not appear in the article. | N38: No evidence found. Explanation: The article focuses on the feasibility and efficacy of a specific clinical intervention (psilocybin-assisted neurofeedback) and does not address the broader ethical or philosophical implications of neurological expansion. | O38: O artigo toca em aspectos éticos do uso de psicodélicos para amplificação cognitiva, mas não discute profundamente filosofia da “expansão neurológica”. | P38: Sim | Q38: Sim | R38: =IF(OR(P38="",Q38=""),"",IF(P38=Q38,"Igual","Diferente")) -> Igual
L39: RQ9 | M39: Excerpt: “No evidence found.” — Explanation: The article does not address research gaps related to BCI technology, mental healthcare, or cognitive enhancement. | N39: Excerpt: “A thorough study with regular sessions and an active control group is crucial to evaluate EFs improvement and their specificity in future.” 9 Explanation: The authors conclude that to validate the method as an effective tool, future research must address current gaps by increasing the number of sessions and incorporating an active control group to rule out non-specific effects. | O39: O artigo aponta lacunas: Necessidade de estudos maiores e com grupo controle ativo. Avaliar especificidade dos ganhos em funções executivas. | P39: Não | Q39: Sim | R39: =IF(OR(P39="",Q39=""),"",IF(P39=Q39,"Igual","Diferente")) -> Diferente
A40: S5 | B40: Journal | C40: Zemla K, Sedek G, Wróbel K, Postepski F, Wojcik GM. Investigating the Impact of Guided Imagery on Stress, Brain Functions, and Attention: A Randomized Trial. Sensors (Basel). 2023 Jul 7;23(13):6210. doi: 10.3390/s23136210. PMID: 37448060; PMCID: PMC10346678. | D40: Sensors (Basel) | E40: Investigating the Impact of Guided Imagery on Stress, Brain Functions, and Attention: A Randomized Trial | F40: https://pubmed.ncbi.nlm.nih.gov/37448060/ | G40: 2023 | H40: Zemla K, et al. | I40: Poland | K40: PubMed | L40: RQ1 | M40: No evidence Found | N40: No evidence Found | O40: Este estudo não usa diretamente BCIs clássicos, mas sim EEG para medir atividade cerebral durante guided imagery (GI). trata-se de um método não-invasivo (EEG). | P40: Não | Q40: Não | R40: =IF(OR(P40="",Q40=""),"",IF(P40=Q40,"Igual","Diferente")) -> Igual | S40: As LMMs não consideram EGG como metodo não invasivo.
L41: RQ2 | M41: No evidence Found | N41: No evidence Found | O41: O artigo não foca em um transtorno clínico específico, mas em redução de estresse e ansiedade em participantes saudáveis. | P41: Sim | Q41: Sim | R41: =IF(OR(P41="",Q41=""),"",IF(P41=Q41,"Igual","Diferente")) -> Igual
L42: RQ3 | M42: RQ3 Excerpt: “the effectiveness of the session in reducing stress was assessed through monitoring beta power reductions and alpha state increases using EEG data recordings and self-reported questionnaires.” — Explanation: The article explicitly lists EEG band power (alpha, beta) changes and self-report questionnaires as outcome metrics used to assess intervention effectiveness; attentional-task error rates (Stroop, anti-saccade, Go/No-go) are also presented as measurable outcomes. | N42: No evidence Found | O42: O estudo usa: EEG (alpha e beta power). Testes de funções executivas: Stroop, Go/No-go, Anti-saccade. Questionários de ansiedade e estresse (STAI, auto-relatos). | P42: Sim | Q42: Não | R42: =IF(OR(P42="",Q42=""),"",IF(P42=Q42,"Igual","Diferente")) -> Diferente
L43: RQ4 | M43: No evidence Found | N43: No evidence Found | O43: O artigo mostra que guided imagery + EEG pode melhorar atenção e controle executivo: “The findings suggest that guided imagery has the potential to enhance attentional control by augmenting the alpha power and reducing stress levels.” | P43: Não | Q43: Não | R43: =IF(OR(P43="",Q43=""),"",IF(P43=Q43,"Igual","Diferente")) -> Igual
L44: RQ5 | M44: No evidence Found | N44: No evidence Found | O44: O artigo não discute barreiras éticas ou técnicas de BCI. | P44: Sim | Q44: Sim | R44: =IF(OR(P44="",Q44=""),"",IF(P44=Q44,"Igual","Diferente")) -> Igual
L45: RQ6 | M45: No evidence Found | N45: No evidence Found | O45: Não há menção a segurança ou privacidade dos dados neurais. | P45: Sim | Q45: Sim | R45: =IF(OR(P45="",Q45=""),"",IF(P45=Q45,"Igual","Diferente")) -> Igual
L46: RQ7 | M46: RQ7 Excerpt: “Moreover, a notable feature of this research involved the application of multi-sensor EEG signal classification and a GLM for the categorization of two mental states. These findings offer compelling evidence regarding the potential for developing innovative therapies in the domain of human–machine interactions ... For instance, the study titled ‘Golden Subject Is Everyone: A Subject Transfer Neural Network for Motor Imagery-based Brain Computer Interfaces’ [106] explores the use of neural networks to transfer knowledge between individuals in the context of motor-imagery-based brain–computer interfaces. The researchers propose a new approach that allows data from one participant to be used to train a neural network, which can then be applied to predict and interpret brain signals from a different participant. The findings indicate that this method has potential and could lead to the development of more inclusive and widely applicable brain–computer interfaces.” — Explanation: The article cites machine-learning / neural-network approaches and subject-transfer for motor-imagery BCIs as an emerging direction, indicating integration of AI methods to improve BCI generalization and applicability. | N46: Excerpt: "For instance, the study titled “Golden Subject Is Everyone: A Subject Transfer Neural Net work for Motor Imagery-based Brain Computer Interfaces” [106] explores the use of neural networks to transfer knowledge between individuals in the context of motor-imagery-based brain–computer interfaces." — Explanation: The article references a related BCI study in its discussion, highlighting the emerging trend of integrating artificial intelligence (neural networks) to create more generalized, personalized BCI applications by transferring knowledge between subjects. | O46: O artigo aborda IA ou neuroestimulação personalizada. | P46: Sim | Q46: Sim | R46: =IF(OR(P46="",Q46=""),"",IF(P46=Q46,"Igual","Diferente")) -> Igual
L47: RQ8 | M47: No evidence Found | N47: No evidence Found | O47: Não há discussão ética ou filosófica sobre expansão neurológica. | P47: Sim | Q47: Sim | R47: =IF(OR(P47="",Q47=""),"",IF(P47=Q47,"Igual","Diferente")) -> Igual
L48: RQ9 | M48: RQ9 Excerpt: “These limitations underscore the need for future research with larger and more diverse samples, longer follow-up periods, and additional control groups. By addressing these methodological considerations, a more comprehensive understanding of the effectiveness and potential limitations of guided imagery can be achieved, not only in the context of stress management but also in terms of enhancing attentional control test results.” — Explanation: While focused on guided imagery, the authors explicitly state research gaps (larger/diverse samples, longer follow-up, more control groups) that are relevant general recommendations for future work linking EEG/BCI research to cognitive and clinical outcomes. | N48: No evidence Found | O48: O artigo aponta lacunas, indica que há pouca pesquisa sobre GI + EEG: “Given the limited existing research on the specific impact of guided imagery on attention control, the study’s findings carry notable significance.” | P48: Parcialmente | Q48: Não | R48: =IF(OR(P48="",Q48=""),"",IF(P48=Q48,"Igual","Diferente")) -> Diferente
A49: S7 | B49: Journal | C49: Chan WL, Olbrich S, Jiang X, Zhang H, Ip CT, Brunovsky M. Subanesthetic ketamine alters EEG signal complexity: Implications for treatment stratification in depression. J Affect Disord. 2025 Oct 1;386:119477. doi: 10.1016/j.jad.2025.119477. Epub 2025 May 24. PMID: 40419149. | D49: Journal of Affective Disorders | E49: Subanesthetic ketamine alters EEG signal complexity: Implications for treatment stratification in depression | F49: https://pubmed.ncbi.nlm.nih.gov/40419149/ | G49: 2025 | H49: Chan WL, et al. | I49: Czech Republic | K49: PubMed | L49: RQ1 | M49: No evidence Found | N49: No evidence Found | O49: O estudo usa EEG não-invasivo para medir complexidade de sinais cerebrais durante infusão de ketamina em pacientes com depressão. | P49: Não | Q49: Não | R49: =IF(OR(P49="",Q49=""),"",IF(P49=Q49,"Igual","Diferente")) -> Igual
I50: Switzerland | L50: RQ2 | M50: No evidence Found | N50: No evidence Found | O50: O artigo foca em major depressive disorder (MDD), especialmente na forma resistente ao tratamento (TRD): “Major depressive disorder, particularly its treatment-resistant form (TRD), poses significant treatment challenges.” | P50: Não | Q50: Não | R50: =IF(OR(P50="",Q50=""),"",IF(P50=Q50,"Igual","Diferente")) -> Igual
L51: RQ3 | M51: No evidence Found | N51: No evidence Found | O51: O estudo usa: Montgomery-Åsberg Depression Rating Scale (MADRS) para avaliar sintomas clínicos. EEG Lempel-Ziv complexity (LZCT e LZCS) como biomarcadores de resposta. | P51: Não | Q51: Não | R51: =IF(OR(P51="",Q51=""),"",IF(P51=Q51,"Igual","Diferente")) -> Igual
L52: RQ4 | M52: No evidence Found | N52: No evidence Found | O52: O artigo não trata de memória ou atenção diretamente, mas mostra que EEG pode prever resposta antidepressiva e está ligado a neuroplasticidade. | P52: Parcialmente | Q52: Parcialmente | R52: =IF(OR(P52="",Q52=""),"",IF(P52=Q52,"Igual","Diferente")) -> Igual
L53: RQ5 | M53: No evidence Found | N53: Excerpt: "Additionally, the use of a 22-channel EEG cap restricted spatial resolution, likely to constrain the ability of $LZC_{S}$ to detect topographic variability. [...] Moreover, the small sample size may compromise the statistical power and robustness of our conclu- sions. The use of a single-blind, fixed-sequence design introduces po- tential biases." 1111 — Explanation: The authors list methodological drawbacks of their study that apply as technical barriers (limited EEG channels for spatial resolution) and clinical/design barriers (small sample size and fixed-sequence design) for research in the field. | O53: O artigo menciona limitações técnicas: Pequeno tamanho da amostra. Resultados inconsistentes entre regiões cerebrais. Complexidade excessiva pode não se traduzir em melhora clínica. | P53: Não | Q53: Sim | R53: =IF(OR(P53="",Q53=""),"",IF(P53=Q53,"Igual","Diferente")) -> Diferente
L54: RQ6 | M54: No evidence Found | N54: No evidence Found | O54: O artigo não discute segurança ou privacidade dos dados neurais. | P54: Sim | Q54: Sim | R54: =IF(OR(P54="",Q54=""),"",IF(P54=Q54,"Igual","Diferente")) -> Igual
L55: RQ7 | M55: No evidence Found | N55: No evidence Found | O55: O artigo não menciona IA ou neuroestimulação personalizada. | P55: Sim | Q55: Sim | R55: =IF(OR(P55="",Q55=""),"",IF(P55=Q55,"Igual","Diferente")) -> Igual
L56: RQ8 | M56: No evidence Found | N56: No evidence Found | O56: Não há discussão ética ou filosófica sobre expansão neurológica. | P56: Sim | Q56: Sim | R56: =IF(OR(P56="",Q56=""),"",IF(P56=Q56,"Igual","Diferente")) -> Igual
L57: RQ9 | M57: No evidence Found | N57: No evidence Found | O57: O artigo aponta lacunas: Necessidade de validar LZC como biomarcador preditivo. Explorar melhor a relação entre complexidade neural e resposta clínica. “The utility of LZC in predicting treatment response to ketamine, particularly in TRD, has not been systematically validated.” | P57: Não | Q57: Não | R57: =IF(OR(P57="",Q57=""),"",IF(P57=Q57,"Igual","Diferente")) -> Igual
A58: S7 | B58: Journal | C58: Jaiswal S, Purpura SR, Manchanda JK, Nan J, Azeez N, Ramanathan D, Mishra J. Design and Implementation of a Brief Digital Mindfulness and Compassion Training App for Health Care Professionals: Cluster Randomized Controlled Trial. JMIR Ment Health. 2024 Jan 22;11:e49467. doi: 10.2196/49467. PMID: 38252479; PMCID: PMC10845023. | D58: JMIR Ment Health | E58: Design and Implementation of a Brief Digital Mindfulness and Compassion Training App...: Cluster Randomized Controlled Trial | F58: https://pubmed.ncbi.nlm.nih.gov/38252479/ | G58: 2024 | H58: Jaiswal S, et al. | I58: United States | K58: PubMed | L58: RQ1 | M58: No evidence Found | N58: No evidence Found | O58: O estudo usa EEG não-invasivo para medir atividade neural durante tarefas de atenção à respiração, antes e depois do treinamento digital. trata-se de BCI não-invasiva (EEG). | P58: Não | Q58: Não | R58: =IF(OR(P58="",Q58=""),"",IF(P58=Q58,"Igual","Diferente")) -> Igual
L59: RQ2 | M59: No evidence Found | N59: No evidence Found | O59: O artigo não foca em um transtorno específico, mas em burnout e estresse ocupacional em profissionais de saúde. | P59: Sim | Q59: Sim | R59: =IF(OR(P59="",Q59=""),"",IF(P59=Q59,"Igual","Diferente")) -> Igual
L60: RQ3 | M60: No evidence Found | N60: Excerpt: “We evaluated the primary outcomes of change in mindfulness and self-compassion and monitored sessions of training engagement. [...] Finally, this study also uniquely assayed objective neurophysiological plasticity associated with the training alongside subjective behavioral changes. For this, we measured electroencephalography (EEG)-based brain signals on an interoceptive attention-to-breathing task, assessed before and after training.” — Explanation: The study used a combination of subjective behavioral assessments (mindfulness and self-compassion scales) and objective neurophysiological measures (EEG-based brain signals) to track the training's effectiveness. | O60: O estudo usa: Escalas comportamentais: Self-Compassion Scale, Mindful Attention Awareness Scale, Maslach Burnout Inventory. EEG source imaging para medir atividade em redes neurais (Default Mode Network, FPN, CON). | P60: Não | Q60: Sim | R60: =IF(OR(P60="",Q60=""),"",IF(P60=Q60,"Igual","Diferente")) -> Diferente
L61: RQ4 | M61: No evidence Found | N61: Excerpt: “Overall, this digital meditative practice is considered closed loop because of its performance-adaptive feature [22,23]. Consistent attention to breathing is emphasized over other types of breathing techniques, such as deep breathing. The moment-to-moment performance tracking further allows quantification of the attentive focus during each session, which is not possible with traditional nondigital meditation.” — Explanation: The "closed-loop," performance-adaptive digital system allows for the tracking and quantification of "attentive focus" during breath monitoring, which serves as a cognitive training and enhancement mechanism. | O61: O artigo mostra que o treinamento digital com EEG está associado a melhora em atenção plena e autocompaixão, além de supressão da DMN (rede cerebral ligada a divagação mental e ruminação). | P61: Não | Q61: Sim | R61: =IF(OR(P61="",Q61=""),"",IF(P61=Q61,"Igual","Diferente")) -> Diferente
L62: RQ5 | M62: No evidence Found | N62: Excerpt: “As per the limitations of this study, the sample size and nonactive control group are the primary limitations, although it is worth noting that this is the first ever implementation of the digital WellMind intervention in health care professionals. [...] These challenges include a clear lack of time for physicians as well as concerns regarding confidentiality and discrimination within this workforce.” — Explanation: The article points out methodological limitations (small sample size, nonactive control group) as clinical barriers, and also highlights adoption barriers like lack of time for healthcare professionals, and ethical concerns over confidentiality and discrimination. | O62: artigo não discute barreiras éticas em profundidade, mas menciona limitações: Pequeno tamanho da amostra. Treinamento individual não altera burnout significativamente (precisa de intervenção organizacional). | P62: Não | Q62: Sim | R62: =IF(OR(P62="",Q62=""),"",IF(P62=Q62,"Igual","Diferente")) -> Diferente
L63: RQ6 | M63: No evidence Found | N63: Excerpt: “This digital program is Health Insurance Portability and Accountability Act (HIPAA) compliant and secured by password protection, and each user interacts through an alphanumeric study ID that is not linked to any personal health information. [...] All data is de-identified, and up to US $150 in compensation was provided as an e-Gift card to all participants for completing all aspects of the study, including assessments and intervention procedures.” — Explanation: The study addresses security and privacy by ensuring the app is HIPAA compliant, secured by password, uses de-identified alphanumeric IDs not linked to personal health information, and confirms all collected data is de-identified. | O63: O estudo menciona que o app apresentando e usado no estudo é protegido por senha, garantindo privacidade dos dados: “This digital program is Health Insurance Portability and Accountability Act (HIPAA) compliant and secured by password protection.” | P63: Não | Q63: Sim | R63: =IF(OR(P63="",Q63=""),"",IF(P63=Q63,"Igual","Diferente")) -> Diferente
L64: RQ7 | M64: No evidence Found | N64: Excerpt: “Also, individuals with high DMN activity at baseline experienced greater DMN suppression with training, suggesting baseline DMN activity as an individual-specific neural marker to determine who may benefit most from such training.” — Explanation: The finding that a baseline neural state (DMN activity) predicts the magnitude of training benefit is an emerging trend, indicating the potential for using individual-specific neural markers to personalize treatment and maximize efficacy. | O64: O artigo não fala de IA ou neuroestimulação personalizada, mas mostra tendência de treinamentos digitais escaláveis e adaptativos. | P64: Não | Q64: Sim | R64: =IF(OR(P64="",Q64=""),"",IF(P64=Q64,"Igual","Diferente")) -> Diferente
L65: RQ8 | M65: No evidence Found | N65: No evidence Found | O65: O artigo não discute aspectos éticos ou filosóficos de expansão neurológica. | P65: Sim | Q65: Sim | R65: =IF(OR(P65="",Q65=""),"",IF(P65=Q65,"Igual","Diferente")) -> Igual
L66: RQ9 | M66: No evidence Found | N66: Excerpt: “The use of an active control group (e.g., providing a different, non-mindfulness, or non-compassion digital training) is necessary in the future to rule out effects related to time, contact, and expectation differences.” — Explanation: A key methodological gap is the need for an active control group (rather than a no-contact group) to conclusively confirm that the positive effects are due to the specific intervention and not simply the result of time, contact, or user expectation. | O66: O artigo aponta lacunas: Necessidade de estudos maiores. Integração com intervenções organizacionais para impacto em burnout. | P66: Não | Q66: Sim | R66: =IF(OR(P66="",Q66=""),"",IF(P66=Q66,"Igual","Diferente")) -> Diferente
A67: S8 | B67: Journal | C67: Horváth D, Négyesi J, Rácz M, Győri T, Matics Z, Puskin A, Csipor J, Rácz L. Feasibility of a novel neurofeedback system: a parallel randomized single-blinded pilot study. Sci Rep. 2023 Oct 13;13(1):17353. doi: 10.1038/s41598-023-44545-1. PMID: 37833489; PMCID: PMC10576027. | D67: Scientific Reports | E67: Feasibility of a novel neurofeedback system: a parallel randomized single-blinded pilot study | F67: https://pubmed.ncbi.nlm.nih.gov/37833489/ | G67: 2023 | H67: Horváth D, et al. | I67: Hungary | K67: PubMed | L67: RQ1 | M67: No evidence Found | N67: No evidence Found | O67: O estudo usa neurofeedback (NF) via EEG não-invasivo, com um novo sistema chamado neuroMoon (nM). | P67: Não | Q67: Não | R67: =IF(OR(P67="",Q67=""),"",IF(P67=Q67,"Igual","Diferente")) -> Igual
L68: RQ2 | M68: No evidence Found | N68: Excerpt: “There is a growing body of literature that supports the effectiveness of NF, particularly in the field of cognitive functions and attention-deficit/hyperactivity disorder (ADHD)”. — Explanation: The article specifically points out that neurofeedback research shows effectiveness for cognitive function and Attention-Deficit/Hyperactivity Disorder (ADHD), suggesting these areas have received significant attention. | O68: Este artigo não foca em transtornos clínicos, mas em atletas jovens saudáveis, avaliando cognição e desempenho perceptual-cognitivo. | P68: Parcialmente | Q68: Sim | R68: =IF(OR(P68="",Q68=""),"",IF(P68=Q68,"Igual","Diferente")) -> Diferente
L69: RQ3 | M69: No evidence Found | N69: Excerpt: “The NF protocol used is aimed at increasing the sensorimotor rhythm-theta ratio (SMR/T)... To assess the success of the nM neurofeedback training, Mann-Whitney U test was performed to com- pare the differences between the real and sham nM groups. Furthermore, to establish the relationship between behavioral and EEG changes, a comprehensive correlation analysis was performed.”. — Explanation: The effectiveness is measured primarily by tracking changes in the SMR/T EEG ratio and comparing these neurophysiological metrics using statistical tests (Mann-Whitney U, correlation analysis) against behavioral outcomes. | O69: O estudo usa: Vienna Test System (VTS): Stroop, Trail-Making, Task-Switching, Reaction Test, Determination Test. Digit Span Backwards (DSB) para memória de trabalho. EEG medidas (SMR/T ratio) durante Neurofeedback. | P69: Não | Q69: Sim | R69: =IF(OR(P69="",Q69=""),"",IF(P69=Q69,"Igual","Diferente")) -> Diferente
L70: RQ4 | M70: No evidence Found | N70: Excerpt: “This closed-loop method helps individuals to control or modify their cortical activity through learned self-regulation, with the aim of improving alertness, reducing anxiety and enhancing cognitive abilities such as attention, memory, and behavior.”. — Explanation: Brain-Computer Interfaces in the form of Neurofeedback (NF) are described as a closed-loop technique that aims to enhance cognitive abilities, including attention and memory, through learned self-regulation of brain function. | O70: O artigo mostra que o neurofeedback (SMR/T ratio) foi usado para melhorar atenção, memória de trabalho e velocidade de reação. | P70: Não | Q70: Sim | R70: =IF(OR(P70="",Q70=""),"",IF(P70=Q70,"Igual","Diferente")) -> Diferente
L71: RQ5 | M71: No evidence Found | N71: Excerpt: “An additional challenge of lightweight EEG hardware is the lack of working electrodes above the areas that are most frequently used in SMR/T NF procedures, most notably, Cz/Pz locations.”. — Explanation: A main technical barrier is the design limitation of portable/lightweight EEG devices, which often lack the necessary number and strategic placement of electrodes (like Cz/Pz) required for optimal Neurofeedback procedures. | O71: O artigo aponta limitações: Melhorias também ocorreram no grupo sham, sugerindo efeito placebo. Pequeno tamanho da amostra. | P71: Não | Q71: Parcialmente | R71: =IF(OR(P71="",Q71=""),"",IF(P71=Q71,"Igual","Diferente")) -> Diferente
L72: RQ6 | M72: No evidence Found | N72: No evidence Found | O72: O artigo não discute segurança ou privacidade dos dados neurais. | P72: Sim | Q72: Sim | R72: =IF(OR(P72="",Q72=""),"",IF(P72=Q72,"Igual","Diferente")) -> Igual
L73: RQ7 | M73: No evidence Found | N73: No evidence Found | O73: artigo não menciona IA ou neuroestimulação personalizada, mas mostra tendência de headsets portáteis de EEG com Neurofeedback gamificado. | P73: Sim | Q73: Sim | R73: =IF(OR(P73="",Q73=""),"",IF(P73=Q73,"Igual","Diferente")) -> Igual
L74: RQ8 | M74: No evidence Found | N74: No evidence Found | O74: O artigo não discute aspectos éticos ou filosóficos. | P74: Sim | Q74: Sim | R74: =IF(OR(P74="",Q74=""),"",IF(P74=Q74,"Igual","Diferente")) -> Igual
L75: RQ9 | M75: No evidence Found | N75: Excerpt: “However, considering that the sham stimulation also induced similar improvements in cognitive abilities, future studies should clearly determine the cognitive measures that could benefit from NF training.”. — Explanation: A crucial research gap is the need to isolate the true effects of Neurofeedback, as the control (sham) stimulation produced similar cognitive improvements, making it difficult to determine which specific measures benefit from the real training. | O75: O artigo aponta lacunas: Necessidade de estudos maiores. Determinar quais medidas cognitivas realmente se beneficiam do Neurofeedback | P75: Não | Q75: Sim | R75: =IF(OR(P75="",Q75=""),"",IF(P75=Q75,"Igual","Diferente")) -> Diferente
A76: S9 | B76: Journal | C76: Krylova, Marina et al. “Comprehensive Mitigation of Peripheral and Central Stress Responses by Nx4: Insights From EEG and Heart Rate Variability in Post‐Stress Resting State.” Human Psychopharmacology 40 (2025): n. pag. | D76: Clinical Pharmacology | E76: Comprehensive Mitigation of Peripheral and Central Stress Responses by Nx4: Insights From EEG and Heart Rate Variability... | F76: https://onlinelibrary.wiley.com/doi/10.1002/hup.70020?af=R 10.1002/hup.70020 | G76: 2025 | H76: Krylova M, et al. | I76: Germany | K76: PubMed | L76: RQ1 | M76: No evidence Found | N76: No evidence Found | O76: Artigo indisponivel publicamente | R76: =IF(OR(P76="",Q76=""),"",IF(P76=Q76,"Igual","Diferente"))
L77: RQ2 | M77: No evidence Found | N77: No evidence Found | R77: =IF(OR(P77="",Q77=""),"",IF(P77=Q77,"Igual","Diferente"))
L78: RQ3 | M78: No evidence Found | N78: No evidence Found | R78: =IF(OR(P78="",Q78=""),"",IF(P78=Q78,"Igual","Diferente"))
L79: RQ4 | M79: No evidence Found | N79: No evidence Found | R79: =IF(OR(P79="",Q79=""),"",IF(P79=Q79,"Igual","Diferente"))
L80: RQ5 | M80: No evidence Found | N80: No evidence Found | R80: =IF(OR(P80="",Q80=""),"",IF(P80=Q80,"Igual","Diferente"))
L81: RQ6 | M81: No evidence Found | N81: No evidence Found | R81: =IF(OR(P81="",Q81=""),"",IF(P81=Q81,"Igual","Diferente"))
L82: RQ7 | M82: No evidence Found | N82: No evidence Found | R82: =IF(OR(P82="",Q82=""),"",IF(P82=Q82,"Igual","Diferente"))
L83: RQ8 | M83: No evidence Found | N83: No evidence Found | R83: =IF(OR(P83="",Q83=""),"",IF(P83=Q83,"Igual","Diferente"))
L84: RQ9 | M84: No evidence Found | N84: No evidence Found | R84: =IF(OR(P84="",Q84=""),"",IF(P84=Q84,"Igual","Diferente"))
A85: S10 | B85: Journal | C85: Zozan Guleken, Gökçer Eskikurt, Sacit Karamürsel, Investigation of the effects of transcranial direct current stimulation and neurofeedback by continuous performance test, Neuroscience Letters, Volume 716, 2020, 134648, ISSN 0304-3940, https://doi.org/10.1016/j.neulet.2019.134648. (https://www.sciencedirect.com/science/article/pii/S0304394019307517) Abstract: Transcranial direct current stimulation (tDCS) is a noninvasive neuromodulation technique based on weak direct current stimulation through the scalp. Neurofeedback (NFB) is a learning strategy that may help alter to brain wave parameters, by monitoring electroencephalography (EEG) feedback via special programs. We aimed to investigate the supportive effects of tDCS in addition to NFB training. 16 healthy volunteers were divided equally into two groups. One of the groups was trained by NFB with the sensorimotor rhythm (SMR) protocol; 2 days per week, 10 sessions of 30 min, the other group received 10 min of tDCS before each NFB sessions. Continuous Performance Test (CPT) was used to measure, response time and suppression and to determine selective attention condition. Also, Beck Depression and Anxiety Inventories were used to exclude people with depression and anxiety. Depression scores of NFB + tDCS group were decreased significantly. CPT scores were better at last sessions for both groups compared to the first sessions. Sessions were analyzed by comparing 1st, 2nd, 5th and 10th sessions. While the NFB + tDCS group had statistically significant changes at theta/beta ratios with SMR and alpha band amplitudes, NFB group statistics had changed at theta/SMR ratios. NFB training shows its effects at the end of 10 sessions. Despite an increase in the latencies of correct and commission responses on the task of CPT, additional use of tDCS improves cognitive performance. Also, tDCS has a supportive effect on the healthy participants who have mild anxiety and depression; also inhibition deficits of subjects were clear. Keywords: Neurofeedback; Transcranial direct current stimulation; Continuous performance test; Sensorimotor rhythm; Inhibition; Neuromodulation | D85: Neuroscience Letters | E85: Investigation of the effects of transcranial direct current stimulation and neurofeedback by continuous performance test | F85: https://doi.org/10.1016/j.neulet.2019.134648 | G85: 2020 | H85: Guleken, Zozan; Eskikurt, Gökçer; Karamürsel, Sacit | I85: Turkey | K85: Science Direct | L85: RQ1 | M85: Excerpt: “Transcranial direct current stimulation (tDCS) is a noninvasive neuromodulation technique based on weak direct current stimulation through the scalp.” — Explanation: This article describes the BCI methods used (tDCS and neurofeedback via EEG) as noninvasive, showing that non‑invasive BCIs are the dominant type in this mental‑health / cognitive‑performance context. | N85: Excerpt: “Transcranial direct current stimulation (tDCS) is a noninvasive neuromodulation technique based on weak direct current stimulation through the scalp. Neurofeedback (NFB) is a learning strategy that may help alter to brain wave parameters...” Explanation: The article defines and utilizes two non-invasive techniques: Transcranial Direct Current Stimulation (tDCS) and Neurofeedback (NFB) , classifying them as non-invasive neuromodulation and learning strategies respectively. | O85: O estudo usa duas técnicas não-invasivas: Neurofeedback (NFB) via EEG. Transcranial Direct Current Stimulation (tDCS). | P85: Sim | Q85: Sim | R85: =IF(OR(P85="",Q85=""),"",IF(P85=Q85,"Igual","Diferente")) -> Igual
L86: RQ2 | M86: Excerpt: “tDCS … had positive results on patients addicted to smoke, drug, alcohol, methamphetamines and cocaine who have problems with selective attention [5–7].” And also: “tDCS has positive effects on psychiatric disorders and may be used as an additional treatment tool.” — Explanation: Though the present study used healthy volunteers, the authors reference prior research on substance‑use disorders (“addicted to smoke, drug, alcohol, … methamphetamines and cocaine”) and more broadly “psychiatric disorders,” implying that addiction and related disorders have received attention in BCI applications. | N86: Excerpt: “Also, tDCS has a supportive effect on the healthy participants who have mild anxiety and depression...” Explanation: While the study was conducted on healthy volunteers, it specifically investigated the effects on mild anxiety and depression symptoms, and used clinical inventories for these conditions. | O86: O artigo não foca em pacientes clínicos, mas em voluntários saudáveis. Ainda assim, mede depressão e ansiedade leves com inventários de Beck. | P86: Sim | Q86: Sim | R86: =IF(OR(P86="",Q86=""),"",IF(P86=Q86,"Igual","Diferente")) -> Igual
L87: RQ3 | M87: Excerpt: “Continuous Performance Test (CPT) was used to measure, response time and suppression and to determine selective attention condition.” And: “Through NFB applications, average amplitudes of the delta, theta, alpha, SMR, beta1, beta2 bands and theta/SMR and theta/beta ratios were obtained.” And also: “Also, pre- and after-training BDI and BAI scores were compared.” — Explanation: The study uses behavioral metrics (CPT: correct/commission/omission responses and reaction times), EEG spectral measures (amplitude of various bands and band‑ratios), and self-report inventories for depression/anxiety (BDI/BAI) to evaluate effectiveness of the BCI interventions. | N87: Excerpt: “Continuous Performance Test (CPT) was used to measure, response time and suppression and to determine selective attention condition. Also, Beck Depression and Anxiety Inventories were used...” Explanation: The study evaluated effectiveness using the Continuous Performance Test (CPT) for cognitive metrics (attention, response time) and the Beck Depression and Anxiety Inventories (BDI, BAI) for psychological symptom scoring. | O87: O estudo usa: Continuous Performance Test (CPT) para atenção seletiva e inibição. Inventários Beck de Depressão (BDI) e Ansiedade (BAI). EEG bandas (theta, alpha, SMR, beta) e suas razões. | P87: Sim | Q87: Sim | R87: =IF(OR(P87="",Q87=""),"",IF(P87=Q87,"Igual","Diferente")) -> Igual
L88: RQ4 | M88: Excerpt: “The test aimed to observe random changes to the given stimuli.” (CPT measuring selective attention, response time and suppression). And: “In this study, the selective attention and inhibition effect of the theta/SMR protocol supports previous studies.” — Explanation: The article shows that BCI (NFB, with or without tDCS) was used to enhance cognitive functions such as selective attention and response inhibition. Although memory is not directly measured, attention and inhibitory control—key cognitive abilities—are assessed. | N88: Excerpt: “Despite an increase in the latencies of correct and commission responses on the task of CPT, additional use of tDCS improves cognitive performance.” Explanation: The research specifically aimed to enhance cognitive abilities, finding that the addition of tDCS to Neurofeedback training improves cognitive performance as measured by the CPT. | O88: O artigo mostra que NFB e tDCS melhoraram: Atenção seletiva (menos erros no CPT). Inibição (redução de comissões e omissões). Desempenho cognitivo (melhora em bandas EEG ligadas à atenção e memória). | P88: Sim | Q88: Sim | R88: =IF(OR(P88="",Q88=""),"",IF(P88=Q88,"Igual","Diferente")) -> Igual
L89: RQ5 | M89: Excerpt: “additional trainings and tDCS applications are needed in a larger subject group using different protocols to improve values of tDCS studies.” — Explanation: The only “limitation” mentioned is the small sample size and the need for further studies with larger groups and varied protocols. The article does not discuss technical or ethical barriers explicitly, so broader barriers remain unaddressed. | N89: No evidence Found | O89: O artigo aponta limitações: Pequeno tamanho da amostra (n=16). Resultados preliminares em voluntários saudáveis (não pacientes). Necessidade de mais sessões para efeitos robustos. | P89: Sim | Q89: Não | R89: =IF(OR(P89="",Q89=""),"",IF(P89=Q89,"Igual","Diferente")) -> Diferente
L90: RQ6 | M90: No evidence Found | N90: No evidence Found | O90: O artigo não discute segurança ou privacidade dos dados neurais. | P90: Sim | Q90: Sim | R90: =IF(OR(P90="",Q90=""),"",IF(P90=Q90,"Igual","Diferente")) -> Igual
L91: RQ7 | M91: No evidence Found | N91: No evidence Found | O91: O artigo não menciona IA | P91: Sim | Q91: Sim | R91: =IF(OR(P91="",Q91=""),"",IF(P91=Q91,"Igual","Diferente")) -> Igual
L92: RQ8 | M92: No evidence Found | N92: No evidence Found | O92: Não há discussão ética ou filosófica sobre expansão neurológica. | P92: Sim | Q92: Sim | R92: =IF(OR(P92="",Q92=""),"",IF(P92=Q92,"Igual","Diferente")) -> Igual
L93: RQ9 | M93: Excerpt: “Also, additional trainings and tDCS applications are needed in a larger subject group using different protocols to improve values of tDCS studies.” — Explanation: The authors identify the need for replication with larger samples and different protocols, indicating a research gap in validating and generalizing their findings before broader therapeutic or enhancement use. | N93: No evidence Found | O93: O artigo aponta lacunas: Necessidade de mais estudos clínicos (não apenas em voluntários saudáveis). Explorar melhor efeitos de longo prazo e mecanismos neurofisiológicos. | P93: Sim | Q93: Não | R93: =IF(OR(P93="",Q93=""),"",IF(P93=Q93,"Igual","Diferente")) -> Diferente
A94: S11 | B94: Journal | C94: Aki Tsuchiyagaito, Jared L. Smith, Nour El-Sabbagh, Vadim Zotev, Masaya Misaki, Obada Al Zoubi, T. Kent Teague, Martin P. Paulus, Jerzy Bodurka, Jonathan Savitz, Real-time fMRI neurofeedback amygdala training may influence kynurenine pathway metabolism in major depressive disorder, NeuroImage: Clinical, Volume 29, 2021, 102559, ISSN 2213-1582, https://doi.org/10.1016/j.nicl.2021.102559. (https://www.sciencedirect.com/science/article/pii/S2213158221000036) Abstract: Real-time fMRI neurofeedback (rtfMRI-nf) left amygdala (LA) training is a promising intervention for major depressive disorder (MDD). We have previously proposed that rtfMRI-nf LA training may reverse depression-associated regional impairments in neuroplasticity and restore information flow within emotion-regulating neural circuits. Inflammatory cytokines as well as the neuroactive metabolites of an immunoregulatory pathway, i.e. the kynurenine pathway (KP), have previously been implicated in neuroplasticity. Therefore, in this proof-of-principle study, we investigated the association between rtfMRI-nf LA training and circulating inflammatory mediators and KP metabolites. Based on our previous work, the primary variable of interest was the ratio of the NMDA-receptor antagonist, kynurenic acid to the NMDA receptor agonist, quinolinic acid (KynA/QA), a putative neuroprotective index. We tested two main hypotheses. i. Whether rtfMRI-nf acutely modulates KynA/QA, and ii. whether baseline KynA/QA predicts response to rtfMRI-nf. Twenty-nine unmedicated participants who met DSM-5 criteria for MDD based on the Mini-International Neuropsychiatric Interview and had current depressive symptoms (Montgomery-Åsberg Depression Rating Scale (MADRS) score > 6) completed two rtfMRI-nf sessions to upregulate LA activity (Visit1 and 2), as well as a follow-up (Visit3) without rtfMRI-nf. All visits occurred at two-week intervals. At all three visits, the MADRS was administered to participants and serum samples for the quantification of inflammatory cytokines and KP metabolites were obtained. First, the longitudinal changes in the MADRS score and immune markers were tested by linear mixed effect model analysis. Further, utilizing a linear regression model, we investigated the relationship between rtfMRI-nf performance and immune markers. After two sessions of rtfMRI-nf, MADRS scores were significantly reduced (t[58] = −4.07, p = 0.009, d = 0.56). Thirteen participants showed a ≥ 25% reduction in the MADRS score (the partial responder group). There was a significant effect of visit (F[2,58] = 3.17, p = 0.05) for the neuroprotective index, KynA to 3-hydroxykynurenine (3-HK), that was driven by a significant increase in KynA/3-HK between Visit1 and Visit3 (t[58] = 2.50, p = 0.03, d = 0.38). A higher baseline level of KynA/QA (β = 5.23, p = 0.06; rho = 0.49, p = 0.02) was associated with greater ability to upregulate the LA. Finally, for exploratory purposes correlation analyses were performed between the partial responder and the non-responder groups as well as in the whole sample including all KP metabolites and cytokines. In the partial responder group, greater ability to upregulate the LA was correlated with an increase in KynA/QA after rtfMRI-nf (rho = 0.75, p = 0.03). The results are consistent with the possibility that rtfMRI-nf decreases metabolism down the so-called neurotoxic branch of the KP. Nevertheless, non-specific effects cannot be ruled out due to the lack of a sham control. Future, controlled studies are needed to determine whether the increase in KynA/3HK and KynA/QA is specific to rtfMRI-nf or whether it is a non-specific correlate of the resolution of depressive symptoms. Similarly, replication studies are needed to determine whether KynA/QA has clinical utility as a treatment response biomarker. Keywords: fMRI neurofeedback; Amygdala; Blood markers; Inflammation; Kynurenine pathway; Depression | D94: NeuroImage: Clinical | E94: Real-time fMRI neurofeedback amygdala training may influence kynurenine pathway metabolism in major depressive disorder | F94: https://doi.org/10.1016/j.nicl.2021.102559 | G94: 2021 | H94: Tsuchiyagaito, Aki; Smith, Jared L.; El-Sabbagh, Nour; Zotev, Vadim; Misaki, Masaya; Al Zoubi, Obada; Kent Teague, T.; Paulus, Martin P.; Bodurka, Jerzy; Savitz, Jonathan | I94: United States | K94: Science Direct | L94: RQ1 | M94: Excerpt: “real-time functional magnetic resonance imaging neurofeedback (rtfMRI-nf)… non-invasive brain neuromodulation approaches” — Explanation: The article describes rtfMRI-nf as a non-invasive neuromodulation method. It does not discuss invasive or hybrid BCIs. | N94: Excerpt: "Real-time fMRI neurofeedback (rtfMRI-nf) left amygdala (LA) training is a promising intervention for major depressive disorder (MDD)." — Explanation: The study focuses on a specific non-invasive BCI application: real-time fMRI neurofeedback (rtfMRI-nf), which is presented as a promising approach for MDD. | O94: O estudo usa real-time fMRI neurofeedback (rtfMRI-nf), que é uma forma não-invasiva de BCI. | P94: Sim | Q94: Sim | R94: =IF(OR(P94="",Q94=""),"",IF(P94=Q94,"Igual","Diferente")) -> Igual
L95: RQ2 | M95: Excerpt: “Major depressive disorder (MDD) is a devastating neuropsychiatric disease…” — Explanation: The only mental disorder studied is major depressive disorder (MDD). No other conditions (e.g., anxiety, ADHD, schizophrenia) are analyzed. | N95: Excerpt: "Real-time fMRI neurofeedback (rtfMRI-nf) left amygdala (LA) training is a promising intervention for major depressive disorder (MDD)." — Explanation: The article is entirely focused on Major Depressive Disorder (MDD), which it states is a devastating neuropsychiatric disease for which novel treatments are urgently needed. | O95: O artigo foca em major depressive disorder (MDD), incluindo pacientes não medicados. | P95: Sim | Q95: Sim | R95: =IF(OR(P95="",Q95=""),"",IF(P95=Q95,"Igual","Diferente")) -> Igual
L96: RQ3 | M96: Excerpt: “the Montgomery-Åsberg Depression Rating Scale (MADRS)… serum samples for the quantification of cytokines and KP metabolites… linear mixed effect model analysis.” — Explanation: Effectiveness was evaluated using MADRS scores, cytokines, kynurenine pathway metabolites, and mixed-effects statistical modeling. | N96: Excerpt: "After two sessions of rtfMRI-nf, MADRS scores were significantly reduced... There was a significant effect of visit... for the neuroprotective index, KynA to 3-hydroxykynurenine (3-HK), that was driven by a significant increase in KynA/3-HK between Visit1 and Visit3." — Explanation: Effectiveness was measured using a clinical self-report scale, the Montgomery-Asberg Depression Rating Scale (MADRS), and specific blood markers of neuroplasticity and inflammation, primarily the ratio of kynurenine pathway metabolites KynA/3-HK and KynA/QA. | O96: O estudo usa: Montgomery-Åsberg Depression Rating Scale (MADRS) para sintomas clínicos. fMRI BOLD signal da amígdala esquerda. Biomarcadores sanguíneos: citocinas inflamatórias e metabólitos da via do quinurenina (KynA, QA, 3-HK). | P96: Sim | Q96: Sim | R96: =IF(OR(P96="",Q96=""),"",IF(P96=Q96,"Igual","Diferente")) -> Igual
L97: RQ4 | M97: No evidence Found | N97: Excerpt: "In previous studies, we leveraged recent advances in rtfMRI-nf to provide MDD individuals with training to enhance their capacity to upregulate left amygdala (LA) activity in response to the recall of positive autobiographical memories..." — Explanation: rtfMRI-nf is used as a brain-based therapy to provide individuals with information about their brain activity and an opportunity to learn to control it. In this case, the training enhances the capacity to upregulate the left amygdala in response to recalling positive autobiographical memories. | O97: O artigo não trata de memória ou atenção diretamente, mas mostra que o neurofeedback pode modular circuitos emocionais e neuroplasticidade. | P97: Sim | Q97: Sim | R97: =IF(OR(P97="",Q97=""),"",IF(P97=Q97,"Igual","Diferente")) -> Igual
L98: RQ5 | M98: Excerpt: “because of the lack of a sham control group, we are unable to identify a direct causal relationship…”; “sample size… exploratory nature… possibility of both type I and type II errors”; “peripheral concentrations… may not reflect brain levels.” — Explanation: The article acknowledges technical limits (peripheral vs. CNS biomarkers), clinical constraints (small sample, no sham control), and methodological limitations, but does not discuss broad ethical issues. | N98: Excerpt: "Nevertheless, non-specific effects cannot be ruled out due to the lack of a sham control." and "A future study needs to control these variables to exclude potential confounding effects." — Explanation: A major clinical/methodological barrier is the current study's lack of a sham control group, which prevents ruling out non-specific effects. Other confounding clinical variables like BMI, smoking history, and medication history also limit the certainty of the results. | O98: O artigo aponta limitações: Pequeno tamanho da amostra (n=29). Ausência de grupo sham (não dá para excluir efeitos não específicos). Necessidade de replicação. | P98: Sim | Q98: Sim | R98: =IF(OR(P98="",Q98=""),"",IF(P98=Q98,"Igual","Diferente")) -> Igual
L99: RQ6 | M99: No evidence Found | N99: No evidence Found | O99: O artigo não discute segurança ou privacidade dos dados neurais. | P99: Sim | Q99: Sim | R99: =IF(OR(P99="",Q99=""),"",IF(P99=Q99,"Igual","Diferente")) -> Igual
L100: RQ7 | M100: Excerpt: “Future, controlled studies are needed… to evaluate the clinical utility of KynA/QA as a treatment response biomarker.” — Explanation: The only forward-looking trend mentioned is the possibility of using KP metabolites as biomarkers. No discussion of AI integration or personalized neurostimulation exists. | N100: Excerpt: "...the baseline serum concentration of KynA/QA may predict response to rtfMRI-nf LA emotional training. Additional controlled clinical trials with larger sample sizes are necessary... to evaluate the clinical utility of KynA/QA as a treatment response biomarker." — Explanation: The finding that a baseline biomarker (KynA/QA) is associated with the ability to upregulate the amygdala points to the emerging trend of using individual biological markers to predict response and personalize BCI-based treatments. | O100: O artigo não menciona IA, mas mostra tendência de usar biomarcadores (KynA/QA) como preditores de resposta ao neurofeedback. | P100: Sim | Q100: Sim | R100: =IF(OR(P100="",Q100=""),"",IF(P100=Q100,"Igual","Diferente")) -> Igual
...

Sheet Métricas e Desempenho
A1: RQ | B1: Total | C1: ChatGPT – acertos % | D1: Gemini – acertos % | E1: ChatGPT – parciais (%) | F1: Gemini – parciais (%) | G1: ChatGPT – erros % | H1: Gemini – erros % | I1: Concordância
A2: RQ1 | B2: =COUNTIF('Extração'!L:L,A2) -> 115 | C2: =IF(B2=0,"",COUNTIFS('Extração'!P:P,"Sim",'Extração'!L:L,A2)/B2) -> 0.6173913 | D2: =IF(B2=0,"",COUNTIFS('Extração'!Q:Q,"Sim",'Extração'!L:L,A2)/B2) -> 0.73043478 | E2: =IF(B2=0,"",COUNTIFS('Extração'!P:P,"Parcialmente",'Extração'!L:L,A2)/B2) -> 0.034782609 | F2: =IF(B2=0,"",COUNTIFS('Extração'!Q:Q,"Parcialmente",'Extração'!L:L,A2)/B2) -> 0.043478261 | G2: =IF(B2=0,"",COUNTIFS('Extração'!P:P,"Não",'Extração'!L:L,A2)/B2) -> 0.28695652 | H2: =IF(B2=0,"",COUNTIFS('Extração'!Q:Q,"Não",'Extração'!L:L,A2)/B2) -> 0.16521739 | I2: =IF(B2=0,"",COUNTIFS('Extração'!R:R,"Igual",'Extração'!L:L,A2)/B2) -> 0.63478261
A3: RQ2 | B3: =COUNTIF('Extração'!L:L,A3) -> 115 | C3: =IF(B3=0,"",COUNTIFS('Extração'!P:P,"Sim",'Extração'!L:L,A3)/B3) -> 0.64347826 | D3: =IF(B3=0,"",COUNTIFS('Extração'!Q:Q,"Sim",'Extração'!L:L,A3)/B3) -> 0.77391304 | E3: =IF(B3=0,"",COUNTIFS('Extração'!P:P,"Parcialmente",'Extração'!L:L,A3)/B3) -> 0.052173913 | F3: =IF(B3=0,"",COUNTIFS('Extração'!Q:Q,"Parcialmente",'Extração'!L:L,A3)/B3) -> 0.017391304 | G3: =IF(B3=0,"",COUNTIFS('Extração'!P:P,"Não",'Extração'!L:L,A3)/B3) -> 0.24347826 | H3: =IF(B3=0,"",COUNTIFS('Extração'!Q:Q,"Não",'Extração'!L:L,A3)/B3) -> 0.14782609 | I3: =IF(B3=0,"",COUNTIFS('Extração'!R:R,"Igual",'Extração'!L:L,A3)/B3) -> 0.62608696
A4: RQ3 | B4: =COUNTIF('Extração'!L:L,A4) -> 115 | C4: =IF(B4=0,"",COUNTIFS('Extração'!P:P,"Sim",'Extração'!L:L,A4)/B4) -> 0.60869565 | D4: =IF(B4=0,"",COUNTIFS('Extração'!Q:Q,"Sim",'Extração'!L:L,A4)/B4) -> 0.79130435 | E4: =IF(B4=0,"",COUNTIFS('Extração'!P:P,"Parcialmente",'Extração'!L:L,A4)/B4) -> 0.07826087 | F4: =IF(B4=0,"",COUNTIFS('Extração'!Q:Q,"Parcialmente",'Extração'!L:L,A4)/B4) -> 0.052173913 | G4: =IF(B4=0,"",COUNTIFS('Extração'!P:P,"Não",'Extração'!L:L,A4)/B4) -> 0.24347826 | H4: =IF(B4=0,"",COUNTIFS('Extração'!Q:Q,"Não",'Extração'!L:L,A4)/B4) -> 0.086956522 | I4: =IF(B4=0,"",COUNTIFS('Extração'!R:R,"Igual",'Extração'!L:L,A4)/B4) -> 0.54782609
A5: RQ4 | B5: =COUNTIF('Extração'!L:L,A5) -> 115 | C5: =IF(B5=0,"",COUNTIFS('Extração'!P:P,"Sim",'Extração'!L:L,A5)/B5) -> 0.51304348 | D5: =IF(B5=0,"",COUNTIFS('Extração'!Q:Q,"Sim",'Extração'!L:L,A5)/B5) -> 0.70434783 | E5: =IF(B5=0,"",COUNTIFS('Extração'!P:P,"Parcialmente",'Extração'!L:L,A5)/B5) -> 0.086956522 | F5: =IF(B5=0,"",COUNTIFS('Extração'!Q:Q,"Parcialmente",'Extração'!L:L,A5)/B5) -> 0.060869565 | G5: =IF(B5=0,"",COUNTIFS('Extração'!P:P,"Não",'Extração'!L:L,A5)/B5) -> 0.33913043 | H5: =IF(B5=0,"",COUNTIFS('Extração'!Q:Q,"Não",'Extração'!L:L,A5)/B5) -> 0.17391304 | I5: =IF(B5=0,"",COUNTIFS('Extração'!R:R,"Igual",'Extração'!L:L,A5)/B5) -> 0.45217391
A6: RQ5 | B6: =COUNTIF('Extração'!L:L,A6) -> 115 | C6: =IF(B6=0,"",COUNTIFS('Extração'!P:P,"Sim",'Extração'!L:L,A6)/B6) -> 0.67826087 | D6: =IF(B6=0,"",COUNTIFS('Extração'!Q:Q,"Sim",'Extração'!L:L,A6)/B6) -> 0.75652174 | E6: =IF(B6=0,"",COUNTIFS('Extração'!P:P,"Parcialmente",'Extração'!L:L,A6)/B6) -> 0.034782609 | F6: =IF(B6=0,"",COUNTIFS('Extração'!Q:Q,"Parcialmente",'Extração'!L:L,A6)/B6) -> 0.060869565 | G6: =IF(B6=0,"",COUNTIFS('Extração'!P:P,"Não",'Extração'!L:L,A6)/B6) -> 0.2173913 | H6: =IF(B6=0,"",COUNTIFS('Extração'!Q:Q,"Não",'Extração'!L:L,A6)/B6) -> 0.11304348 | I6: =IF(B6=0,"",COUNTIFS('Extração'!R:R,"Igual",'Extração'!L:L,A6)/B6) -> 0.67826087
A7: RQ6 | B7: =COUNTIF('Extração'!L:L,A7) -> 115 | C7: =IF(B7=0,"",COUNTIFS('Extração'!P:P,"Sim",'Extração'!L:L,A7)/B7) -> 0.68695652 | D7: =IF(B7=0,"",COUNTIFS('Extração'!Q:Q,"Sim",'Extração'!L:L,A7)/B7) -> 0.77391304 | E7: =IF(B7=0,"",COUNTIFS('Extração'!P:P,"Parcialmente",'Extração'!L:L,A7)/B7) -> 0.034782609 | F7: =IF(B7=0,"",COUNTIFS('Extração'!Q:Q,"Parcialmente",'Extração'!L:L,A7)/B7) -> 0.017391304 | G7: =IF(B7=0,"",COUNTIFS('Extração'!P:P,"Não",'Extração'!L:L,A7)/B7) -> 0.2173913 | H7: =IF(B7=0,"",COUNTIFS('Extração'!Q:Q,"Não",'Extração'!L:L,A7)/B7) -> 0.13913043 | I7: =IF(B7=0,"",COUNTIFS('Extração'!R:R,"Igual",'Extração'!L:L,A7)/B7) -> 0.8
A8: RQ7 | B8: =COUNTIF('Extração'!L:L,A8) -> 115 | C8: =IF(B8=0,"",COUNTIFS('Extração'!P:P,"Sim",'Extração'!L:L,A8)/B8) -> 0.66086957 | D8: =IF(B8=0,"",COUNTIFS('Extração'!Q:Q,"Sim",'Extração'!L:L,A8)/B8) -> 0.77391304 | E8: =IF(B8=0,"",COUNTIFS('Extração'!P:P,"Parcialmente",'Extração'!L:L,A8)/B8) -> 0.043478261 | F8: =IF(B8=0,"",COUNTIFS('Extração'!Q:Q,"Parcialmente",'Extração'!L:L,A8)/B8) -> 0.043478261 | G8: =IF(B8=0,"",COUNTIFS('Extração'!P:P,"Não",'Extração'!L:L,A8)/B8) -> 0.22608696 | H8: =IF(B8=0,"",COUNTIFS('Extração'!Q:Q,"Não",'Extração'!L:L,A8)/B8) -> 0.11304348 | I8: =IF(B8=0,"",COUNTIFS('Extração'!R:R,"Igual",'Extração'!L:L,A8)/B8) -> 0.68695652
A9: RQ8 | B9: =COUNTIF('Extração'!L:L,A9) -> 115 | C9: =IF(B9=0,"",COUNTIFS('Extração'!P:P,"Sim",'Extração'!L:L,A9)/B9) -> 0.7826087 | D9: =IF(B9=0,"",COUNTIFS('Extração'!Q:Q,"Sim",'Extração'!L:L,A9)/B9) -> 0.84347826 | E9: =IF(B9=0,"",COUNTIFS('Extração'!P:P,"Parcialmente",'Extração'!L:L,A9)/B9) -> 0.0086956522 | F9: =IF(B9=0,"",COUNTIFS('Extração'!Q:Q,"Parcialmente",'Extração'!L:L,A9)/B9) -> 0 | G9: =IF(B9=0,"",COUNTIFS('Extração'!P:P,"Não",'Extração'!L:L,A9)/B9) -> 0.14782609 | H9: =IF(B9=0,"",COUNTIFS('Extração'!Q:Q,"Não",'Extração'!L:L,A9)/B9) -> 0.095652174 | I9: =IF(B9=0,"",COUNTIFS('Extração'!R:R,"Igual",'Extração'!L:L,A9)/B9) -> 0.84347826
A10: RQ9 | B10: =COUNTIF('Extração'!L:L,A10) -> 115 | C10: =IF(B10=0,"",COUNTIFS('Extração'!P:P,"Sim",'Extração'!L:L,A10)/B10) -> 0.64347826 | D10: =IF(B10=0,"",COUNTIFS('Extração'!Q:Q,"Sim",'Extração'!L:L,A10)/B10) -> 0.69565217 | E10: =IF(B10=0,"",COUNTIFS('Extração'!P:P,"Parcialmente",'Extração'!L:L,A10)/B10) -> 0.060869565 | F10: =IF(B10=0,"",COUNTIFS('Extração'!Q:Q,"Parcialmente",'Extração'!L:L,A10)/B10) -> 0.052173913 | G10: =IF(B10=0,"",COUNTIFS('Extração'!P:P,"Não",'Extração'!L:L,A10)/B10) -> 0.22608696 | H10: =IF(B10=0,"",COUNTIFS('Extração'!Q:Q,"Não",'Extração'!L:L,A10)/B10) -> 0.1826087 | I10: =IF(B10=0,"",COUNTIFS('Extração'!R:R,"Igual",'Extração'!L:L,A10)/B10) -> 0.50434783
B11: =COUNTIF('Extração'!L:L,A11) -> 0 | C11: =IF(B11=0,"",COUNTIFS('Extração'!P:P,"Sim",'Extração'!L:L,A11)/B11) | D11: =IF(B11=0,"",COUNTIFS('Extração'!Q:Q,"Sim",'Extração'!L:L,A11)/B11) | E11: =IF(B11=0,"",COUNTIFS('Extração'!P:P,"Parcialmente",'Extração'!L:L,A11)/B11) | F11: =IF(B11=0,"",COUNTIFS('Extração'!Q:Q,"Parcialmente",'Extração'!L:L,A11)/B11) | G11: =IF(B11=0,"",COUNTIFS('Extração'!P:P,"Não",'Extração'!L:L,A11)/B11) | H11: =IF(B11=0,"",COUNTIFS('Extração'!Q:Q,"Não",'Extração'!L:L,A11)/B11) | I11: =IF(B11=0,"",COUNTIFS('Extração'!R:R,"Igual",'Extração'!L:L,A11)/B11)
B12: =COUNTIF('Extração'!L:L,A12) -> 0 | C12: =IF(B12=0,"",COUNTIFS('Extração'!P:P,"Sim",'Extração'!L:L,A12)/B12) | D12: =IF(B12=0,"",COUNTIFS('Extração'!Q:Q,"Sim",'Extração'!L:L,A12)/B12) | E12: =IF(B12=0,"",COUNTIFS('Extração'!P:P,"Parcialmente",'Extração'!L:L,A12)/B12) | F12: =IF(B12=0,"",COUNTIFS('Extração'!Q:Q,"Parcialmente",'Extração'!L:L,A12)/B12) | G12: =IF(B12=0,"",COUNTIFS('Extração'!P:P,"Não",'Extração'!L:L,A12)/B12) | H12: =IF(B12=0,"",COUNTIFS('Extração'!Q:Q,"Não",'Extração'!L:L,A12)/B12) | I12: =IF(B12=0,"",COUNTIFS('Extração'!R:R,"Igual",'Extração'!L:L,A12)/B12)
B13: =COUNTIF('Extração'!L:L,A13) -> 0 | C13: =IF(B13=0,"",COUNTIFS('Extração'!P:P,"Sim",'Extração'!L:L,A13)/B13) | D13: =IF(B13=0,"",COUNTIFS('Extração'!Q:Q,"Sim",'Extração'!L:L,A13)/B13) | E13: =IF(B13=0,"",COUNTIFS('Extração'!P:P,"Parcialmente",'Extração'!L:L,A13)/B13) | F13: =IF(B13=0,"",COUNTIFS('Extração'!Q:Q,"Parcialmente",'Extração'!L:L,A13)/B13) | G13: =IF(B13=0,"",COUNTIFS('Extração'!P:P,"Não",'Extração'!L:L,A13)/B13) | H13: =IF(B13=0,"",COUNTIFS('Extração'!Q:Q,"Não",'Extração'!L:L,A13)/B13) | I13: =IF(B13=0,"",COUNTIFS('Extração'!R:R,"Igual",'Extração'!L:L,A13)/B13)
B14: =COUNTIF('Extração'!L:L,A14) -> 0 | C14: =IF(B14=0,"",COUNTIFS('Extração'!P:P,"Sim",'Extração'!L:L,A14)/B14) | D14: =IF(B14=0,"",COUNTIFS('Extração'!Q:Q,"Sim",'Extração'!L:L,A14)/B14) | E14: =IF(B14=0,"",COUNTIFS('Extração'!P:P,"Parcialmente",'Extração'!L:L,A14)/B14) | F14: =IF(B14=0,"",COUNTIFS('Extração'!Q:Q,"Parcialmente",'Extração'!L:L,A14)/B14) | G14: =IF(B14=0,"",COUNTIFS('Extração'!P:P,"Não",'Extração'!L:L,A14)/B14) | H14: =IF(B14=0,"",COUNTIFS('Extração'!Q:Q,"Não",'Extração'!L:L,A14)/B14) | I14: =IF(B14=0,"",COUNTIFS('Extração'!R:R,"Igual",'Extração'!L:L,A14)/B14)
B15: =COUNTIF('Extração'!L:L,A15) -> 0 | C15: =IF(B15=0,"",COUNTIFS('Extração'!P:P,"Sim",'Extração'!L:L,A15)/B15) | D15: =IF(B15=0,"",COUNTIFS('Extração'!Q:Q,"Sim",'Extração'!L:L,A15)/B15) | E15: =IF(B15=0,"",COUNTIFS('Extração'!P:P,"Parcialmente",'Extração'!L:L,A15)/B15) | F15: =IF(B15=0,"",COUNTIFS('Extração'!Q:Q,"Parcialmente",'Extração'!L:L,A15)/B15) | G15: =IF(B15=0,"",COUNTIFS('Extração'!P:P,"Não",'Extração'!L:L,A15)/B15) | H15: =IF(B15=0,"",COUNTIFS('Extração'!Q:Q,"Não",'Extração'!L:L,A15)/B15) | I15: =IF(B15=0,"",COUNTIFS('Extração'!R:R,"Igual",'Extração'!L:L,A15)/B15)
B16: =COUNTIF('Extração'!L:L,A16) -> 0 | C16: =IF(B16=0,"",COUNTIFS('Extração'!P:P,"Sim",'Extração'!L:L,A16)/B16) | D16: =IF(B16=0,"",COUNTIFS('Extração'!Q:Q,"Sim",'Extração'!L:L,A16)/B16) | E16: =IF(B16=0,"",COUNTIFS('Extração'!P:P,"Parcialmente",'Extração'!L:L,A16)/B16) | F16: =IF(B16=0,"",COUNTIFS('Extração'!Q:Q,"Parcialmente",'Extração'!L:L,A16)/B16) | G16: =IF(B16=0,"",COUNTIFS('Extração'!P:P,"Não",'Extração'!L:L,A16)/B16) | H16: =IF(B16=0,"",COUNTIFS('Extração'!Q:Q,"Não",'Extração'!L:L,A16)/B16) | I16: =IF(B16=0,"",COUNTIFS('Extração'!R:R,"Igual",'Extração'!L:L,A16)/B16)
B17: =COUNTIF('Extração'!L:L,A17) -> 0 | C17: =IF(B17=0,"",COUNTIFS('Extração'!P:P,"Sim",'Extração'!L:L,A17)/B17) | D17: =IF(B17=0,"",COUNTIFS('Extração'!Q:Q,"Sim",'Extração'!L:L,A17)/B17) | E17: =IF(B17=0,"",COUNTIFS('Extração'!P:P,"Parcialmente",'Extração'!L:L,A17)/B17) | F17: =IF(B17=0,"",COUNTIFS('Extração'!Q:Q,"Parcialmente",'Extração'!L:L,A17)/B17) | G17: =IF(B17=0,"",COUNTIFS('Extração'!P:P,"Não",'Extração'!L:L,A17)/B17) | H17: =IF(B17=0,"",COUNTIFS('Extração'!Q:Q,"Não",'Extração'!L:L,A17)/B17) | I17: =IF(B17=0,"",COUNTIFS('Extração'!R:R,"Igual",'Extração'!L:L,A17)/B17)
B18: =COUNTIF('Extração'!L:L,A18) -> 0 | C18: =IF(B18=0,"",COUNTIFS('Extração'!P:P,"Sim",'Extração'!L:L,A18)/B18) | D18: =IF(B18=0,"",COUNTIFS('Extração'!Q:Q,"Sim",'Extração'!L:L,A18)/B18) | E18: =IF(B18=0,"",COUNTIFS('Extração'!P:P,"Parcialmente",'Extração'!L:L,A18)/B18) | F18: =IF(B18=0,"",COUNTIFS('Extração'!Q:Q,"Parcialmente",'Extração'!L:L,A18)/B18) | G18: =IF(B18=0,"",COUNTIFS('Extração'!P:P,"Não",'Extração'!L:L,A18)/B18) | H18: =IF(B18=0,"",COUNTIFS('Extração'!Q:Q,"Não",'Extração'!L:L,A18)/B18) | I18: =IF(B18=0,"",COUNTIFS('Extração'!R:R,"Igual",'Extração'!L:L,A18)/B18)
B19: =COUNTIF('Extração'!L:L,A19) -> 0 | C19: =IF(B19=0,"",COUNTIFS('Extração'!P:P,"Sim",'Extração'!L:L,A19)/B19) | D19: =IF(B19=0,"",COUNTIFS('Extração'!Q:Q,"Sim",'Extração'!L:L,A19)/B19) | E19: =IF(B19=0,"",COUNTIFS('Extração'!P:P,"Parcialmente",'Extração'!L:L,A19)/B19) | F19: =IF(B19=0,"",COUNTIFS('Extração'!Q:Q,"Parcialmente",'Extração'!L:L,A19)/B19) | G19: =IF(B19=0,"",COUNTIFS('Extração'!P:P,"Não",'Extração'!L:L,A19)/B19) | H19: =IF(B19=0,"",COUNTIFS('Extração'!Q:Q,"Não",'Extração'!L:L,A19)/B19) | I19: =IF(B19=0,"",COUNTIFS('Extração'!R:R,"Igual",'Extração'!L:L,A19)/B19)
B20: =COUNTIF('Extração'!L:L,A20) -> 0 | C20: =IF(B20=0,"",COUNTIFS('Extração'!P:P,"Sim",'Extração'!L:L,A20)/B20) | D20: =IF(B20=0,"",COUNTIFS('Extração'!Q:Q,"Sim",'Extração'!L:L,A20)/B20) | E20: =IF(B20=0,"",COUNTIFS('Extração'!P:P,"Parcialmente",'Extração'!L:L,A20)/B20) | F20: =IF(B20=0,"",COUNTIFS('Extração'!Q:Q,"Parcialmente",'Extração'!L:L,A20)/B20) | G20: =IF(B20=0,"",COUNTIFS('Extração'!P:P,"Não",'Extração'!L:L,A20)/B20) | H20: =IF(B20=0,"",COUNTIFS('Extração'!Q:Q,"Não",'Extração'!L:L,A20)/B20) | I20: =IF(B20=0,"",COUNTIFS('Extração'!R:R,"Igual",'Extração'!L:L,A20)/B20)
B21: =COUNTIF('Extração'!L:L,A21) -> 0 | C21: =IF(B21=0,"",COUNTIFS('Extração'!P:P,"Sim",'Extração'!L:L,A21)/B21) | D21: =IF(B21=0,"",COUNTIFS('Extração'!Q:Q,"Sim",'Extração'!L:L,A21)/B21) | E21: =IF(B21=0,"",COUNTIFS('Extração'!P:P,"Parcialmente",'Extração'!L:L,A21)/B21) | F21: =IF(B21=0,"",COUNTIFS('Extração'!Q:Q,"Parcialmente",'Extração'!L:L,A21)/B21) | G21: =IF(B21=0,"",COUNTIFS('Extração'!P:P,"Não",'Extração'!L:L,A21)/B21) | H21: =IF(B21=0,"",COUNTIFS('Extração'!Q:Q,"Não",'Extração'!L:L,A21)/B21) | I21: =IF(B21=0,"",COUNTIFS('Extração'!R:R,"Igual",'Extração'!L:L,A21)/B21)
B22: =COUNTIF('Extração'!L:L,A22) -> 0 | C22: =IF(B22=0,"",COUNTIFS('Extração'!P:P,"Sim",'Extração'!L:L,A22)/B22) | D22: =IF(B22=0,"",COUNTIFS('Extração'!Q:Q,"Sim",'Extração'!L:L,A22)/B22) | E22: =IF(B22=0,"",COUNTIFS('Extração'!P:P,"Parcialmente",'Extração'!L:L,A22)/B22) | F22: =IF(B22=0,"",COUNTIFS('Extração'!Q:Q,"Parcialmente",'Extração'!L:L,A22)/B22) | G22: =IF(B22=0,"",COUNTIFS('Extração'!P:P,"Não",'Extração'!L:L,A22)/B22) | H22: =IF(B22=0,"",COUNTIFS('Extração'!Q:Q,"Não",'Extração'!L:L,A22)/B22) | I22: =IF(B22=0,"",COUNTIFS('Extração'!R:R,"Igual",'Extração'!L:L,A22)/B22)
... B1000: =COUNTIF('Extração'!L:L,A1000) -> 0 | C1000: =IF(B1000=0,"",COUNTIFS('Extração'!P:P,"Sim",'Extração'!L:L,A1000)/B1000) | D1000: =IF(B1000=0,"",COUNTIFS('Extração'!Q:Q,"Sim",'Extração'!L:L,A1000)/B1000) | E1000: =IF(B1000=0,"",COUNTIFS('Extração'!P:P,"Parcialmente",'Extração'!L:L,A1000)/B1000) | F1000: =IF(B1000=0,"",COUNTIFS('Extração'!Q:Q,"Parcialmente",'Extração'!L:L,A1000)/B1000) | G1000: =IF(B1000=0,"",COUNTIFS('Extração'!P:P,"Não",'Extração'!L:L,A1000)/B1000) | H1000: =IF(B1000=0,"",COUNTIFS('Extração'!Q:Q,"Não",'Extração'!L:L,A1000)/B1000) | I1000: =IF(B1000=0,"",COUNTIFS('Extração'!R:R,"Igual",'Extração'!L:L,A1000)/B1000)

Sheet Planilhas pro artigo
B1: Table 1: List of selected studies. | Q1: PLANILHAS DAS RESPOSTAS - PREENCHER ESSE!!! | V1: NAO RESPONDER ESSAS
B2: ID | C2: Ano | D2: Base | E2: Tipo | F2: Title | G2: Authors | H2: Country | I2: Citation | L2: ID | M2: Content | N2: Citations | O2: Total | Q2: RQ ID | R2: Type | S2: Citations | T2: Total | V2: RQ ID | W2: Citations | X2: Total
B3: S1 | C3: 2020 | D3: PubMed | E3: Journal | F3: Effects of working memory training on EEG, cognitive performance, and self-report indices potentially relevant for social anxiety | G3: Xin Zhao, Chen Dang, Joseph H R Maes | H3: China and Netherlands | I3: (Xin Zhao et al, 2020) | L3: RQ1 | M3: <<What types of Brain-Computer Interfaces (invasive, non-invasive, hybrid) have been most used in mental health applications?>> | N3: ES01, ES | Q3: RQ1 | R3: Invasive | T3: 0 | V3: RQ1 | W3: S2, S3, S4, S5, S6, S7, S8, S10, S11, S12, S13, S14, S16, S17,S19, S20, S21, S22, s27, s28, s29, s30, s31, s32, s34, s36, s37, s38, s39, s40, s41, s42, s43, s44, s45, s46, s47, s48, s49 | X3: 39
